Workbook

Sheet TRACKER
F2: CATEGORY | V2: GRAPHIC STATUS | AI2: DATASET STATUS
E3: TOTAL Charts | F3: {=TRANSPOSE(Validation!A2:A6)} -> Infographic WITHOUT Data | G3: Infographic WITH Data | H3: Chart to recreate | I3: Chart for Direct Use | J3: Maps to recreate | K3: Uncategorized | N3: {=TRANSPOSE(Validation!I2:I6)} -> Pending | O3: In process | P3: Not supported by pipeline | Q3: Ready | R3: Deleted | T3: Unclear | V3: {=TRANSPOSE(Validation!I2:I9)} -> #VALUE! | Z3: Unclear | AC3: {=TRANSPOSE(Validation!I2:I9)} -> #VALUE! | AG3: Unclear | AI3: {=TRANSPOSE(Validation!I2:I9)} -> #VALUE! | AM3: Unclear
B4: Module1 | C4: =_xlfn.CONCAT($B4,"!B3:B100") -> Module1!B3:B100 | D4: =_xlfn.CONCAT($B4,"!N3:N100") -> Module1!N3:N100 | E4: =COUNTA(INDIRECT(C4)) -> 35 | F4: =COUNTIF(INDIRECT($D4),F$3) -> 0 | G4: =COUNTIF(INDIRECT($D4),G$3) -> 2 | H4: =COUNTIF(INDIRECT($D4),H$3) -> 25 | I4: =COUNTIF(INDIRECT($D4),I$3) -> 6 | J4: =COUNTIF(INDIRECT($D4),J$3) -> 2 | K4: =E4-SUM(F4:J4) -> 0 | M4: =_xlfn.CONCAT($B4,"!I3:I100") -> Module1!I3:I100 | N4: =COUNTIF(INDIRECT($M4),N$3) -> 0 | O4: =COUNTIF(INDIRECT($M4),O$3) -> 0 | P4: =COUNTIF(INDIRECT($M4),P$3) -> 0 | Q4: =COUNTIF(INDIRECT($M4),Q$3) -> 0 | T4: =(E4-SUM(N4:Q4)) -> 35 | V4: =N4/$E4 -> 0 | W4: =O4/$E4 -> 0 | X4: =P4/$E4 -> 0 | Y4: =Q4/$E4 -> 0 | Z4: =T4/$E4 -> 1 | AB4: =_xlfn.CONCAT($B4,"!p3:p100") -> Module1!p3:p100 | AC4: =COUNTIF(INDIRECT($AB4),AC$3) -> 0 | AD4: =COUNTIF(INDIRECT($AB4),AD$3) -> 0 | AE4: =COUNTIF(INDIRECT($AB4),AE$3) -> 0 | AF4: =COUNTIF(INDIRECT($AB4),AF$3) -> 0 | AG4: =(H4-SUM(AC4:AF4)) -> 25 | AI4: =AC4/$H4 -> 0 | AJ4: =AD4/$H4 -> 0 | AK4: =AE4/$H4 -> 0 | AL4: =AF4/$H4 -> 0 | AM4: =AG4/$H4 -> 1
B5: Module2 | C5: =_xlfn.CONCAT($B5,"!B3:B100") -> Module2!B3:B100 | D5: =_xlfn.CONCAT($B5,"!N3:N100") -> Module2!N3:N100 | E5: =COUNTA(INDIRECT(C5)) -> 35 | F5: =COUNTIF(INDIRECT($D5),F$3) -> 0 | G5: =COUNTIF(INDIRECT($D5),G$3) -> 0 | H5: =COUNTIF(INDIRECT($D5),H$3) -> 25 | I5: =COUNTIF(INDIRECT($D5),I$3) -> 7 | J5: =COUNTIF(INDIRECT($D5),J$3) -> 1 | K5: =E5-SUM(F5:J5) -> 2 | M5: =_xlfn.CONCAT($B5,"!I3:I100") -> Module2!I3:I100 | N5: =COUNTIF(INDIRECT($M5),N$3) -> 0 | O5: =COUNTIF(INDIRECT($M5),O$3) -> 0 | P5: =COUNTIF(INDIRECT($M5),P$3) -> 0 | Q5: =COUNTIF(INDIRECT($M5),Q$3) -> 0 | T5: =(E5-SUM(N5:Q5)) -> 35 | V5: =N5/$E5 -> 0 | W5: =O5/$E5 -> 0 | X5: =P5/$E5 -> 0 | Y5: =Q5/$E5 -> 0 | Z5: =T5/$E5 -> 1 | AB5: =_xlfn.CONCAT($B5,"!p3:p100") -> Module2!p3:p100 | AC5: =COUNTIF(INDIRECT($AB5),AC$3) -> 0 | AD5: =COUNTIF(INDIRECT($AB5),AD$3) -> 0 | AE5: =COUNTIF(INDIRECT($AB5),AE$3) -> 0 | AF5: =COUNTIF(INDIRECT($AB5),AF$3) -> 0 | AG5: =(H5-SUM(AC5:AF5)) -> 25 | AI5: =AC5/$H5 -> 0 | AJ5: =AD5/$H5 -> 0 | AK5: =AE5/$H5 -> 0 | AL5: =AF5/$H5 -> 0 | AM5: =AG5/$H5 -> 1
B6: Module3 | C6: =_xlfn.CONCAT($B6,"!B3:B100") -> Module3!B3:B100 | D6: =_xlfn.CONCAT($B6,"!N3:N100") -> Module3!N3:N100 | E6: =COUNTA(INDIRECT(C6)) -> 12 | F6: =COUNTIF(INDIRECT($D6),F$3) -> 0 | G6: =COUNTIF(INDIRECT($D6),G$3) -> 0 | H6: =COUNTIF(INDIRECT($D6),H$3) -> 10 | I6: =COUNTIF(INDIRECT($D6),I$3) -> 2 | J6: =COUNTIF(INDIRECT($D6),J$3) -> 0 | K6: =E6-SUM(F6:J6) -> 0 | M6: =_xlfn.CONCAT($B6,"!I3:I100") -> Module3!I3:I100 | N6: =COUNTIF(INDIRECT($M6),N$3) -> 0 | O6: =COUNTIF(INDIRECT($M6),O$3) -> 0 | P6: =COUNTIF(INDIRECT($M6),P$3) -> 0 | Q6: =COUNTIF(INDIRECT($M6),Q$3) -> 0 | T6: =(E6-SUM(N6:Q6)) -> 12 | V6: =N6/$E6 -> 0 | W6: =O6/$E6 -> 0 | X6: =P6/$E6 -> 0 | Y6: =Q6/$E6 -> 0 | Z6: =T6/$E6 -> 1 | AB6: =_xlfn.CONCAT($B6,"!p3:p100") -> Module3!p3:p100 | AC6: =COUNTIF(INDIRECT($AB6),AC$3) -> 0 | AD6: =COUNTIF(INDIRECT($AB6),AD$3) -> 0 | AE6: =COUNTIF(INDIRECT($AB6),AE$3) -> 0 | AF6: =COUNTIF(INDIRECT($AB6),AF$3) -> 0 | AG6: =(H6-SUM(AC6:AF6)) -> 10 | AI6: =AC6/$H6 -> 0 | AJ6: =AD6/$H6 -> 0 | AK6: =AE6/$H6 -> 0 | AL6: =AF6/$H6 -> 0 | AM6: =AG6/$H6 -> 1
B7: Module4 | C7: =_xlfn.CONCAT($B7,"!B3:B100") -> Module4!B3:B100 | D7: =_xlfn.CONCAT($B7,"!N3:N100") -> Module4!N3:N100 | E7: =COUNTA(INDIRECT(C7)) -> 14 | F7: =COUNTIF(INDIRECT($D7),F$3) -> 0 | G7: =COUNTIF(INDIRECT($D7),G$3) -> 0 | H7: =COUNTIF(INDIRECT($D7),H$3) -> 13 | I7: =COUNTIF(INDIRECT($D7),I$3) -> 1 | J7: =COUNTIF(INDIRECT($D7),J$3) -> 0 | K7: =E7-SUM(F7:J7) -> 0 | M7: =_xlfn.CONCAT($B7,"!I3:I100") -> Module4!I3:I100 | N7: =COUNTIF(INDIRECT($M7),N$3) -> 0 | O7: =COUNTIF(INDIRECT($M7),O$3) -> 0 | P7: =COUNTIF(INDIRECT($M7),P$3) -> 0 | Q7: =COUNTIF(INDIRECT($M7),Q$3) -> 0 | T7: =(E7-SUM(N7:Q7)) -> 14 | V7: =N7/$E7 -> 0 | W7: =O7/$E7 -> 0 | X7: =P7/$E7 -> 0 | Y7: =Q7/$E7 -> 0 | Z7: =T7/$E7 -> 1 | AB7: =_xlfn.CONCAT($B7,"!p3:p100") -> Module4!p3:p100 | AC7: =COUNTIF(INDIRECT($AB7),AC$3) -> 0 | AD7: =COUNTIF(INDIRECT($AB7),AD$3) -> 0 | AE7: =COUNTIF(INDIRECT($AB7),AE$3) -> 0 | AF7: =COUNTIF(INDIRECT($AB7),AF$3) -> 0 | AG7: =(H7-SUM(AC7:AF7)) -> 13 | AI7: =AC7/$H7 -> 0 | AJ7: =AD7/$H7 -> 0 | AK7: =AE7/$H7 -> 0 | AL7: =AF7/$H7 -> 0 | AM7: =AG7/$H7 -> 1
B8: Module5 | C8: =_xlfn.CONCAT($B8,"!B3:B100") -> Module5!B3:B100 | D8: =_xlfn.CONCAT($B8,"!N3:N100") -> Module5!N3:N100 | E8: =COUNTA(INDIRECT(C8)) -> 4 | F8: =COUNTIF(INDIRECT($D8),F$3) -> 0 | G8: =COUNTIF(INDIRECT($D8),G$3) -> 0 | H8: =COUNTIF(INDIRECT($D8),H$3) -> 4 | I8: =COUNTIF(INDIRECT($D8),I$3) -> 0 | J8: =COUNTIF(INDIRECT($D8),J$3) -> 0 | K8: =E8-SUM(F8:J8) -> 0 | M8: =_xlfn.CONCAT($B8,"!I3:I100") -> Module5!I3:I100 | N8: =COUNTIF(INDIRECT($M8),N$3) -> 0 | O8: =COUNTIF(INDIRECT($M8),O$3) -> 0 | P8: =COUNTIF(INDIRECT($M8),P$3) -> 0 | Q8: =COUNTIF(INDIRECT($M8),Q$3) -> 0 | T8: =(E8-SUM(N8:Q8)) -> 4 | V8: =N8/$E8 -> 0 | W8: =O8/$E8 -> 0 | X8: =P8/$E8 -> 0 | Y8: =Q8/$E8 -> 0 | Z8: =T8/$E8 -> 1 | AB8: =_xlfn.CONCAT($B8,"!p3:p100") -> Module5!p3:p100 | AC8: =COUNTIF(INDIRECT($AB8),AC$3) -> 0 | AD8: =COUNTIF(INDIRECT($AB8),AD$3) -> 0 | AE8: =COUNTIF(INDIRECT($AB8),AE$3) -> 0 | AF8: =COUNTIF(INDIRECT($AB8),AF$3) -> 0 | AG8: =(H8-SUM(AC8:AF8)) -> 4 | AI8: =AC8/$H8 -> 0 | AJ8: =AD8/$H8 -> 0 | AK8: =AE8/$H8 -> 0 | AL8: =AF8/$H8 -> 0 | AM8: =AG8/$H8 -> 1
B9: Module6 | C9: =_xlfn.CONCAT($B9,"!B3:B100") -> Module6!B3:B100 | D9: =_xlfn.CONCAT($B9,"!N3:N100") -> Module6!N3:N100 | E9: =COUNTA(INDIRECT(C9)) -> 20 | F9: =COUNTIF(INDIRECT($D9),F$3) -> 0 | G9: =COUNTIF(INDIRECT($D9),G$3) -> 0 | H9: =COUNTIF(INDIRECT($D9),H$3) -> 20 | I9: =COUNTIF(INDIRECT($D9),I$3) -> 0 | J9: =COUNTIF(INDIRECT($D9),J$3) -> 0 | K9: =E9-SUM(F9:J9) -> 0 | M9: =_xlfn.CONCAT($B9,"!I3:I100") -> Module6!I3:I100 | N9: =COUNTIF(INDIRECT($M9),N$3) -> 0 | O9: =COUNTIF(INDIRECT($M9),O$3) -> 0 | P9: =COUNTIF(INDIRECT($M9),P$3) -> 0 | Q9: =COUNTIF(INDIRECT($M9),Q$3) -> 0 | T9: =(E9-SUM(N9:Q9)) -> 20 | V9: =N9/$E9 -> 0 | W9: =O9/$E9 -> 0 | X9: =P9/$E9 -> 0 | Y9: =Q9/$E9 -> 0 | Z9: =T9/$E9 -> 1 | AB9: =_xlfn.CONCAT($B9,"!p3:p100") -> Module6!p3:p100 | AC9: =COUNTIF(INDIRECT($AB9),AC$3) -> 0 | AD9: =COUNTIF(INDIRECT($AB9),AD$3) -> 0 | AE9: =COUNTIF(INDIRECT($AB9),AE$3) -> 0 | AF9: =COUNTIF(INDIRECT($AB9),AF$3) -> 0 | AG9: =(H9-SUM(AC9:AF9)) -> 20 | AI9: =AC9/$H9 -> 0 | AJ9: =AD9/$H9 -> 0 | AK9: =AE9/$H9 -> 0 | AL9: =AF9/$H9 -> 0 | AM9: =AG9/$H9 -> 1
B10: Module7 | C10: =_xlfn.CONCAT($B10,"!B3:B100") -> Module7!B3:B100 | D10: =_xlfn.CONCAT($B10,"!N3:N100") -> Module7!N3:N100 | E10: =COUNTA(INDIRECT(C10)) -> 9 | F10: =COUNTIF(INDIRECT($D10),F$3) -> 2 | G10: =COUNTIF(INDIRECT($D10),G$3) -> 0 | H10: =COUNTIF(INDIRECT($D10),H$3) -> 5 | I10: =COUNTIF(INDIRECT($D10),I$3) -> 0 | J10: =COUNTIF(INDIRECT($D10),J$3) -> 0 | K10: =E10-SUM(F10:J10) -> 2 | M10: =_xlfn.CONCAT($B10,"!I3:I100") -> Module7!I3:I100 | N10: =COUNTIF(INDIRECT($M10),N$3) -> 0 | O10: =COUNTIF(INDIRECT($M10),O$3) -> 0 | P10: =COUNTIF(INDIRECT($M10),P$3) -> 0 | Q10: =COUNTIF(INDIRECT($M10),Q$3) -> 0 | T10: =(E10-SUM(N10:Q10)) -> 9 | V10: =N10/$E10 -> 0 | W10: =O10/$E10 -> 0 | X10: =P10/$E10 -> 0 | Y10: =Q10/$E10 -> 0 | Z10: =T10/$E10 -> 1 | AB10: =_xlfn.CONCAT($B10,"!p3:p100") -> Module7!p3:p100 | AC10: =COUNTIF(INDIRECT($AB10),AC$3) -> 0 | AD10: =COUNTIF(INDIRECT($AB10),AD$3) -> 0 | AE10: =COUNTIF(INDIRECT($AB10),AE$3) -> 0 | AF10: =COUNTIF(INDIRECT($AB10),AF$3) -> 0 | AG10: =(H10-SUM(AC10:AF10)) -> 5 | AI10: =AC10/$H10 -> 0 | AJ10: =AD10/$H10 -> 0 | AK10: =AE10/$H10 -> 0 | AL10: =AF10/$H10 -> 0 | AM10: =AG10/$H10 -> 1
B11: Module8 | C11: =_xlfn.CONCAT($B11,"!B3:B100") -> Module8!B3:B100 | D11: =_xlfn.CONCAT($B11,"!N3:N100") -> Module8!N3:N100 | E11: =COUNTA(INDIRECT(C11)) -> 26 | F11: =COUNTIF(INDIRECT($D11),F$3) -> 0 | G11: =COUNTIF(INDIRECT($D11),G$3) -> 1 | H11: =COUNTIF(INDIRECT($D11),H$3) -> 24 | I11: =COUNTIF(INDIRECT($D11),I$3) -> 1 | J11: =COUNTIF(INDIRECT($D11),J$3) -> 0 | K11: =E11-SUM(F11:J11) -> 0 | M11: =_xlfn.CONCAT($B11,"!I3:I100") -> Module8!I3:I100 | N11: =COUNTIF(INDIRECT($M11),N$3) -> 0 | O11: =COUNTIF(INDIRECT($M11),O$3) -> 0 | P11: =COUNTIF(INDIRECT($M11),P$3) -> 0 | Q11: =COUNTIF(INDIRECT($M11),Q$3) -> 0 | T11: =(E11-SUM(N11:Q11)) -> 26 | V11: =N11/$E11 -> 0 | W11: =O11/$E11 -> 0 | X11: =P11/$E11 -> 0 | Y11: =Q11/$E11 -> 0 | Z11: =T11/$E11 -> 1 | AB11: =_xlfn.CONCAT($B11,"!p3:p100") -> Module8!p3:p100 | AC11: =COUNTIF(INDIRECT($AB11),AC$3) -> 0 | AD11: =COUNTIF(INDIRECT($AB11),AD$3) -> 0 | AE11: =COUNTIF(INDIRECT($AB11),AE$3) -> 0 | AF11: =COUNTIF(INDIRECT($AB11),AF$3) -> 0 | AG11: =(H11-SUM(AC11:AF11)) -> 24 | AI11: =AC11/$H11 -> 0 | AJ11: =AD11/$H11 -> 0 | AK11: =AE11/$H11 -> 0 | AL11: =AF11/$H11 -> 0 | AM11: =AG11/$H11 -> 1
B12: TOTAL | E12: =SUM(E4:E11) -> 155 | F12: =SUM(F4:F11) -> 2 | G12: =SUM(G4:G11) -> 3 | H12: =SUM(H4:H11) -> 126 | I12: =SUM(I4:I11) -> 17 | J12: =SUM(J4:J11) -> 3 | K12: =E12-SUM(F12:J12) -> 4 | N12: =SUM(N4:N11) -> 0 | O12: =SUM(O4:O11) -> 0 | P12: =SUM(P4:P11) -> 0 | Q12: =SUM(Q4:Q11) -> 0 | T12: =(E12-SUM(N12:Q12)) -> 155 | V12: =N12/$E12 -> 0 | W12: =O12/$E12 -> 0 | X12: =P12/$E12 -> 0 | Y12: =Q12/$E12 -> 0 | Z12: =T12/$E12 -> 1 | AC12: =SUM(AC4:AC11) -> 0 | AD12: =SUM(AD4:AD11) -> 0 | AE12: =SUM(AE4:AE11) -> 0 | AF12: =SUM(AF4:AF11) -> 0 | AG12: =(H12-SUM(AC12:AF12)) -> 126 | AI12: =AC12/$H12 -> 0 | AJ12: =AD12/$H12 -> 0 | AK12: =AE12/$H12 -> 0 | AL12: =AF12/$H12 -> 0 | AM12: =AG12/$H12 -> 1
F15: DATASET STATUS | V15: DATASET STATUS
B16: Lead | E16: TOTAL Charts | F16: {=TRANSPOSE(Validation!J2:J7)} -> Pending | G16: In process | H16: Review pending | I16: Needs fixing | J16: Ready | K16: Deleted | V16: {=TRANSPOSE(Validation!I2:I5)} -> Pending | W16: In process | X16: Not supported by pipeline | Y16: Ready
B17: Gabriela | E17: =COUNTIF(ChartsM1[Lead],TRACKER!B17)+COUNTIF(ChartsM2[Lead],TRACKER!B17)++COUNTIF(ChartsM3[Lead],TRACKER!B17)+COUNTIF(ChartsM4[Lead],TRACKER!B17)+COUNTIF(ChartsM5[Lead],TRACKER!B17)+COUNTIF(ChartsM6[Lead],TRACKER!B17)+COUNTIF(ChartsM7[Lead],TRACKER!B17)+COUNTIF(ChartsM8[Lead],TRACKER!B17) -> 35 | F17: =(COUNTIFS(ChartsM1[Lead],TRACKER!$B17,ChartsM1[Dataset Status],TRACKER!$F$16) +COUNTIFS(ChartsM2[Lead],TRACKER!$B17,ChartsM2[Dataset Status],TRACKER!$F$16) +COUNTIFS(ChartsM3[Lead],TRACKER!$B17,ChartsM3[Dataset Status],TRACKER!$F$16) +COUNTIFS(ChartsM4[Lead],TRACKER!$B17,ChartsM4[Dataset Status],TRACKER!$F$16) +COUNTIFS(ChartsM5[Lead],TRACKER!$B17,ChartsM5[Dataset Status],TRACKER!$F$16) +COUNTIFS(ChartsM6[Lead],TRACKER!$B17,ChartsM6[Dataset Status],TRACKER!$F$16) +COUNTIFS(ChartsM7[Lead],TRACKER!$B17,ChartsM7[Dataset Status],TRACKER!$F$16) +COUNTIFS(ChartsM8[Lead],TRACKER!$B17,ChartsM8[Dataset Status],TRACKER!$F$16)) -> 4 | G17: =(COUNTIFS(ChartsM1[Lead],TRACKER!$B17,ChartsM1[Dataset Status],TRACKER!$G$16) +COUNTIFS(ChartsM2[Lead],TRACKER!$B17,ChartsM2[Dataset Status],TRACKER!$G$16) +COUNTIFS(ChartsM3[Lead],TRACKER!$B17,ChartsM3[Dataset Status],TRACKER!$G$16) +COUNTIFS(ChartsM4[Lead],TRACKER!$B17,ChartsM4[Dataset Status],TRACKER!$G$16) +COUNTIFS(ChartsM5[Lead],TRACKER!$B17,ChartsM5[Dataset Status],TRACKER!$G$16) +COUNTIFS(ChartsM6[Lead],TRACKER!$B17,ChartsM6[Dataset Status],TRACKER!$G$16) +COUNTIFS(ChartsM7[Lead],TRACKER!$B17,ChartsM7[Dataset Status],TRACKER!$G$16) +COUNTIFS(ChartsM8[Lead],TRACKER!$B17,ChartsM8[Dataset Status],TRACKER!$G$16)) -> 0 | H17: =(COUNTIFS(ChartsM1[Lead],TRACKER!$B17,ChartsM1[Dataset Status],TRACKER!$H$16) +COUNTIFS(ChartsM2[Lead],TRACKER!$B17,ChartsM2[Dataset Status],TRACKER!$H$16) +COUNTIFS(ChartsM3[Lead],TRACKER!$B17,ChartsM3[Dataset Status],TRACKER!$H$16) +COUNTIFS(ChartsM4[Lead],TRACKER!$B17,ChartsM4[Dataset Status],TRACKER!$H$16) +COUNTIFS(ChartsM5[Lead],TRACKER!$B17,ChartsM5[Dataset Status],TRACKER!$H$16) +COUNTIFS(ChartsM6[Lead],TRACKER!$B17,ChartsM6[Dataset Status],TRACKER!$H$16) +COUNTIFS(ChartsM7[Lead],TRACKER!$B17,ChartsM7[Dataset Status],TRACKER!$H$16) +COUNTIFS(ChartsM8[Lead],TRACKER!$B17,ChartsM8[Dataset Status],TRACKER!$H$16)) -> 3 | I17: =(COUNTIFS(ChartsM1[Lead],TRACKER!$B17,ChartsM1[Dataset Status],TRACKER!$I$16) +COUNTIFS(ChartsM2[Lead],TRACKER!$B17,ChartsM2[Dataset Status],TRACKER!$I$16) +COUNTIFS(ChartsM3[Lead],TRACKER!$B17,ChartsM3[Dataset Status],TRACKER!$I$16) +COUNTIFS(ChartsM4[Lead],TRACKER!$B17,ChartsM4[Dataset Status],TRACKER!$I$16) +COUNTIFS(ChartsM5[Lead],TRACKER!$B17,ChartsM5[Dataset Status],TRACKER!$I$16) +COUNTIFS(ChartsM6[Lead],TRACKER!$B17,ChartsM6[Dataset Status],TRACKER!$I$16) +COUNTIFS(ChartsM7[Lead],TRACKER!$B17,ChartsM7[Dataset Status],TRACKER!$I$16) +COUNTIFS(ChartsM8[Lead],TRACKER!$B17,ChartsM8[Dataset Status],TRACKER!$I$16)) -> 0 | J17: =(COUNTIFS(ChartsM1[Lead],TRACKER!$B17,ChartsM1[Dataset Status],TRACKER!$J$16) +COUNTIFS(ChartsM2[Lead],TRACKER!$B17,ChartsM2[Dataset Status],TRACKER!$J$16) +COUNTIFS(ChartsM3[Lead],TRACKER!$B17,ChartsM3[Dataset Status],TRACKER!$J$16) +COUNTIFS(ChartsM4[Lead],TRACKER!$B17,ChartsM4[Dataset Status],TRACKER!$J$16) +COUNTIFS(ChartsM5[Lead],TRACKER!$B17,ChartsM5[Dataset Status],TRACKER!$J$16) +COUNTIFS(ChartsM6[Lead],TRACKER!$B17,ChartsM6[Dataset Status],TRACKER!$J$16) +COUNTIFS(ChartsM7[Lead],TRACKER!$B17,ChartsM7[Dataset Status],TRACKER!$J$16) +COUNTIFS(ChartsM8[Lead],TRACKER!$B17,ChartsM8[Dataset Status],TRACKER!$J$16)) -> 25 | K17: =(COUNTIFS(ChartsM1[Lead],TRACKER!$B17,ChartsM1[Dataset Status],TRACKER!$K$16) +COUNTIFS(ChartsM2[Lead],TRACKER!$B17,ChartsM2[Dataset Status],TRACKER!$K$16) +COUNTIFS(ChartsM3[Lead],TRACKER!$B17,ChartsM3[Dataset Status],TRACKER!$K$16) +COUNTIFS(ChartsM4[Lead],TRACKER!$B17,ChartsM4[Dataset Status],TRACKER!$K$16) +COUNTIFS(ChartsM5[Lead],TRACKER!$B17,ChartsM5[Dataset Status],TRACKER!$K$16) +COUNTIFS(ChartsM6[Lead],TRACKER!$B17,ChartsM6[Dataset Status],TRACKER!$K$16) +COUNTIFS(ChartsM7[Lead],TRACKER!$B17,ChartsM7[Dataset Status],TRACKER!$K$16) +COUNTIFS(ChartsM8[Lead],TRACKER!$B17,ChartsM8[Dataset Status],TRACKER!$K$16)) -> 1 | V17: =F17/$E17 -> 0.11428571 | W17: =G17/$E17 -> 0 | X17: =I17/$E17 -> 0
B18: Zhong | E18: =COUNTIF(ChartsM1[Lead],TRACKER!B18)+COUNTIF(ChartsM2[Lead],TRACKER!B18)++COUNTIF(ChartsM3[Lead],TRACKER!B18)+COUNTIF(ChartsM4[Lead],TRACKER!B18)+COUNTIF(ChartsM5[Lead],TRACKER!B18)+COUNTIF(ChartsM6[Lead],TRACKER!B18)+COUNTIF(ChartsM7[Lead],TRACKER!B18)+COUNTIF(ChartsM8[Lead],TRACKER!B18) -> 32 | F18: =(COUNTIFS(ChartsM1[Lead],TRACKER!$B18,ChartsM1[Dataset Status],TRACKER!$F$16) +COUNTIFS(ChartsM2[Lead],TRACKER!$B18,ChartsM2[Dataset Status],TRACKER!$F$16) +COUNTIFS(ChartsM3[Lead],TRACKER!$B18,ChartsM3[Dataset Status],TRACKER!$F$16) +COUNTIFS(ChartsM4[Lead],TRACKER!$B18,ChartsM4[Dataset Status],TRACKER!$F$16) +COUNTIFS(ChartsM5[Lead],TRACKER!$B18,ChartsM5[Dataset Status],TRACKER!$F$16) +COUNTIFS(ChartsM6[Lead],TRACKER!$B18,ChartsM6[Dataset Status],TRACKER!$F$16) +COUNTIFS(ChartsM7[Lead],TRACKER!$B18,ChartsM7[Dataset Status],TRACKER!$F$16) +COUNTIFS(ChartsM8[Lead],TRACKER!$B18,ChartsM8[Dataset Status],TRACKER!$F$16)) -> 4 | G18: =(COUNTIFS(ChartsM1[Lead],TRACKER!$B18,ChartsM1[Dataset Status],TRACKER!$G$16) +COUNTIFS(ChartsM2[Lead],TRACKER!$B18,ChartsM2[Dataset Status],TRACKER!$G$16) +COUNTIFS(ChartsM3[Lead],TRACKER!$B18,ChartsM3[Dataset Status],TRACKER!$G$16) +COUNTIFS(ChartsM4[Lead],TRACKER!$B18,ChartsM4[Dataset Status],TRACKER!$G$16) +COUNTIFS(ChartsM5[Lead],TRACKER!$B18,ChartsM5[Dataset Status],TRACKER!$G$16) +COUNTIFS(ChartsM6[Lead],TRACKER!$B18,ChartsM6[Dataset Status],TRACKER!$G$16) +COUNTIFS(ChartsM7[Lead],TRACKER!$B18,ChartsM7[Dataset Status],TRACKER!$G$16) +COUNTIFS(ChartsM8[Lead],TRACKER!$B18,ChartsM8[Dataset Status],TRACKER!$G$16)) -> 0 | H18: =(COUNTIFS(ChartsM1[Lead],TRACKER!$B18,ChartsM1[Dataset Status],TRACKER!$H$16) +COUNTIFS(ChartsM2[Lead],TRACKER!$B18,ChartsM2[Dataset Status],TRACKER!$H$16) +COUNTIFS(ChartsM3[Lead],TRACKER!$B18,ChartsM3[Dataset Status],TRACKER!$H$16) +COUNTIFS(ChartsM4[Lead],TRACKER!$B18,ChartsM4[Dataset Status],TRACKER!$H$16) +COUNTIFS(ChartsM5[Lead],TRACKER!$B18,ChartsM5[Dataset Status],TRACKER!$H$16) +COUNTIFS(ChartsM6[Lead],TRACKER!$B18,ChartsM6[Dataset Status],TRACKER!$H$16) +COUNTIFS(ChartsM7[Lead],TRACKER!$B18,ChartsM7[Dataset Status],TRACKER!$H$16) +COUNTIFS(ChartsM8[Lead],TRACKER!$B18,ChartsM8[Dataset Status],TRACKER!$H$16)) -> 0 | I18: =(COUNTIFS(ChartsM1[Lead],TRACKER!$B18,ChartsM1[Dataset Status],TRACKER!$I$16) +COUNTIFS(ChartsM2[Lead],TRACKER!$B18,ChartsM2[Dataset Status],TRACKER!$I$16) +COUNTIFS(ChartsM3[Lead],TRACKER!$B18,ChartsM3[Dataset Status],TRACKER!$I$16) +COUNTIFS(ChartsM4[Lead],TRACKER!$B18,ChartsM4[Dataset Status],TRACKER!$I$16) +COUNTIFS(ChartsM5[Lead],TRACKER!$B18,ChartsM5[Dataset Status],TRACKER!$I$16) +COUNTIFS(ChartsM6[Lead],TRACKER!$B18,ChartsM6[Dataset Status],TRACKER!$I$16) +COUNTIFS(ChartsM7[Lead],TRACKER!$B18,ChartsM7[Dataset Status],TRACKER!$I$16) +COUNTIFS(ChartsM8[Lead],TRACKER!$B18,ChartsM8[Dataset Status],TRACKER!$I$16)) -> 0 | J18: =(COUNTIFS(ChartsM1[Lead],TRACKER!$B18,ChartsM1[Dataset Status],TRACKER!$J$16) +COUNTIFS(ChartsM2[Lead],TRACKER!$B18,ChartsM2[Dataset Status],TRACKER!$J$16) +COUNTIFS(ChartsM3[Lead],TRACKER!$B18,ChartsM3[Dataset Status],TRACKER!$J$16) +COUNTIFS(ChartsM4[Lead],TRACKER!$B18,ChartsM4[Dataset Status],TRACKER!$J$16) +COUNTIFS(ChartsM5[Lead],TRACKER!$B18,ChartsM5[Dataset Status],TRACKER!$J$16) +COUNTIFS(ChartsM6[Lead],TRACKER!$B18,ChartsM6[Dataset Status],TRACKER!$J$16) +COUNTIFS(ChartsM7[Lead],TRACKER!$B18,ChartsM7[Dataset Status],TRACKER!$J$16) +COUNTIFS(ChartsM8[Lead],TRACKER!$B18,ChartsM8[Dataset Status],TRACKER!$J$16)) -> 24 | K18: =(COUNTIFS(ChartsM1[Lead],TRACKER!$B18,ChartsM1[Dataset Status],TRACKER!$K$16) +COUNTIFS(ChartsM2[Lead],TRACKER!$B18,ChartsM2[Dataset Status],TRACKER!$K$16) +COUNTIFS(ChartsM3[Lead],TRACKER!$B18,ChartsM3[Dataset Status],TRACKER!$K$16) +COUNTIFS(ChartsM4[Lead],TRACKER!$B18,ChartsM4[Dataset Status],TRACKER!$K$16) +COUNTIFS(ChartsM5[Lead],TRACKER!$B18,ChartsM5[Dataset Status],TRACKER!$K$16) +COUNTIFS(ChartsM6[Lead],TRACKER!$B18,ChartsM6[Dataset Status],TRACKER!$K$16) +COUNTIFS(ChartsM7[Lead],TRACKER!$B18,ChartsM7[Dataset Status],TRACKER!$K$16) +COUNTIFS(ChartsM8[Lead],TRACKER!$B18,ChartsM8[Dataset Status],TRACKER!$K$16)) -> 1 | V18: =F18/$E18 -> 0.125 | W18: =G18/$E18 -> 0 | X18: =I18/$E18 -> 0
B19: Divya | E19: =COUNTIF(ChartsM1[Lead],TRACKER!B19)+COUNTIF(ChartsM2[Lead],TRACKER!B19)++COUNTIF(ChartsM3[Lead],TRACKER!B19)+COUNTIF(ChartsM4[Lead],TRACKER!B19)+COUNTIF(ChartsM5[Lead],TRACKER!B19)+COUNTIF(ChartsM6[Lead],TRACKER!B19)+COUNTIF(ChartsM7[Lead],TRACKER!B19)+COUNTIF(ChartsM8[Lead],TRACKER!B19) -> 29 | F19: =(COUNTIFS(ChartsM1[Lead],TRACKER!$B19,ChartsM1[Dataset Status],TRACKER!$F$16) +COUNTIFS(ChartsM2[Lead],TRACKER!$B19,ChartsM2[Dataset Status],TRACKER!$F$16) +COUNTIFS(ChartsM3[Lead],TRACKER!$B19,ChartsM3[Dataset Status],TRACKER!$F$16) +COUNTIFS(ChartsM4[Lead],TRACKER!$B19,ChartsM4[Dataset Status],TRACKER!$F$16) +COUNTIFS(ChartsM5[Lead],TRACKER!$B19,ChartsM5[Dataset Status],TRACKER!$F$16) +COUNTIFS(ChartsM6[Lead],TRACKER!$B19,ChartsM6[Dataset Status],TRACKER!$F$16) +COUNTIFS(ChartsM7[Lead],TRACKER!$B19,ChartsM7[Dataset Status],TRACKER!$F$16) +COUNTIFS(ChartsM8[Lead],TRACKER!$B19,ChartsM8[Dataset Status],TRACKER!$F$16)) -> 2 | G19: =(COUNTIFS(ChartsM1[Lead],TRACKER!$B19,ChartsM1[Dataset Status],TRACKER!$G$16) +COUNTIFS(ChartsM2[Lead],TRACKER!$B19,ChartsM2[Dataset Status],TRACKER!$G$16) +COUNTIFS(ChartsM3[Lead],TRACKER!$B19,ChartsM3[Dataset Status],TRACKER!$G$16) +COUNTIFS(ChartsM4[Lead],TRACKER!$B19,ChartsM4[Dataset Status],TRACKER!$G$16) +COUNTIFS(ChartsM5[Lead],TRACKER!$B19,ChartsM5[Dataset Status],TRACKER!$G$16) +COUNTIFS(ChartsM6[Lead],TRACKER!$B19,ChartsM6[Dataset Status],TRACKER!$G$16) +COUNTIFS(ChartsM7[Lead],TRACKER!$B19,ChartsM7[Dataset Status],TRACKER!$G$16) +COUNTIFS(ChartsM8[Lead],TRACKER!$B19,ChartsM8[Dataset Status],TRACKER!$G$16)) -> 4 | H19: =(COUNTIFS(ChartsM1[Lead],TRACKER!$B19,ChartsM1[Dataset Status],TRACKER!$H$16) +COUNTIFS(ChartsM2[Lead],TRACKER!$B19,ChartsM2[Dataset Status],TRACKER!$H$16) +COUNTIFS(ChartsM3[Lead],TRACKER!$B19,ChartsM3[Dataset Status],TRACKER!$H$16) +COUNTIFS(ChartsM4[Lead],TRACKER!$B19,ChartsM4[Dataset Status],TRACKER!$H$16) +COUNTIFS(ChartsM5[Lead],TRACKER!$B19,ChartsM5[Dataset Status],TRACKER!$H$16) +COUNTIFS(ChartsM6[Lead],TRACKER!$B19,ChartsM6[Dataset Status],TRACKER!$H$16) +COUNTIFS(ChartsM7[Lead],TRACKER!$B19,ChartsM7[Dataset Status],TRACKER!$H$16) +COUNTIFS(ChartsM8[Lead],TRACKER!$B19,ChartsM8[Dataset Status],TRACKER!$H$16)) -> 2 | I19: =(COUNTIFS(ChartsM1[Lead],TRACKER!$B19,ChartsM1[Dataset Status],TRACKER!$I$16) +COUNTIFS(ChartsM2[Lead],TRACKER!$B19,ChartsM2[Dataset Status],TRACKER!$I$16) +COUNTIFS(ChartsM3[Lead],TRACKER!$B19,ChartsM3[Dataset Status],TRACKER!$I$16) +COUNTIFS(ChartsM4[Lead],TRACKER!$B19,ChartsM4[Dataset Status],TRACKER!$I$16) +COUNTIFS(ChartsM5[Lead],TRACKER!$B19,ChartsM5[Dataset Status],TRACKER!$I$16) +COUNTIFS(ChartsM6[Lead],TRACKER!$B19,ChartsM6[Dataset Status],TRACKER!$I$16) +COUNTIFS(ChartsM7[Lead],TRACKER!$B19,ChartsM7[Dataset Status],TRACKER!$I$16) +COUNTIFS(ChartsM8[Lead],TRACKER!$B19,ChartsM8[Dataset Status],TRACKER!$I$16)) -> 0 | J19: =(COUNTIFS(ChartsM1[Lead],TRACKER!$B19,ChartsM1[Dataset Status],TRACKER!$J$16) +COUNTIFS(ChartsM2[Lead],TRACKER!$B19,ChartsM2[Dataset Status],TRACKER!$J$16) +COUNTIFS(ChartsM3[Lead],TRACKER!$B19,ChartsM3[Dataset Status],TRACKER!$J$16) +COUNTIFS(ChartsM4[Lead],TRACKER!$B19,ChartsM4[Dataset Status],TRACKER!$J$16) +COUNTIFS(ChartsM5[Lead],TRACKER!$B19,ChartsM5[Dataset Status],TRACKER!$J$16) +COUNTIFS(ChartsM6[Lead],TRACKER!$B19,ChartsM6[Dataset Status],TRACKER!$J$16) +COUNTIFS(ChartsM7[Lead],TRACKER!$B19,ChartsM7[Dataset Status],TRACKER!$J$16) +COUNTIFS(ChartsM8[Lead],TRACKER!$B19,ChartsM8[Dataset Status],TRACKER!$J$16)) -> 20 | K19: =(COUNTIFS(ChartsM1[Lead],TRACKER!$B19,ChartsM1[Dataset Status],TRACKER!$K$16) +COUNTIFS(ChartsM2[Lead],TRACKER!$B19,ChartsM2[Dataset Status],TRACKER!$K$16) +COUNTIFS(ChartsM3[Lead],TRACKER!$B19,ChartsM3[Dataset Status],TRACKER!$K$16) +COUNTIFS(ChartsM4[Lead],TRACKER!$B19,ChartsM4[Dataset Status],TRACKER!$K$16) +COUNTIFS(ChartsM5[Lead],TRACKER!$B19,ChartsM5[Dataset Status],TRACKER!$K$16) +COUNTIFS(ChartsM6[Lead],TRACKER!$B19,ChartsM6[Dataset Status],TRACKER!$K$16) +COUNTIFS(ChartsM7[Lead],TRACKER!$B19,ChartsM7[Dataset Status],TRACKER!$K$16) +COUNTIFS(ChartsM8[Lead],TRACKER!$B19,ChartsM8[Dataset Status],TRACKER!$K$16)) -> 1 | V19: =F19/$E19 -> 0.068965517 | W19: =G19/$E19 -> 0.13793103 | X19: =I19/$E19 -> 0
B20: Danae | E20: =COUNTIF(ChartsM1[Lead],TRACKER!B20)+COUNTIF(ChartsM2[Lead],TRACKER!B20)++COUNTIF(ChartsM3[Lead],TRACKER!B20)+COUNTIF(ChartsM4[Lead],TRACKER!B20)+COUNTIF(ChartsM5[Lead],TRACKER!B20)+COUNTIF(ChartsM6[Lead],TRACKER!B20)+COUNTIF(ChartsM7[Lead],TRACKER!B20)+COUNTIF(ChartsM8[Lead],TRACKER!B20) -> 23 | F20: =(COUNTIFS(ChartsM1[Lead],TRACKER!$B20,ChartsM1[Dataset Status],TRACKER!$F$16) +COUNTIFS(ChartsM2[Lead],TRACKER!$B20,ChartsM2[Dataset Status],TRACKER!$F$16) +COUNTIFS(ChartsM3[Lead],TRACKER!$B20,ChartsM3[Dataset Status],TRACKER!$F$16) +COUNTIFS(ChartsM4[Lead],TRACKER!$B20,ChartsM4[Dataset Status],TRACKER!$F$16) +COUNTIFS(ChartsM5[Lead],TRACKER!$B20,ChartsM5[Dataset Status],TRACKER!$F$16) +COUNTIFS(ChartsM6[Lead],TRACKER!$B20,ChartsM6[Dataset Status],TRACKER!$F$16) +COUNTIFS(ChartsM7[Lead],TRACKER!$B20,ChartsM7[Dataset Status],TRACKER!$F$16) +COUNTIFS(ChartsM8[Lead],TRACKER!$B20,ChartsM8[Dataset Status],TRACKER!$F$16)) -> 0 | G20: =(COUNTIFS(ChartsM1[Lead],TRACKER!$B20,ChartsM1[Dataset Status],TRACKER!$G$16) +COUNTIFS(ChartsM2[Lead],TRACKER!$B20,ChartsM2[Dataset Status],TRACKER!$G$16) +COUNTIFS(ChartsM3[Lead],TRACKER!$B20,ChartsM3[Dataset Status],TRACKER!$G$16) +COUNTIFS(ChartsM4[Lead],TRACKER!$B20,ChartsM4[Dataset Status],TRACKER!$G$16) +COUNTIFS(ChartsM5[Lead],TRACKER!$B20,ChartsM5[Dataset Status],TRACKER!$G$16) +COUNTIFS(ChartsM6[Lead],TRACKER!$B20,ChartsM6[Dataset Status],TRACKER!$G$16) +COUNTIFS(ChartsM7[Lead],TRACKER!$B20,ChartsM7[Dataset Status],TRACKER!$G$16) +COUNTIFS(ChartsM8[Lead],TRACKER!$B20,ChartsM8[Dataset Status],TRACKER!$G$16)) -> 0 | H20: =(COUNTIFS(ChartsM1[Lead],TRACKER!$B20,ChartsM1[Dataset Status],TRACKER!$H$16) +COUNTIFS(ChartsM2[Lead],TRACKER!$B20,ChartsM2[Dataset Status],TRACKER!$H$16) +COUNTIFS(ChartsM3[Lead],TRACKER!$B20,ChartsM3[Dataset Status],TRACKER!$H$16) +COUNTIFS(ChartsM4[Lead],TRACKER!$B20,ChartsM4[Dataset Status],TRACKER!$H$16) +COUNTIFS(ChartsM5[Lead],TRACKER!$B20,ChartsM5[Dataset Status],TRACKER!$H$16) +COUNTIFS(ChartsM6[Lead],TRACKER!$B20,ChartsM6[Dataset Status],TRACKER!$H$16) +COUNTIFS(ChartsM7[Lead],TRACKER!$B20,ChartsM7[Dataset Status],TRACKER!$H$16) +COUNTIFS(ChartsM8[Lead],TRACKER!$B20,ChartsM8[Dataset Status],TRACKER!$H$16)) -> 11 | I20: =(COUNTIFS(ChartsM1[Lead],TRACKER!$B20,ChartsM1[Dataset Status],TRACKER!$I$16) +COUNTIFS(ChartsM2[Lead],TRACKER!$B20,ChartsM2[Dataset Status],TRACKER!$I$16) +COUNTIFS(ChartsM3[Lead],TRACKER!$B20,ChartsM3[Dataset Status],TRACKER!$I$16) +COUNTIFS(ChartsM4[Lead],TRACKER!$B20,ChartsM4[Dataset Status],TRACKER!$I$16) +COUNTIFS(ChartsM5[Lead],TRACKER!$B20,ChartsM5[Dataset Status],TRACKER!$I$16) +COUNTIFS(ChartsM6[Lead],TRACKER!$B20,ChartsM6[Dataset Status],TRACKER!$I$16) +COUNTIFS(ChartsM7[Lead],TRACKER!$B20,ChartsM7[Dataset Status],TRACKER!$I$16) +COUNTIFS(ChartsM8[Lead],TRACKER!$B20,ChartsM8[Dataset Status],TRACKER!$I$16)) -> 0 | J20: =(COUNTIFS(ChartsM1[Lead],TRACKER!$B20,ChartsM1[Dataset Status],TRACKER!$J$16) +COUNTIFS(ChartsM2[Lead],TRACKER!$B20,ChartsM2[Dataset Status],TRACKER!$J$16) +COUNTIFS(ChartsM3[Lead],TRACKER!$B20,ChartsM3[Dataset Status],TRACKER!$J$16) +COUNTIFS(ChartsM4[Lead],TRACKER!$B20,ChartsM4[Dataset Status],TRACKER!$J$16) +COUNTIFS(ChartsM5[Lead],TRACKER!$B20,ChartsM5[Dataset Status],TRACKER!$J$16) +COUNTIFS(ChartsM6[Lead],TRACKER!$B20,ChartsM6[Dataset Status],TRACKER!$J$16) +COUNTIFS(ChartsM7[Lead],TRACKER!$B20,ChartsM7[Dataset Status],TRACKER!$J$16) +COUNTIFS(ChartsM8[Lead],TRACKER!$B20,ChartsM8[Dataset Status],TRACKER!$J$16)) -> 12 | K20: =(COUNTIFS(ChartsM1[Lead],TRACKER!$B20,ChartsM1[Dataset Status],TRACKER!$K$16) +COUNTIFS(ChartsM2[Lead],TRACKER!$B20,ChartsM2[Dataset Status],TRACKER!$K$16) +COUNTIFS(ChartsM3[Lead],TRACKER!$B20,ChartsM3[Dataset Status],TRACKER!$K$16) +COUNTIFS(ChartsM4[Lead],TRACKER!$B20,ChartsM4[Dataset Status],TRACKER!$K$16) +COUNTIFS(ChartsM5[Lead],TRACKER!$B20,ChartsM5[Dataset Status],TRACKER!$K$16) +COUNTIFS(ChartsM6[Lead],TRACKER!$B20,ChartsM6[Dataset Status],TRACKER!$K$16) +COUNTIFS(ChartsM7[Lead],TRACKER!$B20,ChartsM7[Dataset Status],TRACKER!$K$16) +COUNTIFS(ChartsM8[Lead],TRACKER!$B20,ChartsM8[Dataset Status],TRACKER!$K$16)) -> 0 | V20: =F20/$E20 -> 0 | W20: =G20/$E20 -> 0 | X20: =I20/$E20 -> 0
B21: Ahmad | E21: =COUNTIF(ChartsM1[Lead],TRACKER!B21)+COUNTIF(ChartsM2[Lead],TRACKER!B21)++COUNTIF(ChartsM3[Lead],TRACKER!B21)+COUNTIF(ChartsM4[Lead],TRACKER!B21)+COUNTIF(ChartsM5[Lead],TRACKER!B21)+COUNTIF(ChartsM6[Lead],TRACKER!B21)+COUNTIF(ChartsM7[Lead],TRACKER!B21)+COUNTIF(ChartsM8[Lead],TRACKER!B21) -> 5 | F21: =(COUNTIFS(ChartsM1[Lead],TRACKER!$B21,ChartsM1[Dataset Status],TRACKER!$F$16) +COUNTIFS(ChartsM2[Lead],TRACKER!$B21,ChartsM2[Dataset Status],TRACKER!$F$16) +COUNTIFS(ChartsM3[Lead],TRACKER!$B21,ChartsM3[Dataset Status],TRACKER!$F$16) +COUNTIFS(ChartsM4[Lead],TRACKER!$B21,ChartsM4[Dataset Status],TRACKER!$F$16) +COUNTIFS(ChartsM5[Lead],TRACKER!$B21,ChartsM5[Dataset Status],TRACKER!$F$16) +COUNTIFS(ChartsM6[Lead],TRACKER!$B21,ChartsM6[Dataset Status],TRACKER!$F$16) +COUNTIFS(ChartsM7[Lead],TRACKER!$B21,ChartsM7[Dataset Status],TRACKER!$F$16) +COUNTIFS(ChartsM8[Lead],TRACKER!$B21,ChartsM8[Dataset Status],TRACKER!$F$16)) -> 4 | G21: =(COUNTIFS(ChartsM1[Lead],TRACKER!$B21,ChartsM1[Dataset Status],TRACKER!$G$16) +COUNTIFS(ChartsM2[Lead],TRACKER!$B21,ChartsM2[Dataset Status],TRACKER!$G$16) +COUNTIFS(ChartsM3[Lead],TRACKER!$B21,ChartsM3[Dataset Status],TRACKER!$G$16) +COUNTIFS(ChartsM4[Lead],TRACKER!$B21,ChartsM4[Dataset Status],TRACKER!$G$16) +COUNTIFS(ChartsM5[Lead],TRACKER!$B21,ChartsM5[Dataset Status],TRACKER!$G$16) +COUNTIFS(ChartsM6[Lead],TRACKER!$B21,ChartsM6[Dataset Status],TRACKER!$G$16) +COUNTIFS(ChartsM7[Lead],TRACKER!$B21,ChartsM7[Dataset Status],TRACKER!$G$16) +COUNTIFS(ChartsM8[Lead],TRACKER!$B21,ChartsM8[Dataset Status],TRACKER!$G$16)) -> 0 | H21: =(COUNTIFS(ChartsM1[Lead],TRACKER!$B21,ChartsM1[Dataset Status],TRACKER!$H$16) +COUNTIFS(ChartsM2[Lead],TRACKER!$B21,ChartsM2[Dataset Status],TRACKER!$H$16) +COUNTIFS(ChartsM3[Lead],TRACKER!$B21,ChartsM3[Dataset Status],TRACKER!$H$16) +COUNTIFS(ChartsM4[Lead],TRACKER!$B21,ChartsM4[Dataset Status],TRACKER!$H$16) +COUNTIFS(ChartsM5[Lead],TRACKER!$B21,ChartsM5[Dataset Status],TRACKER!$H$16) +COUNTIFS(ChartsM6[Lead],TRACKER!$B21,ChartsM6[Dataset Status],TRACKER!$H$16) +COUNTIFS(ChartsM7[Lead],TRACKER!$B21,ChartsM7[Dataset Status],TRACKER!$H$16) +COUNTIFS(ChartsM8[Lead],TRACKER!$B21,ChartsM8[Dataset Status],TRACKER!$H$16)) -> 0 | I21: =(COUNTIFS(ChartsM1[Lead],TRACKER!$B21,ChartsM1[Dataset Status],TRACKER!$I$16) +COUNTIFS(ChartsM2[Lead],TRACKER!$B21,ChartsM2[Dataset Status],TRACKER!$I$16) +COUNTIFS(ChartsM3[Lead],TRACKER!$B21,ChartsM3[Dataset Status],TRACKER!$I$16) +COUNTIFS(ChartsM4[Lead],TRACKER!$B21,ChartsM4[Dataset Status],TRACKER!$I$16) +COUNTIFS(ChartsM5[Lead],TRACKER!$B21,ChartsM5[Dataset Status],TRACKER!$I$16) +COUNTIFS(ChartsM6[Lead],TRACKER!$B21,ChartsM6[Dataset Status],TRACKER!$I$16) +COUNTIFS(ChartsM7[Lead],TRACKER!$B21,ChartsM7[Dataset Status],TRACKER!$I$16) +COUNTIFS(ChartsM8[Lead],TRACKER!$B21,ChartsM8[Dataset Status],TRACKER!$I$16)) -> 0 | J21: =(COUNTIFS(ChartsM1[Lead],TRACKER!$B21,ChartsM1[Dataset Status],TRACKER!$J$16) +COUNTIFS(ChartsM2[Lead],TRACKER!$B21,ChartsM2[Dataset Status],TRACKER!$J$16) +COUNTIFS(ChartsM3[Lead],TRACKER!$B21,ChartsM3[Dataset Status],TRACKER!$J$16) +COUNTIFS(ChartsM4[Lead],TRACKER!$B21,ChartsM4[Dataset Status],TRACKER!$J$16) +COUNTIFS(ChartsM5[Lead],TRACKER!$B21,ChartsM5[Dataset Status],TRACKER!$J$16) +COUNTIFS(ChartsM6[Lead],TRACKER!$B21,ChartsM6[Dataset Status],TRACKER!$J$16) +COUNTIFS(ChartsM7[Lead],TRACKER!$B21,ChartsM7[Dataset Status],TRACKER!$J$16) +COUNTIFS(ChartsM8[Lead],TRACKER!$B21,ChartsM8[Dataset Status],TRACKER!$J$16)) -> 1 | K21: =(COUNTIFS(ChartsM1[Lead],TRACKER!$B21,ChartsM1[Dataset Status],TRACKER!$K$16) +COUNTIFS(ChartsM2[Lead],TRACKER!$B21,ChartsM2[Dataset Status],TRACKER!$K$16) +COUNTIFS(ChartsM3[Lead],TRACKER!$B21,ChartsM3[Dataset Status],TRACKER!$K$16) +COUNTIFS(ChartsM4[Lead],TRACKER!$B21,ChartsM4[Dataset Status],TRACKER!$K$16) +COUNTIFS(ChartsM5[Lead],TRACKER!$B21,ChartsM5[Dataset Status],TRACKER!$K$16) +COUNTIFS(ChartsM6[Lead],TRACKER!$B21,ChartsM6[Dataset Status],TRACKER!$K$16) +COUNTIFS(ChartsM7[Lead],TRACKER!$B21,ChartsM7[Dataset Status],TRACKER!$K$16) +COUNTIFS(ChartsM8[Lead],TRACKER!$B21,ChartsM8[Dataset Status],TRACKER!$K$16)) -> 0
E22: =COUNTIFS(ChartsM1[Lead],"", ChartsM1[Chapter], ">0") +COUNTIFS(ChartsM2[Lead],"", ChartsM2[Chapter], ">0") +COUNTIFS(ChartsM3[Lead],"", ChartsM3[Chapter], ">0") +COUNTIFS(ChartsM4[Lead],"", ChartsM4[Chapter], ">0") +COUNTIFS(ChartsM5[Lead],"", ChartsM5[Chapter], ">0") +COUNTIFS(ChartsM6[Lead],"", ChartsM6[Chapter], ">0") +COUNTIFS(ChartsM7[Lead],"", ChartsM7[Chapter], ">0") +COUNTIFS(ChartsM8[Lead],"", ChartsM8[Chapter], ">0") -> 31 | F22: =(COUNTIFS(ChartsM1[Lead],"",ChartsM1[Dataset Status],TRACKER!$F$16) +COUNTIFS(ChartsM2[Lead],"",ChartsM2[Dataset Status],TRACKER!$F$16) +COUNTIFS(ChartsM3[Lead],"",ChartsM3[Dataset Status],TRACKER!$F$16) +COUNTIFS(ChartsM4[Lead],"",ChartsM4[Dataset Status],TRACKER!$F$16) +COUNTIFS(ChartsM5[Lead],"",ChartsM5[Dataset Status],TRACKER!$F$16) +COUNTIFS(ChartsM6[Lead],"",ChartsM6[Dataset Status],TRACKER!$F$16) +COUNTIFS(ChartsM7[Lead],"",ChartsM7[Dataset Status],TRACKER!$F$16) +COUNTIFS(ChartsM8[Lead],"",ChartsM8[Dataset Status],TRACKER!$F$16)) -> 5 | G22: =(COUNTIFS(ChartsM1[Lead],"",ChartsM1[Dataset Status],TRACKER!$G$16) +COUNTIFS(ChartsM2[Lead],"",ChartsM2[Dataset Status],TRACKER!$G$16) +COUNTIFS(ChartsM3[Lead],"",ChartsM3[Dataset Status],TRACKER!$G$16) +COUNTIFS(ChartsM4[Lead],"",ChartsM4[Dataset Status],TRACKER!$G$16) +COUNTIFS(ChartsM5[Lead],"",ChartsM5[Dataset Status],TRACKER!$G$16) +COUNTIFS(ChartsM6[Lead],"",ChartsM6[Dataset Status],TRACKER!$G$16) +COUNTIFS(ChartsM7[Lead],"",ChartsM7[Dataset Status],TRACKER!$G$16) +COUNTIFS(ChartsM8[Lead],"",ChartsM8[Dataset Status],TRACKER!$G$16)) -> 0 | H22: =(COUNTIFS(ChartsM1[Lead],"",ChartsM1[Dataset Status],TRACKER!$H$16) +COUNTIFS(ChartsM2[Lead],"",ChartsM2[Dataset Status],TRACKER!$H$16) +COUNTIFS(ChartsM3[Lead],"",ChartsM3[Dataset Status],TRACKER!$H$16) +COUNTIFS(ChartsM4[Lead],"",ChartsM4[Dataset Status],TRACKER!$H$16) +COUNTIFS(ChartsM5[Lead],"",ChartsM5[Dataset Status],TRACKER!$H$16) +COUNTIFS(ChartsM6[Lead],"",ChartsM6[Dataset Status],TRACKER!$H$16) +COUNTIFS(ChartsM7[Lead],"",ChartsM7[Dataset Status],TRACKER!$H$16) +COUNTIFS(ChartsM8[Lead],"",ChartsM8[Dataset Status],TRACKER!$H$16)) -> 5 | I22: =(COUNTIFS(ChartsM1[Lead],"",ChartsM1[Dataset Status],TRACKER!$I$16) +COUNTIFS(ChartsM2[Lead],"",ChartsM2[Dataset Status],TRACKER!$I$16) +COUNTIFS(ChartsM3[Lead],"",ChartsM3[Dataset Status],TRACKER!$I$16) +COUNTIFS(ChartsM4[Lead],"",ChartsM4[Dataset Status],TRACKER!$I$16) +COUNTIFS(ChartsM5[Lead],"",ChartsM5[Dataset Status],TRACKER!$I$16) +COUNTIFS(ChartsM6[Lead],"",ChartsM6[Dataset Status],TRACKER!$I$16) +COUNTIFS(ChartsM7[Lead],"",ChartsM7[Dataset Status],TRACKER!$I$16) +COUNTIFS(ChartsM8[Lead],"",ChartsM8[Dataset Status],TRACKER!$I$16)) -> 0 | J22: =(COUNTIFS(ChartsM1[Lead],"",ChartsM1[Dataset Status],TRACKER!$J$16) +COUNTIFS(ChartsM2[Lead],"",ChartsM2[Dataset Status],TRACKER!$J$16) +COUNTIFS(ChartsM3[Lead],"",ChartsM3[Dataset Status],TRACKER!$J$16) +COUNTIFS(ChartsM4[Lead],"",ChartsM4[Dataset Status],TRACKER!$J$16) +COUNTIFS(ChartsM5[Lead],"",ChartsM5[Dataset Status],TRACKER!$J$16) +COUNTIFS(ChartsM6[Lead],"",ChartsM6[Dataset Status],TRACKER!$J$16) +COUNTIFS(ChartsM7[Lead],"",ChartsM7[Dataset Status],TRACKER!$J$16) +COUNTIFS(ChartsM8[Lead],"",ChartsM8[Dataset Status],TRACKER!$J$16)) -> 2 | K22: =(COUNTIFS(ChartsM1[Lead],"",ChartsM1[Dataset Status],TRACKER!$K$16) +COUNTIFS(ChartsM2[Lead],"",ChartsM2[Dataset Status],TRACKER!$K$16) +COUNTIFS(ChartsM3[Lead],"",ChartsM3[Dataset Status],TRACKER!$K$16) +COUNTIFS(ChartsM4[Lead],"",ChartsM4[Dataset Status],TRACKER!$K$16) +COUNTIFS(ChartsM5[Lead],"",ChartsM5[Dataset Status],TRACKER!$K$16) +COUNTIFS(ChartsM6[Lead],"",ChartsM6[Dataset Status],TRACKER!$K$16) +COUNTIFS(ChartsM7[Lead],"",ChartsM7[Dataset Status],TRACKER!$K$16) +COUNTIFS(ChartsM8[Lead],"",ChartsM8[Dataset Status],TRACKER!$K$16)) -> 1
B23: TOTAL | E23: =SUM(E15:E22) -> 155 | F23: =SUM(F17:F22) -> 19 | G23: =SUM(G17:G22) -> 4 | H23: =SUM(H17:H22) -> 21 | I23: =SUM(I17:I22) -> 0 | J23: =SUM(J17:J22) -> 84 | K23: =SUM(K17:K22) -> 4 | V23: =N23/$E23 -> 0 | W23: =O23/$E23 -> 0 | X23: =P23/$E23 -> 0

Sheet Links
A1: Title | B1: Lead | C1: Link
A2: Module 1. Introduction to Sustainable Energy for Development | C2: https://www.figma.com/design/G63dbqCKnazZenINIwtfY1/SEA_Modules-with-new-templates--1-4-?node-id=1-3&p=f&t=15mvoon4RjwZLIC5-0
A3: Module 2. Energy Access and Inclusive Energy Services | B3: Shadé
A4: Module 3. Just Energy Transition | B4: Danae
A5: Module 4. Sustainable Energy Finance | B5: Adam
A6: Module 5. Intersectionality and Energy Policy | B6: Farida | C6: https://www.figma.com/design/AFNWazZePMsFoFYNajOESM/SEA_Modules-with-new-templates--5-8-?node-id=2388-81&t=8lQv8NwY8k2geRUP-0
A7: Module 6. Climate-Energy Nexus
A8: Module 7. Data in Sustainable Energy | B8: Danae
A9: Module 8. Innovation and Future of Renewable Energy | B9: Shadé
A11: OV Graphic Development - Figma file | B11: SiNae | C11: https://www.figma.com/design/1MhqUWjCIcKip6jthZgla7/%5BOV%5D-SEA-Graphic-Development-Task?node-id=0-1&p=f&t=TAGe9NlhcM2y1Vqf-0
A13: Datasets - Infographics with Data | B13: Danae | C13: https://undp.sharepoint.com/:x:/r/sites/SEHCoreTeam/Shared%20Documents/General/04.%20Sustainable%20Energy%20Academy/SEA%20Charts%20and%20Infographics/Datasets/Datasets%20-%20Infographics%20with%20Data.xlsx?d=w6d11da9e3dab40f6b27c20158828a094&csf=1&web=1&e=KqVtlB

Sheet Screenshots
A2: Module | B2: Figure ID | C2: Title | D2: Screenshot | E2: New Screenshot
A3: =MID(B3,2,1) -> 1 | B3: M1_C1_2 | C3: The Human Development Index (HDI) and energy use per capita, 2019 | D3: #VALUE!
A4: =MID(B4,2,1) -> 1 | B4: M1_C1_3 | C4: Global energy flows in the NZE Scenario (2021) | D4: #VALUE!
A5: =MID(B5,2,1) -> 1 | B5: M1_C1_5 | C5: Global fossil fuel consumption | D5: #VALUE!
A6: =MID(B6,2,1) -> 1 | B6: M1_C1_6 | C6: Energy use per person | D6: #VALUE!
A7: =MID(B7,2,1) -> 1 | B7: M1_C1_7 | C7: Global CO2 emissions from energy combustion and industrial processes and their annual change, 1900-2022 | D7: #VALUE!
A8: =MID(B8,2,1) -> 1 | B8: M1_C1_8 | C8: Energy and Climate Change | D8: #VALUE! | E8: #VALUE!
A9: =MID(B9,2,1) -> 1 | B9: M1_C1_9 | C9: Exhibit 1: Energy system losses from primary to useful, 2019 | D9: #VALUE!
A10: =MID(B10,2,1) -> 1 | B10: M1_C1_10 | C10: Global energy demand | D10: #VALUE!
A11: =MID(B11,2,1) -> 1 | B11: M1_C1_12 | C11: Share of renewable sources in final energy consumption and by end use, 2015 and 2021 (percentage) | D11: #VALUE!
A12: =MID(B12,2,1) -> 1 | B12: M1_C1_13 | C12: Installed capacity for renewable electricity generation, 2015 and 2022 (watts per capita) | D12: #VALUE!
A13: =MID(B13,2,1) -> 1 | B13: M1_C1_14 | C13: FIGURE 1.2 Energy-related CO2 emission trajectories based on past COP announcements, PES and the 1.5°C Scenario | D13: #VALUE!
A14: =MID(B14,2,1) -> 1 | B14: M1_C1_15 | C14: The Energy System We Need: Energy Flow in 2050 in a 1.5° aligned scenario | D14: #VALUE!
A15: =MID(B15,2,1) -> 1 | B15: M1_C3_17 | C15: Energy Access in LDCs and Conflict Affected Countries within the Arab States Region | D15: #VALUE!
A16: =MID(B16,2,1) -> 1 | B16: M1_C3_18 | C16: Share of Population with Electricity Access and Clean Cooking Access in the Arab Region | D16: #VALUE!
A17: =MID(B17,2,1) -> 1 | B17: M1_C3_19 | C17: Inflation by sector | D17: #VALUE!
A18: =MID(B18,2,1) -> 1 | B18: M1_C3_20 | C18: Total Energy Subsidies Value in Some Arab Countries | D18: #VALUE!
A19: =MID(B19,2,1) -> 1 | B19: M1_C3_21 | C19: Renewable energy produced per source per country, 2022 | D19: #VALUE!
A20: =MID(B20,2,1) -> 1 | B20: M1_C3_22 | C20: Renewable Energy Installed Capacities and Share in the Total Capacity in 2020 | D20: #VALUE!
... A35: =MID(B35,2,1) -> 1 | B35: M1_C3_36 | C35: Nationally determined contributions and net-zero emissions targets | D35: #VALUE!

Sheet Module1
A1: Module | B1: 1
A2: Chapter | B2: # | C2: Figure ID | D2: Title | E2: Screenshot | F2: New Screenshot | G2: Lead | H2: Source (APA) | I2: Footnote | J2: Source Link | K2: Dataset Link | L2: Chart Status | M2: Dataset Status | N2: Category | O2: Chart Type | P2: Apache Possible | Q2: Apache Link | R2: Automation Possible | S2: Notes
A3: 1 | B3: 2 | C3: =_xlfn.CONCAT("M",$B$1,"_C",ChartsM1[[#This Row],[Chapter]],"_",ChartsM1[[#This Row],['#]]) -> M1_C1_2 | D3: The Human Development Index (HDI) and energy use per capita, 2019 | E3: #VALUE! | G3: Zhong | H3: Cleveland, C., & Clifford, H. (2022, September 30) | I3: Sources: Our World in Data; United Nations Development Programme Boston University Institute for Global Sustainability | visualizingenergy.org | CC BY 4.0 | J3: https://visualizingenergy.org/does-more-energy-use-increase-the-level-of-human-development/ | K3: M1_C1_2 | L3: In process | M3: Ready | N3: Chart to recreate | O3: Scatter Chart Categories | P3: Yes | Q3: https://echarts.apache.org/examples/en/editor.html?c=scatter-simple | R3: Yes | S3: Zhong: Apache Example: https://echarts.apache.org/examples/en/editor.html?c=scatter-simple
A4: 1 | B4: 3 | C4: =_xlfn.CONCAT("M",$B$1,"_C",ChartsM1[[#This Row],[Chapter]],"_",ChartsM1[[#This Row],['#]]) -> M1_C1_3 | D4: Global energy flows in the NZE Scenario (2021) | E4: #VALUE! | L4: In process | N4: Chart for Direct Use
A5: 1 | B5: 5 | C5: =_xlfn.CONCAT("M",$B$1,"_C",ChartsM1[[#This Row],[Chapter]],"_",ChartsM1[[#This Row],['#]]) -> M1_C1_5 | D5: Global fossil fuel consumption | E5: #VALUE! | L5: In process | N5: Chart for Direct Use
A6: 1 | B6: 6 | C6: =_xlfn.CONCAT("M",$B$1,"_C",ChartsM1[[#This Row],[Chapter]],"_",ChartsM1[[#This Row],['#]]) -> M1_C1_6 | D6: Energy use per person | E6: #VALUE! | L6: In process | N6: Chart for Direct Use
A7: 1 | B7: 7 | C7: =_xlfn.CONCAT("M",$B$1,"_C",ChartsM1[[#This Row],[Chapter]],"_",ChartsM1[[#This Row],['#]]) -> M1_C1_7 | D7: Global CO2 emissions from energy combustion and industrial processes and their annual change, 1900-2022 | E7: #VALUE! | G7: Zhong | H7: IEA (2023, p.5) | J7: https://iea.blob.core.windows.net/assets/3c8fa115-35c4-4474-b237-1b00424c8844/CO2Emissionsin2022.pdf | K7: M1_C1_7 | L7: In process | M7: Ready | N7: Chart to recreate | O7: Line Chart | P7: Yes | Q7: https://echarts.apache.org/examples/en/editor.html?c=line-simple | R7: Yes | S7: Yevgen's note I would add here a target of Paris Agreement on limiting the emissions, e.g. by adding a net zero point in 2050 Zhong: Apache Example: https://echarts.apache.org/examples/en/editor.html?c=line-simple; https://echarts.apache.org/examples/en/editor.html?c=bar-simple Frederick's Note: Should this plot be created as one Infographic comprised of both the line and bar chart or should two seperate charts be created. If yes, please open a new row for that.
A8: 1 | B8: 8 | C8: =_xlfn.CONCAT("M",$B$1,"_C",ChartsM1[[#This Row],[Chapter]],"_",ChartsM1[[#This Row],['#]]) -> M1_C1_8 | D8: Energy and Climate Change | E8: #VALUE! | F8: #VALUE! | G8: Zhong | H8: Stanford Doerr School of Sustainability (n.d.) via Climate Watch (2024) | I8: Pie chart showing the sources of GHG emissions by sector in 2021. Energy includes Electricity and Heat, Manufacturing and Construction, Transportation, Fugitive Emissions, and Buildings | J8: https://understand-energy.stanford.edu/current-energy-landscape | K8: M1_C1_8 | L8: In process | M8: Ready | N8: Chart to recreate | O8: Pie chart | P8: Yes | Q8: https://echarts.apache.org/examples/en/editor.html?c=pie-simple | R8: Yes | S8: Zhong: Apache Example: https://echarts.apache.org/examples/en/editor.html?c=pie-simple
A9: 1 | B9: 9 | C9: =_xlfn.CONCAT("M",$B$1,"_C",ChartsM1[[#This Row],[Chapter]],"_",ChartsM1[[#This Row],['#]]) -> M1_C1_9 | D9: Exhibit 1: Energy system losses from primary to useful, 2019 | E9: #VALUE! | H9: Walter, D., Bond, K., Lovins, A., Speelman, L., Gulli, C., & Butler-Sloss, S. (2024) | L9: In process | N9: Chart for Direct Use
A10: 1 | B10: 10 | C10: =_xlfn.CONCAT("M",$B$1,"_C",ChartsM1[[#This Row],[Chapter]],"_",ChartsM1[[#This Row],['#]]) -> M1_C1_10 | D10: Global energy demand | E10: #VALUE! | G10: Zhong | H10: ExxonMobil (2024) | I10: Source: Smil, Energy Transitions (1900-1960), 2024 ExxonMobil Global Outlook (1970-2050) | J10: https://corporate.exxonmobil.com/sustainability-and-reports/global-outlook/energy-demand-drivers | K10: M1_C1_10 | L10: In process | M10: Ready | N10: Chart to recreate | O10: Bar Chart Stacked Vertical | P10: Yes | Q10: https://echarts.apache.org/examples/en/editor.html?c=bar-stack | R10: Yes | S10: Zhong: Data points prior to 2000 were manually extracted (estimates). Data points from 2000 to 2050 are from the ExxonMobil Global Outlook (2024): https://corporate.exxonmobil.com/-/media/global/files/global-outlook/2024/global-outlook-data-2024.xlsx Apache Example: https://echarts.apache.org/examples/en/editor.html?c=bar-stack
A11: 1 | B11: 12 | C11: =_xlfn.CONCAT("M",$B$1,"_C",ChartsM1[[#This Row],[Chapter]],"_",ChartsM1[[#This Row],['#]]) -> M1_C1_12 | D11: Share of renewable sources in final energy consumption and by end use, 2015 and 2021 (percentage) | E11: #VALUE! | G11: Zhong | H11: United Nations Statistics Division (n.d.) | J11: https://unstats.un.org/sdgs/report/2024/Goal-07/ | K11: M1_C1_12 | L11: In process | M11: Ready | N11: Chart to recreate | O11: Bar Chart Categories Horizontal | P11: Yes | Q11: https://echarts.apache.org/examples/en/editor.html?c=bar-y-category-stack | R11: Yes | S11: Zhong: Apache Example: https://echarts.apache.org/examples/en/editor.html?c=bar-y-category-stack Note Frederick: Grouped Stacked Bar Chart changed to Grouped Bar Chart in Dataset
A12: 1 | B12: 13 | C12: =_xlfn.CONCAT("M",$B$1,"_C",ChartsM1[[#This Row],[Chapter]],"_",ChartsM1[[#This Row],['#]]) -> M1_C1_13 | D12: Installed capacity for renewable electricity generation, 2015 and 2022 (watts per capita) | E12: #VALUE! | G12: Zhong | H12: United Nations Statistics Division (n.d.) | J12: https://unstats.un.org/sdgs/report/2024/Goal-07/ | K12: M1_C1_13 | L12: In process | M12: Ready | N12: Chart to recreate | O12: Bar Chart Categories Horizontal | P12: Yes | Q12: https://echarts.apache.org/examples/en/editor.html?c=bar-y-category | R12: Yes | S12: Zhong: Apache Example: https://echarts.apache.org/examples/en/editor.html?c=bar-y-category
A13: 1 | B13: 14 | C13: =_xlfn.CONCAT("M",$B$1,"_C",ChartsM1[[#This Row],[Chapter]],"_",ChartsM1[[#This Row],['#]]) -> M1_C1_14 | D13: Energy-related CO2 emission trajectories based on past COP announcements, PES and the 1.5°C Scenario | E13: #VALUE! | G13: Zhong | H13: IRENA (2024, p.26) | I13: Notes: COP announcements trajectory based on data from (Meinshausen et al., 2023); GtCO2 = gigatonne of carbon dioxide; PES = Planned Energy Scenario; COP = conference of the parties (United Nations Climate Change Conference). | J13: https://www.irena.org/-/media/Files/IRENA/Agency/Publication/2024/Nov/IRENA_World_energy_transitions_outlook_2024.pdf | L13: Pending | M13: Pending | N13: Chart to recreate | O13: Line Chart Stacked | P13: Yes | Q13: https://echarts.apache.org/examples/en/editor.html?c=line-stack | R13: Yes | S13: Zhong: Accordint to the footnote, the original data source is Meinshausen, et al. (2023), “NDC factsheets”, 01 December 2023, https://www.climate-resource.com/ tools/ndcs However, I cannot locate the exact data points to replicate the line chart.
A14: 1 | B14: 15 | C14: =_xlfn.CONCAT("M",$B$1,"_C",ChartsM1[[#This Row],[Chapter]],"_",ChartsM1[[#This Row],['#]]) -> M1_C1_15 | D14: The Energy System We Need: Energy Flow in 2050 in a 1.5° aligned scenario | E14: #VALUE! | G14: Ahmad | L14: Pending | M14: Pending | N14: Chart for Direct Use | S14: File Housing Plots is available in a zip folder that is 3GB, downloading, pending
A15: 3 | B15: 17 | C15: =_xlfn.CONCAT("M",$B$1,"_C",ChartsM1[[#This Row],[Chapter]],"_",ChartsM1[[#This Row],['#]]) -> M1_C3_17 | D15: Energy Access in LDCs and Conflict Affected Countries within the Arab States Region | E15: #VALUE! | L15: Pending | M15: Pending | N15: Infographic WITH Data
A16: 3 | B16: 18 | C16: =_xlfn.CONCAT("M",$B$1,"_C",ChartsM1[[#This Row],[Chapter]],"_",ChartsM1[[#This Row],['#]]) -> M1_C3_18 | D16: Share of Population with Electricity Access and Clean Cooking Access in the Arab Region | E16: #VALUE! | G16: Ahmad | H16: Arab future energy index 2023 | United Nations Development Programme. (n.d.). https://www.undp.org/arab-states/publications/arab-future-energy-index-2023 | J16: https://www.undp.org/arab-states/publications/arab-future-energy-index-2023 | K16: https://undp.sharepoint.com/:x:/r/sites/SEHCoreTeam/Shared%20Documents/General/04.%20Sustainable%20Energy%20Academy/SEA%20Charts%20and%20Infographics/SEA%20-%20Charts/Datasets/Module%201%20-%20Datasets%20for%20Charts.xlsx?d=w3f72cf2573e04beea03a0913cad89118&csf=1&web=1&e=ScPEJb&nav=MTVfe0VFNjdDQzdCLTRFQTktNEVFMi05Q0IzLUQ1MzU0QjRCQThFQn0 | L16: In process | M16: Ready | N16: Chart to recreate | O16: Bar Chart categories vertical | P16: Yes | R16: Yes
A17: 3 | B17: 19 | C17: =_xlfn.CONCAT("M",$B$1,"_C",ChartsM1[[#This Row],[Chapter]],"_",ChartsM1[[#This Row],['#]]) -> M1_C3_19 | D17: Inflation by sector | E17: #VALUE! | G17: Zhong | H17: Human Rights Watch (n.d.) | J17: https://www.hrw.org/news/2023/03/09/lebanon-electricity-crisis-exacerbates-poverty-inequality | L17: Pending | M17: Pending | N17: Chart to recreate | O17: Line Chart multi | P17: Yes | Q17: https://echarts.apache.org/examples/en/editor.html?c=line-stack | R17: Yes | S17: Zhong: I cannot locate the exact data points to replicate the line chart.
A18: 3 | B18: 20 | C18: =_xlfn.CONCAT("M",$B$1,"_C",ChartsM1[[#This Row],[Chapter]],"_",ChartsM1[[#This Row],['#]]) -> M1_C3_20 | D18: Total energy subsides value in some of Arab countries (Real 2020 million USD) | E18: #VALUE! | G18: Zhong | H18: Regional Center for Renewable Energy and Energy Efficiency (2023, p.61) | J18: https://www.undp.org/sites/g/files/zskgke326/files/2023-09/final_afex_2023-_18-9-2023.pdf | K18: M1_C3_20 | L18: In process | M18: Ready | N18: Chart to recreate | O18: Bar chart categories horizontal | P18: Yes | Q18: https://echarts.apache.org/examples/en/editor.html?c=bar-y-category | R18: Yes | S18: Zhong: I cannot locate the original chart in green but I was able to find the source chart in the PDF report (p.61): https://www.undp.org/sites/g/files/zskgke326/files/2023-09/final_afex_2023-_18-9-2023.pdf
A19: 3 | B19: 21 | C19: =_xlfn.CONCAT("M",$B$1,"_C",ChartsM1[[#This Row],[Chapter]],"_",ChartsM1[[#This Row],['#]]) -> M1_C3_21 | D19: Renewable energy produced per source per country, 2022 | E19: #VALUE! | G19: Zhong | H19: Regional Center for Renewable Energy and Energy Efficiency (2023, p.36) | J19: https://www.undp.org/sites/g/files/zskgke326/files/2023-09/final_afex_2023-_18-9-2023.pdf | K19: M1_C3_21 | L19: In process | M19: Ready | N19: Chart to recreate | O19: Bar chart stacked vertical | P19: Yes | Q19: https://echarts.apache.org/examples/en/editor.html?c=bar-y-category | R19: Yes | S19: Zhong: I cannot locate the original chart in green but I was able to find the source chart in the PDF report (p.36): https://www.undp.org/sites/g/files/zskgke326/files/2023-09/final_afex_2023-_18-9-2023.pdf
A20: 3 | B20: 23 | C20: =_xlfn.CONCAT("M",$B$1,"_C",ChartsM1[[#This Row],[Chapter]],"_",ChartsM1[[#This Row],['#]]) -> M1_C3_23 | D20: National Renewable Energy Targets in the Arab Region | E20: #VALUE! | L20: In process | N20: Chart for Direct Use
A21: 3 | B21: 25 | C21: =_xlfn.CONCAT("M",$B$1,"_C",ChartsM1[[#This Row],[Chapter]],"_",ChartsM1[[#This Row],['#]],"_1") -> M1_C3_25_1 | D21: Average cost of natural disasters and energy prices in the Caribbean | E21: #VALUE! | G21: Gabriela | H21: Guerson, A., Morsink, J., and Muñoz, S. (2023). Caribbean Climate Crisis Demands Urgent Action by Governments and Investors. IMF Blog. | I21: Sources: EM-DAT, World Economic Outlook; and IMF staff calculations. _x000D_globalpetrolprices.com. Prices for gasoline and diesel as on 20 February, 2023; electricity for June 2022. Note: Left panel - Three subgroups are identified as weather-related natural disasters climatological (incl. drought, wildfire), hydrological (incl. flood, landslide), and meteorological (storm, extreme temperature). Groups of WHD, Pacific and rest of the world are exclusive. LAC = Latin America and the Caribbean; CAPDR = Central _x000D_America, Panama,and the Dominican Republic; RoW = Rest of world. | J21: https://www.imf.org/en/Blogs/Articles/2023/06/27/caribbean-climate-crisis-demands-urgent-action-by-governments-and-investors | K21: M1_C3_25_1 | L21: In process | M21: Ready | N21: Chart to recreate | O21: Bar Chart Vertical | P21: Yes | Q21: Db1. https://echarts.apache.org/examples/en/editor.html?c=pictorialBar-bar-transition; Db2. https://echarts.apache.org/examples/en/editor.html?c=dataset-simple1 | R21: Yes | S21: I've made 2 diferent Db for the combined chart, here is the second one: M1_C3_25_2
A22: 3 | B22: 25 | C22: =_xlfn.CONCAT("M",$B$1,"_C",ChartsM1[[#This Row],[Chapter]],"_",ChartsM1[[#This Row],['#]],"_2") -> M1_C3_25_2 | D22: Average cost of natural disasters and energy prices in the Caribbean | E22: #VALUE! | G22: Gabriela | H22: Guerson, A., Morsink, J., and Muñoz, S. (2023). Caribbean Climate Crisis Demands Urgent Action by Governments and Investors. IMF Blog. | I22: Sources: EM-DAT, World Economic Outlook; and IMF staff calculations. _x000D_globalpetrolprices.com. Prices for gasoline and diesel as on 20 February, 2023; electricity for June 2022. Note: Left panel - Three subgroups are identified as weather-related natural disasters climatological (incl. drought, wildfire), hydrological (incl. flood, landslide), and meteorological (storm, extreme temperature). Groups of WHD, Pacific and rest of the world are exclusive. LAC = Latin America and the Caribbean; CAPDR = Central _x000D_America, Panama,and the Dominican Republic; RoW = Rest of world. | J22: https://www.imf.org/en/Blogs/Articles/2023/06/27/caribbean-climate-crisis-demands-urgent-action-by-governments-and-investors | K22: M1_C3_25_2 | L22: In process | M22: Ready | N22: Chart to recreate | O22: Bar Chart categories vertical | P22: Yes | Q22: Db1. https://echarts.apache.org/examples/en/editor.html?c=pictorialBar-bar-transition; Db2. https://echarts.apache.org/examples/en/editor.html?c=dataset-simple1 | R22: Yes | S22: I've made 2 diferent Db for the combined chart, here is the second one: M1_C3_25_2
A23: 3 | B23: 25 | C23: =_xlfn.CONCAT("M",$B$1,"_C",ChartsM1[[#This Row],[Chapter]],"_",ChartsM1[[#This Row],['#]]) -> M1_C3_25 | D23: Scenarios for green jobs creation in Latin America and the Caribbean, 2020-2030 | E23: #VALUE! | G23: Gabriela | H23: OECD et al. (2022), Latin American Economic Outlook 2022: Towards a Green and Just Transition, OECD Publishing, Paris, https://doi.org/10.1787/3d5554fc-en | I23: Notes: LAC countries included are Argentina, Bolivia, Brazil, Colombia, Ecuador, Guatemala, Mexico, Paraguay and Uruguay. The data refer to an unweighted average over the countries’ forecasts. Green sectors are defined in each country by first identifying the number of green tasks that workers perform in their occupations and then by examining the top ten industries across which those jobs are distributed. The baseline scenario assumes that, in each green sector, value added and employment will follow the same dynamic as in the past ten years. The counterfactual scenarios are defined according to the impact of a green policy that aims to boost investment in fixed and human capital, with a positive impact on value‑added growth in each green sector. The high‑impact scenario assumes that the value added in each sector will increase by 3 percentage points per year, adjusting to the new equilibrium. The medium‑impact scenario assumes that the value added will increase by 2 percentage points per year, while the low‑impact scenario assumes it will decrease by 1 percentage point per year. In all forecasts, total factor productivity will increase by 1 percentage point due to lower climate damages and new technology‑induced change. Employment change is forecast using the estimated short‑term elasticity to the value added, applying a panel dynamic model, defined by each sector and country, in the last ten years. Sources: Authors’ estimates based on Labour Force Surveys, National Accounts data by industries, (Vona et al., 2018[13]) and (Hardy, Keister and Lewandowski, 2018[14]). | J23: https://www.oecd.org/en/publications/latin-american-economic-outlook-2022_3d5554fc-en.html | K23: M1_C3_25 | L23: In process | M23: Ready | N23: Chart to recreate | O23: Line Chart Multi | P23: Yes | Q23: https://echarts.apache.org/examples/en/editor.html?c=line-race | R23: Yes | S23: Footnotes are the author's
A24: 3 | B24: 26 | C24: =_xlfn.CONCAT("M",$B$1,"_C",ChartsM1[[#This Row],[Chapter]],"_",ChartsM1[[#This Row],['#]]) -> M1_C3_26 | D24: Clean Energy Equlty Index (CEEI) | E24: #VALUE! | J24: https://undpgeohub.org/maps/338 | L24: In process | N24: Maps to recreate
A25: 3 | B25: 27 | C25: =_xlfn.CONCAT("M",$B$1,"_C",ChartsM1[[#This Row],[Chapter]],"_",ChartsM1[[#This Row],['#]]) -> M1_C3_27 | D25: Crude oil production, global ranking, 2022 | E25: #VALUE! | G25: Gabriela | H25: IEA. (2022). Africa - Oil: Crude oil production, global ranking, 2022. | I25: Source: World Energy Balances | J25: https://www.iea.org/regions/africa/oil | K25: M1_C3_27 | L25: In process | M25: Ready | N25: Chart to recreate | O25: Morphing between Map and Bar | P25: Yes | Q25: https://echarts.apache.org/examples/en/editor.html?c=map-bar-morph | R25: Yes
A26: 3 | B26: 28 | C26: =_xlfn.CONCAT("M",$B$1,"_C",ChartsM1[[#This Row],[Chapter]],"_",ChartsM1[[#This Row],['#]]) -> M1_C3_28 | D26: Total electricity production, regional ranking, 2022 | E26: #VALUE! | G26: Gabriela | H26: IEA. (2022). Africa - Electricity: Total electricity production, regional ranking, 2022 | I26: Source: Electricity Information | J26: https://www.iea.org/regions/africa/electricity | K26: M1_C3_28 | L26: In process | M26: Ready | N26: Chart to recreate | O26: Morphing between Map and Bar | P26: Yes | Q26: https://echarts.apache.org/examples/en/editor.html?c=map-bar-morph | R26: Yes
A27: 3 | B27: 29 | C27: =_xlfn.CONCAT("M",$B$1,"_C",ChartsM1[[#This Row],[Chapter]],"_",ChartsM1[[#This Row],['#]]) -> M1_C3_29 | D27: Total electricity production, regional ranking, 2022 | E27: #VALUE! | G27: Gabriela | H27: IEA. (2022). Africa - Electricity: Total electricity production, global ranking, 2022 | I27: Source: Electricity Information | J27: https://www.iea.org/regions/africa/electricity | K27: M1_C3_29 | L27: In process | M27: Ready | N27: Chart to recreate | O27: Morphing between Map and Bar | P27: Yes | Q27: https://echarts.apache.org/examples/en/editor.html?c=map-bar-morph | R27: Yes | S27: What is the difference between 28 and 29?
A28: 1 | B28: 37 | C28: =_xlfn.CONCAT("M",$B$1,"_C",ChartsM1[[#This Row],[Chapter]],"_",ChartsM1[[#This Row],['#]]) -> M1_C1_37 | D28: Share of renewable electricity generation by technology, 2000-2030 | E28: #VALUE! | G28: Gabriela | H28: IEA. (2023). Share of renewable electricity generation by technology, 2000-2030 | I28: Notes: Electricity generation from wind and solar PV indicate potential generation including current curtailment rates. However, it does not project future curtailment of wind and solar PV, which may be significant in a few countries by 2028. | J28: https://www.iea.org/data-and-statistics/charts/share-of-renewable-electricity-generation-by-technology-2000-2030 | K28: M1_C1_37 | L28: Pending | M28: Ready | N28: Chart to recreate | O28: Line Chart Multi | P28: Yes | Q28: https://echarts.apache.org/examples/en/editor.html?c=line-race | R28: Yes
A29: 3 | B29: 30 | C29: =_xlfn.CONCAT("M",$B$1,"_C",ChartsM1[[#This Row],[Chapter]],"_",ChartsM1[[#This Row],['#]]) -> M1_C3_30 | D29: Evolution of electricity generation sources in Asia Pacific since 2000 | E29: #VALUE! | G29: Divya | H29: International Energy Agency. (n.d.). Electricity – Asia Pacific. IEA. Retrieved June 24, 2025, from https://www.iea.org/regions/asia-pacific/electricity | J29: https://www.iea.org/regions/africa/electricity | K29: https://www.iea.org/regions/asia-pacific/electricity | L29: In process | M29: Ready | N29: Chart to recreate | O29: Line Chart Multi | P29: Yes | Q29: https://echarts.apache.org/examples/data/thumb/line-race.webp?_v_=1749990823367 | R29: Yes
A30: 3 | B30: 31 | C30: =_xlfn.CONCAT("M",$B$1,"_C",ChartsM1[[#This Row],[Chapter]],"_",ChartsM1[[#This Row],['#]]) -> M1_C3_31 | D30: Reduction in cooling energy demand in the SDS compared to the STEPS | E30: #VALUE! | G30: Divya | H30: International Energy Agency. (n.d.). Reduction in cooling energy demand in the SDS compared to the STEPS, 2015–2040. IEA. Retrieved June 24, 2025, from https://www.iea.org/data-and-statistics/charts/reduction-in-cooling-energy-demand-in-the-sds-compared-to-the-steps-2015-2040 | J30: https://www.iea.org/data-and-statistics/charts/reduction-in-cooling-energy-demand-in-the-sds-compared-to-the-steps-2015-2040 | K30: https://www.iea.org/data-and-statistics/charts/reduction-in-cooling-energy-demand-in-the-sds-compared-to-the-steps-2015-2040 | L30: In process | M30: Ready | N30: Chart to recreate | O30: Line Chart Multi | P30: Yes | Q30: https://echarts.apache.org/examples/en/editor.html?c=area-stack | R30: Yes
A31: 3 | B31: 32 | C31: =_xlfn.CONCAT("M",$B$1,"_C",ChartsM1[[#This Row],[Chapter]],"_",ChartsM1[[#This Row],['#]]) -> M1_C3_32 | D31: Energy poverty levels are high in some countries | E31: #VALUE! | G31: Divya | L31: In process | M31: In process | N31: Chart to recreate | P31: Yes | Q31: https://echarts.apache.org/examples/en/editor.html?c=map-bar-morph | S31: Can't find the dataset
A32: 3 | B32: 33 | C32: =_xlfn.CONCAT("M",$B$1,"_C",ChartsM1[[#This Row],[Chapter]],"_",ChartsM1[[#This Row],['#]]) -> M1_C3_33 | D32: Total energy suply by country | E32: #VALUE! | G32: Divya | L32: In process | M32: In process | N32: Chart to recreate | O32: Bar Chart Stacked Horizontal | P32: Yes | Q32: https://echarts.apache.org/examples/en/editor.html?c=bar-race-country
A33: 3 | B33: 34 | C33: =_xlfn.CONCAT("M",$B$1,"_C",ChartsM1[[#This Row],[Chapter]],"_",ChartsM1[[#This Row],['#]]) -> M1_C3_34 | D33: Electricity generated from fossil fuels, 2022 | E33: #VALUE! | G33: Divya | H33: International Energy Agency. (n.d.). World energy statistics. IEA. Retrieved June 24, 2025, from https://www.iea.org/data-and-statistics/data-product/world-energy-statistics | K33: https://www.iea.org/data-and-statistics/data-product/world-energy-statistics | L33: Ready | M33: Ready | N33: Chart to recreate | P33: Yes | Q33: https://echarts.apache.org/examples/en/editor.html?c=bar-race-country
A34: 3 | B34: 35 | C34: =_xlfn.CONCAT("M",$B$1,"_C",ChartsM1[[#This Row],[Chapter]],"_",ChartsM1[[#This Row],['#]]) -> M1_C3_35 | D34: Relative CBAM Exposure Index, Eastern Europe & Central Asia | E34: #VALUE! | L34: In process | N34: Maps to recreate
A35: 3 | B35: 36 | C35: =_xlfn.CONCAT("M",$B$1,"_C",ChartsM1[[#This Row],[Chapter]],"_",ChartsM1[[#This Row],['#]]) -> M1_C3_36 | D35: Nationally determined contributions and net-zero emissions targets | E35: #VALUE! | G35: Divya | H35: World Resources Institute. (n.d.). Net-Zero Tracker. Climate Watch. Retrieved June 24, 2025, from https://www.climatewatchdata.org/net-zero-tracker | J35: https://www.climatewatchdata.org/net-zero-tracker | K35: https://www.climatewatchdata.org/ndcs-explore?category=2025_ndc_tracker | L35: Ready | M35: Ready | N35: Chart to recreate | P35: Yes | Q35: https://echarts.apache.org/examples/en/editor.html?c=map-HK
A36: 3 | B36: 22 | C36: =_xlfn.CONCAT("M",$B$1,"_C",ChartsM1[[#This Row],[Chapter]],"_",ChartsM1[[#This Row],['#]]) -> M1_C3_22 | D36: Renewable Energy Installed Capacities and Share in the Total Capacity in 2020 | E36: #VALUE! | L36: Deleted | M36: Deleted | N36: Infographic WITH Data
A37: 3 | B37: 24 | C37: =_xlfn.CONCAT("M",$B$1,"_C",ChartsM1[[#This Row],[Chapter]],"_",ChartsM1[[#This Row],['#]]) -> M1_C3_24 | D37: Residential Electricity Costs in the Arab Region | E37: #VALUE! | G37: Zhong | H37: Regional Center for Renewable Energy and Energy Efficiency (2023, p.62) | J37: https://www.undp.org/sites/g/files/zskgke326/files/2023-09/final_afex_2023-_18-9-2023.pdf | L37: Deleted | M37: Deleted | N37: Chart to recreate

Sheet Module2
A1: Module | B1: 2
A2: Chapter | B2: # | C2: Figure ID | D2: Title | E2: Screenshot | F2: New Screenshot | G2: Lead | H2: Source (APA) | I2: Footnote | J2: Source Link | K2: Dataset Link | L2: Chart Status | M2: Dataset Status | N2: Category | O2: Chart Type | P2: Apache Possible | Q2: Apache Link | R2: Automation Possible | S2: Notes
A3: 2 | B3: 0 | C3: =_xlfn.CONCAT("M",$B$1,"_C",ChartsM2[[#This Row],[Chapter]],"_",ChartsM2[[#This Row],['#]]) -> M2_C2_0 | D3: Number of People without access to electricity | E3: #VALUE! | N3: Chart for Direct Use
A4: 2 | B4: 1 | C4: =_xlfn.CONCAT("M",$B$1,"_C",ChartsM2[[#This Row],[Chapter]],"_",ChartsM2[[#This Row],['#]]) -> M2_C2_1 | D4: Number of People without access to electricity | E4: #VALUE! | N4: Chart for Direct Use
A5: 2 | B5: 2 | C5: =_xlfn.CONCAT("M",$B$1,"_C",ChartsM2[[#This Row],[Chapter]],"_",ChartsM2[[#This Row],['#]]) -> M2_C2_2 | D5: Number of People with and without access to clean cooking fuels | E5: #VALUE! | H5: World Bank., 2025 | J5: https://datacatalog.worldbank.org/search/dataset/0037712/World-Development-Indicators | N5: Chart for Direct Use | O5: Map - Choropleth map
A6: 2 | B6: 48 | C6: =_xlfn.CONCAT("M",$B$1,"_C",ChartsM2[[#This Row],[Chapter]],"_",ChartsM2[[#This Row],['#]]) -> M2_C2_48 | D6: Annual increases in electrification and population, by region, 2020-22 | E6: #VALUE! | G6: Gabriela | H6: IEA, IRENA, UNSD, World Bank, WHO. (2024). Tracking SDG 7: The Energy Progress Report. World Bank, Washington DC. © World Bank. License: Creative Commons Attribution—NonCommercial 3.0 IGO (CC BY-NC 3.0 IGO). | I6: Source: World Bank, 2024 | J6: https://trackingsdg7.esmap.org/data/files/download-documents/sdg7-report2024-0611-v9-highresforweb.pdf | K6: Module 2 - Datasets for Charts.xlsx | L6: In process | M6: Ready | N6: Chart to recreate | O6: Bar Chart Categories Vertical | P6: Yes | Q6: https://echarts.apache.org/examples/en/editor.html?c=bar-negative&lang=ts | R6: Yes
A7: 2 | B7: 47 | C7: =_xlfn.CONCAT("M",$B$1,"_C",ChartsM2[[#This Row],[Chapter]],"_",ChartsM2[[#This Row],['#]],"_1") -> M2_C2_47_1 | D7: Increases in global access to electricity in urban and rural areas, 2010, 2020, and 2022 | E7: #VALUE! | G7: Gabriela | H7: IEA, IRENA, UNSD, World Bank, WHO. (2024). Tracking SDG 7: The Energy Progress Report. World Bank, Washington DC. © World Bank. License: Creative Commons Attribution—NonCommercial 3.0 IGO (CC BY-NC 3.0 IGO). | I7: Source: World Bank, 2024 | J7: https://trackingsdg7.esmap.org/data/files/download-documents/sdg7-report2024-0611-v9-highresforweb.pdf | K7: Module 2 - Datasets for Charts.xlsx | L7: Pending | M7: Ready | N7: Chart to recreate | O7: Bar Chart Stacked Vertical | P7: Yes | Q7: https://echarts.apache.org/examples/en/editor.html?c=dynamic-data | R7: Yes | S7: Shouldn't the dataset linked to M_C2_50 actually be linked to M_C2_47? Where does the M_C2_47 Dataset come from? It does not match the Source Data
A8: 2 | B8: 47 | C8: =_xlfn.CONCAT("M",$B$1,"_C",ChartsM2[[#This Row],[Chapter]],"_",ChartsM2[[#This Row],['#]],"_2") -> M2_C2_47_2 | D8: Increases in global access to electricity in urban and rural areas, 2010, 2020, and 2022 | E8: #VALUE! | G8: Gabriela | H8: IEA, IRENA, UNSD, World Bank, WHO. (2024). Tracking SDG 7: The Energy Progress Report. World Bank, Washington DC. © World Bank. License: Creative Commons Attribution—NonCommercial 3.0 IGO (CC BY-NC 3.0 IGO). | I8: Source: World Bank, 2024 | J8: https://trackingsdg7.esmap.org/data/files/download-documents/sdg7-report2024-0611-v9-highresforweb.pdf | K8: Module 2 - Datasets for Charts.xlsx | L8: Pending | M8: Ready | N8: Chart to recreate | O8: Bar Chart Stacked Vertical | P8: Yes | Q8: https://echarts.apache.org/examples/en/editor.html?c=dynamic-data | R8: Yes | S8: Shouldn't the dataset linked to M_C2_50 actually be linked to M_C2_47? Where does the M_C2_47 Dataset come from? It does not match the Source Data
A9: 2 | B9: 47 | C9: =_xlfn.CONCAT("M",$B$1,"_C",ChartsM2[[#This Row],[Chapter]],"_",ChartsM2[[#This Row],['#]],"_3") -> M2_C2_47_3 | D9: Increases in global access to electricity in urban and rural areas, 2010, 2020, and 2022 | E9: #VALUE! | G9: Gabriela | H9: IEA, IRENA, UNSD, World Bank, WHO. (2024). Tracking SDG 7: The Energy Progress Report. World Bank, Washington DC. © World Bank. License: Creative Commons Attribution—NonCommercial 3.0 IGO (CC BY-NC 3.0 IGO). | I9: Source: World Bank, 2024 | J9: https://trackingsdg7.esmap.org/data/files/download-documents/sdg7-report2024-0611-v9-highresforweb.pdf | K9: Module 2 - Datasets for Charts.xlsx | L9: Pending | M9: Ready | N9: Chart to recreate | O9: Line Chart Multi | P9: Yes | Q9: https://echarts.apache.org/examples/en/editor.html?c=dynamic-data | R9: Yes | S9: Shouldn't the dataset linked to M_C2_50 actually be linked to M_C2_47? Where does the M_C2_47 Dataset come from? It does not match the Source Data
A10: 2 | B10: 13 | C10: =_xlfn.CONCAT("M",$B$1,"_C",ChartsM2[[#This Row],[Chapter]],"_",ChartsM2[[#This Row],['#]]) -> M2_C2_13 | D10: Number of people living in urban and rural areas, World | E10: #VALUE! | N10: Chart for Direct Use
A11: 2 | B11: 49 | C11: =_xlfn.CONCAT("M",$B$1,"_C",ChartsM2[[#This Row],[Chapter]],"_",ChartsM2[[#This Row],['#]]) -> M2_C2_49 | D11: Annual growth in electricity access and population in urban and rural areas by region, 2020-22 | E11: #VALUE! | G11: Gabriela | H11: IEA, IRENA, UNSD, World Bank, WHO. (2024). Tracking SDG 7: The Energy Progress Report. World Bank, Washington DC. © World Bank. License: Creative Commons Attribution—NonCommercial 3.0 IGO (CC BY-NC 3.0 IGO). | I11: Source: World Bank, 2024 | J11: https://trackingsdg7.esmap.org/data/files/download-documents/sdg7-report2024-0611-v9-highresforweb.pdf | K11: Module 2 - Datasets for Charts.xlsx | M11: Ready | N11: Chart to recreate | O11: Bar Chart Categories Vertical | P11: Yes | Q11: https://echarts.apache.org/examples/en/editor.html?c=bar-label-rotation | R11: Yes
A12: 2 | B12: 14 | C12: =_xlfn.CONCAT("M",$B$1,"_C",ChartsM2[[#This Row],[Chapter]],"_",ChartsM2[[#This Row],['#]]) -> M2_C2_14 | D12: Share of urban population living in slums, 2020 | E12: #VALUE! | N12: Chart for Direct Use
A13: 2 | B13: 50 | C13: =_xlfn.CONCAT("M",$B$1,"_C",ChartsM2[[#This Row],[Chapter]],"_",ChartsM2[[#This Row],['#]],"_1") -> M2_C2_50_1 | D13: Increases in global access to electricity in least-developed countries and countries affected by fragility, conflict, and violence, 2010, 2020, and 2022 | E13: #VALUE! | G13: Gabriela | H13: IEA, IRENA, UNSD, World Bank, WHO. (2024). Tracking SDG 7: The Energy Progress Report. World Bank, Washington DC. © World Bank. License: Creative Commons Attribution—NonCommercial 3.0 IGO (CC BY-NC 3.0 IGO). | I13: Source: World Bank, 2024 | J13: https://trackingsdg7.esmap.org/data/files/download-documents/sdg7-report2024-0611-v9-highresforweb.pdf | K13: Module 2 - Datasets for Charts.xlsx | L13: Pending | M13: Pending | N13: Chart to recreate | O13: Bar Chart Stacked Vertical | P13: Yes | Q13: https://echarts.apache.org/examples/en/editor.html?c=dynamic-data | R13: Yes | S13: Fragile and conflict-affected countries Bar
A14: 2 | B14: 50 | C14: =_xlfn.CONCAT("M",$B$1,"_C",ChartsM2[[#This Row],[Chapter]],"_",ChartsM2[[#This Row],['#]],"_2") -> M2_C2_50_2 | D14: Increases in global access to electricity in least-developed countries and countries affected by fragility, conflict, and violence, 2010, 2020, and 2022 | E14: #VALUE! | G14: Gabriela | H14: IEA, IRENA, UNSD, World Bank, WHO. (2024). Tracking SDG 7: The Energy Progress Report. World Bank, Washington DC. © World Bank. License: Creative Commons Attribution—NonCommercial 3.0 IGO (CC BY-NC 3.0 IGO). | I14: Source: World Bank, 2024 | J14: https://trackingsdg7.esmap.org/data/files/download-documents/sdg7-report2024-0611-v9-highresforweb.pdf | K14: Module 2 - Datasets for Charts.xlsx | L14: Pending | M14: Pending | N14: Chart to recreate | O14: Bar Chart Stacked Vertical | P14: Yes | Q14: https://echarts.apache.org/examples/en/editor.html?c=dynamic-data | R14: Yes | S14: Least-developed countries Bar
A15: 2 | B15: 50 | C15: =_xlfn.CONCAT("M",$B$1,"_C",ChartsM2[[#This Row],[Chapter]],"_",ChartsM2[[#This Row],['#]],"_2") -> M2_C2_50_2 | D15: Increases in global access to electricity in least-developed countries and countries affected by fragility, conflict, and violence, 2010, 2020, and 2022 | E15: #VALUE! | G15: Gabriela | H15: IEA, IRENA, UNSD, World Bank, WHO. (2024). Tracking SDG 7: The Energy Progress Report. World Bank, Washington DC. © World Bank. License: Creative Commons Attribution—NonCommercial 3.0 IGO (CC BY-NC 3.0 IGO). | I15: Source: World Bank, 2024 | J15: https://trackingsdg7.esmap.org/data/files/download-documents/sdg7-report2024-0611-v9-highresforweb.pdf | K15: Module 2 - Datasets for Charts.xlsx | L15: Pending | M15: Pending | N15: Chart to recreate | O15: Line Chart Multi | P15: Yes | Q15: https://echarts.apache.org/examples/en/editor.html?c=dynamic-data | R15: Yes | S15: Relative share for both, Line
A16: 2 | B16: 51 | C16: =_xlfn.CONCAT("M",$B$1,"_C",ChartsM2[[#This Row],[Chapter]],"_",ChartsM2[[#This Row],['#]]) -> M2_C2_51 | D16: Share of population with access to clean cooking fuels and technologies, 2022 (percent) | E16: #VALUE! | G16: Gabriela | H16: IEA, IRENA, UNSD, World Bank, WHO. (2024). Tracking SDG 7: The Energy Progress Report. World Bank, Washington DC. © World Bank. License: Creative Commons Attribution—NonCommercial 3.0 IGO (CC BY-NC 3.0 IGO). | I16: Source: WHO, 2024 | J16: https://trackingsdg7.esmap.org/data/files/download-documents/sdg7-report2024-0611-v9-highresforweb.pdf | K16: Module 2 - Datasets for Charts.xlsx | L16: Pending | M16: Review pending | N16: Maps to recreate | O16: Population Density of HongKong (2011) | P16: Yes | Q16: https://echarts.apache.org/examples/en/editor.html?c=map-HK | R16: No
A17: 2 | B17: 52 | C17: =_xlfn.CONCAT("M",$B$1,"_C",ChartsM2[[#This Row],[Chapter]],"_",ChartsM2[[#This Row],['#]]) -> M2_C2_52 | D17: Share of the rural and urban population with access to clean fuels for cooking, World | E17: #VALUE! | G17: Gabriela | H17: World Bank and International Energy Agency. (2025). Share of the rural and urban population with access to clean fuels for cooking, World | I17: Data source: World Bank and International Energy Agency, 2025 - processed by Our World in Data | J17: https://ourworldindata.org/grapher/share-of-the-rural-and-urban-population-with-access-to-clean-fuels-for-cooking | L17: In process | N17: Chart for Direct Use | S17: No dataset needed
A18: 2 | B18: 53 | C18: =_xlfn.CONCAT("M",$B$1,"_C",ChartsM2[[#This Row],[Chapter]],"_",ChartsM2[[#This Row],['#]]) -> M2_C2_53 | D18: Population with access to clean fuels and technologies for cooking by SDG region (percent) | E18: #VALUE! | G18: Zhong | H18: International Energy Agency et al. (2024, p.55) | I18: Source: WHO 2024a. SDG = Sustainable Development Goal. | J18: https://trackingsdg7.esmap.org/data/files/download-documents/sdg7-report2024-0611-v9-highresforweb.pdf | K18: M2_C_53 | L18: In process | M18: Ready | N18: Chart to recreate | O18: Bar Chart Categories Horizontal | P18: Yes | Q18: https://echarts.apache.org/examples/en/editor.html?c=bar-y-category | R18: Yes
A19: 2 | B19: 54 | C19: =_xlfn.CONCAT("M",$B$1,"_C",ChartsM2[[#This Row],[Chapter]],"_",ChartsM2[[#This Row],['#]],"_1") -> M2_C2_54_1 | D19: Percentage of People Mainly Using Each Type of Cooking Fuel in Low- and Middle-Income Countries, Urban, Rural, and Overall | E19: #VALUE! | G19: Zhong | H19: International Energy Agency et al. (2024, p.56) | I19: Source: WHO 2024a. | J19: https://trackingsdg7.esmap.org/data/files/download-documents/sdg7-report2024-0611-v9-highresforweb.pdf | K19: M2_C_54 | M19: Ready | N19: Chart to recreate | O19: Line Chart Multi | P19: Yes | Q19: https://echarts.apache.org/examples/en/editor.html?c=line-stack | R19: Yes | S19: Zhong: The original data source is WHO. 2024. Global Health Observatory (Household Energy Database). Geneva: WHO. https://www.who.int/data/ gho/data/themes/air-pollution/who-household-energy-db. I also included the most recent data (2021 & 2022) from here: https://www.who.int/data/gho/data/indicators/indicator-details/GHO/proportion-of-population-with-primary-reliance-on-fuels-and-technologies-for-cooking-by-fuel-type No 1 -> Urban Chart
A20: 2 | B20: 54 | C20: =_xlfn.CONCAT("M",$B$1,"_C",ChartsM2[[#This Row],[Chapter]],"_",ChartsM2[[#This Row],['#]],"_2") -> M2_C2_54_2 | D20: Percentage of People Mainly Using Each Type of Cooking Fuel in Low- and Middle-Income Countries, Urban, Rural, and Overall | E20: #VALUE! | G20: Zhong | H20: International Energy Agency et al. (2024, p.56) | I20: Source: WHO 2024a. | J20: https://trackingsdg7.esmap.org/data/files/download-documents/sdg7-report2024-0611-v9-highresforweb.pdf | K20: M2_C_54 | M20: Ready | N20: Chart to recreate | O20: Line Chart Multi | P20: Yes | Q20: https://echarts.apache.org/examples/en/editor.html?c=line-stack | R20: Yes | S20: Zhong: The original data source is WHO. 2024. Global Health Observatory (Household Energy Database). Geneva: WHO. https://www.who.int/data/ gho/data/themes/air-pollution/who-household-energy-db. I also included the most recent data (2021 & 2022) from here: https://www.who.int/data/gho/data/indicators/indicator-details/GHO/proportion-of-population-with-primary-reliance-on-fuels-and-technologies-for-cooking-by-fuel-type No 2 -> Rural Chart
A21: 2 | B21: 54 | C21: =_xlfn.CONCAT("M",$B$1,"_C",ChartsM2[[#This Row],[Chapter]],"_",ChartsM2[[#This Row],['#]],"_3") -> M2_C2_54_3 | D21: Percentage of People Mainly Using Each Type of Cooking Fuel in Low- and Middle-Income Countries, Urban, Rural, and Overall | E21: #VALUE! | G21: Zhong | H21: International Energy Agency et al. (2024, p.56) | I21: Source: WHO 2024a. | J21: https://trackingsdg7.esmap.org/data/files/download-documents/sdg7-report2024-0611-v9-highresforweb.pdf | K21: M2_C_54 | M21: Ready | N21: Chart to recreate | O21: Line Chart Multi | P21: Yes | Q21: https://echarts.apache.org/examples/en/editor.html?c=line-stack | R21: Yes | S21: Zhong: The original data source is WHO. 2024. Global Health Observatory (Household Energy Database). Geneva: WHO. https://www.who.int/data/ gho/data/themes/air-pollution/who-household-energy-db. I also included the most recent data (2021 & 2022) from here: https://www.who.int/data/gho/data/indicators/indicator-details/GHO/proportion-of-population-with-primary-reliance-on-fuels-and-technologies-for-cooking-by-fuel-type No 3 -> Total Chart
A22: 2 | B22: 55 | C22: =_xlfn.CONCAT("M",$B$1,"_C",ChartsM2[[#This Row],[Chapter]],"_",ChartsM2[[#This Row],['#]]) -> M2_C2_55 | D22: Share of all deaths altributed to sub-oplimal lemperatures | E22: #VALUE! | G22: Zhong | H22: Zhao et al. (2021) | I22: Data sources: Zhao et al. (2021). Global, regional, and national burden of mortality associated with non-optimal ambient temperatures from 2000 to 2019: a three-stage modelling study. – processed by Our World in Data | J22: https://ourworldindata.org/grapher/temp-deaths-zhao | K22: M2_C_55 | M22: Ready | N22: Chart to recreate | O22: Bar Chart Stacked Horizontal | P22: Yes | Q22: https://echarts.apache.org/examples/en/editor.html?c=bar-y-category-stack | R22: Yes
A23: 2 | B23: 56 | C23: =_xlfn.CONCAT("M",$B$1,"_C",ChartsM2[[#This Row],[Chapter]],"_",ChartsM2[[#This Row],['#]]) -> M2_C2_56 | D23: Share of population living in a hot climate, 2022, and penetration of air conditioners, 2000-2022 | E23: #VALUE! | G23: Zhong | H23: International Energy Agency (2023) | I23: Notes AC = Air-conditioning unit. A climate is assumed to be “hot” when the sum total of the difference between the daily mean outdoor temperature and the base temperature of 10°C (cooling degree days with base temperature of 10°C) adds up to at least 5 000 over the course of one year. Need for space cooling does not necessarily correspond to the need for installing space cooling equipment, but rather a need to consider cooling-oriented design options during the building construction phase. | J23: https://www.iea.org/data-and-statistics/charts/share-of-population-living-in-a-hot-climate-2022-and-penetration-of-air-conditioners-2000-2022 | K23: M2_C_56 | M23: Ready | N23: Chart to recreate | O23: Bar Chart Categories Vertical | P23: Yes | Q23: https://echarts.apache.org/examples/en/editor.html?c=dataset-simple0 | R23: Yes | S23: Zhong: the original chart screenshot is from here: https://www.unicef.org/innocenti/cooling-dilemma-amid-climate-change
A24: 2 | B24: 57 | C24: =_xlfn.CONCAT("M",$B$1,"_C",ChartsM2[[#This Row],[Chapter]],"_",ChartsM2[[#This Row],['#]]) -> M2_C2_57 | D24: The "Energy Ladder" - The dominant energy source for cooking and heating, by level of income | E24: #VALUE! | G24: Zhong | H24: Roser (2021) | J24: https://ourworldindata.org/energy-ladder | N24: Chart for Direct Use | S24: Zhong: the diagram is based on WHO (2006). Fuel for Life : Household Energy and Health. https://iris.who.int/bitstream/handle/10665/43421/9241563168_eng.pdf?sequence=1
A25: 2 | B25: 58 | C25: =_xlfn.CONCAT("M",$B$1,"_C",ChartsM2[[#This Row],[Chapter]],"_",ChartsM2[[#This Row],['#]],"_1") -> M2_C2_58_1 | D25: Top 10 countries with rural and urban poor populations at high risk (2023) | E25: #VALUE! | G25: Zhong | H25: Sustainable Energy for All (2023) | I25: Zhong's note: Consider adding a definition of high risk, such as "high risk refers to a lack of access to cooling for thermal comfort, food and agricultural produce and medical products" | J25: https://www.seforall.org/chilling-prospects-access-to-cooling-gaps-2023/risk-profiles#1 | K25: M2_C_58 | M25: Ready | N25: Chart to recreate | O25: Bar Chart Categories Horizontal | P25: Yes | R25: Yes | S25: Zhong: The table title is vague, consider "Top 10 countries with rural and urban poor populations at high risk of cooling access (2023)". The table can be directly used or redesigned in Excel.
A26: 2 | B26: 58 | C26: =_xlfn.CONCAT("M",$B$1,"_C",ChartsM2[[#This Row],[Chapter]],"_",ChartsM2[[#This Row],['#]],"_2") -> M2_C2_58_2 | D26: Top 10 countries with rural and urban poor populations at high risk (2023) | E26: #VALUE! | G26: Zhong | H26: Sustainable Energy for All (2023) | I26: Zhong's note: Consider adding a definition of high risk, such as "high risk refers to a lack of access to cooling for thermal comfort, food and agricultural produce and medical products" | J26: https://www.seforall.org/chilling-prospects-access-to-cooling-gaps-2023/risk-profiles#1 | K26: M2_C_58 | M26: Ready | N26: Chart to recreate | O26: Bar Chart Categories Vertical | P26: Yes | R26: Yes | S26: Zhong: The table title is vague, consider "Top 10 countries with rural and urban poor populations at high risk of cooling access (2023)". The table can be directly used or redesigned in Excel.
A27: 2 | B27: 59 | C27: =_xlfn.CONCAT("M",$B$1,"_C",ChartsM2[[#This Row],[Chapter]],"_",ChartsM2[[#This Row],['#]]) -> M2_C2_59 | D27: ANNUAL INTERNATIONAL PUBLIC FINANCIAL FLOWS TO RENEWABLES, BY REGION, 2010-22 | E27: #VALUE! | G27: Divya | H27: World Bank. (2024). Tracking SDG 7: The Energy Progress Report 2024. World Bank Group. https://documents1.worldbank.org/curated/en/099031225175211404/pdf/P506480-b566c620-4bc2-4b71-866e-05d3db3de1ba.pdf | J27: https://documents1.worldbank.org/curated/en/099031225175211404/pdf/P506480-b566c620-4bc2-4b71-866e-05d3db3de1ba.pdf | M27: Ready | N27: Chart to recreate | O27: Bar Chart Stacked Vertical | P27: Yes | Q27: https://echarts.apache.org/examples/en/editor.html?c=bar-stack-borderRadius | R27: Yes
A28: 2 | B28: 60 | C28: =_xlfn.CONCAT("M",$B$1,"_C",ChartsM2[[#This Row],[Chapter]],"_",ChartsM2[[#This Row],['#]]) -> M2_C2_60 | D28: INTERNATIONAL PUBLIC FINANCIAL FLOWS TO LEAST-DEVELOPED COUNTRIES, LANDLOCKED DEVELOPING COUNTRIES, AND SMALL ISLAND DEVELOPING STATES, 2010-22 | E28: #VALUE! | G28: Divya | H28: ESMAP, IEA, IRENA, UNSD, & World Bank. (2024). Tracking SDG 7: The Energy Progress Report 2024 – Chapter 5: International Public Financial Flows to Developing Countries. World Bank Group. https://trackingsdg7.esmap.org/data/files/download-documents/SDG7%20-%20Report%202024%20-%20Chapter5-InterPibliFinanFlowsDevelop.pdf | J28: https://trackingsdg7.esmap.org/data/files/download-documents/SDG7%20-%20Report%202024%20-%20Chapter5-InterPibliFinanFlowsDevelop.pdf | M28: Ready | N28: Chart to recreate | O28: Line Chart Multi | P28: Yes | Q28: https://echarts.apache.org/examples/en/editor.html?c=line-simple | R28: Yes
A29: 2 | B29: 61 | C29: =_xlfn.CONCAT("M",$B$1,"_C",ChartsM2[[#This Row],[Chapter]],"_",ChartsM2[[#This Row],['#]]) -> M2_C2_61 | D29: GLOBAL INVESTMENT REQUIRED FOR UNIVERSAL ELECTRICITY ACCESS, BY SCENARIO (BILLIONS OF DOLLARS) | E29: #VALUE! | G29: Divya | H29: Can't find | M29: Ready | N29: Chart to recreate | O29: Bar Chart Categories Vertical | P29: Yes | Q29: https://echarts.apache.org/examples/en/editor.html?c=bar-label-rotation | R29: Yes
A30: 2 | B30: 62 | C30: =_xlfn.CONCAT("M",$B$1,"_C",ChartsM2[[#This Row],[Chapter]],"_",ChartsM2[[#This Row],['#]],"_1") -> M2_C2_62_1 | D30: Share of the population gaining access to clean cooking by technology in the " Access for All" scenario 2022-2030 | E30: #VALUE! | G30: Divya | H30: International Energy Agency (IEA). (2022). A vision for clean cooking access for all: Executive summary. https://www.iea.org/reports/a-vision-for-clean-cooking-access-for-all/executive-summary | I30: Share of population gaining access by technology in the Access for All scenario, 2022-2030 | J30: https://www.iea.org/reports/a-vision-for-clean-cooking-access-for-all/executive-summary | M30: Ready | N30: Chart to recreate | O30: Bar Chart Vertical | P30: Yes | Q30: https://echarts.apache.org/examples/en/editor.html?c=pie-rich-text | R30: Yes
A31: 2 | B31: 62 | C31: =_xlfn.CONCAT("M",$B$1,"_C",ChartsM2[[#This Row],[Chapter]],"_",ChartsM2[[#This Row],['#]],"_2") -> M2_C2_62_2 | D31: Share of the population gaining access to clean cooking by technology in the " Access for All" scenario 2022-2030 | E31: #VALUE! | G31: Divya | H31: International Energy Agency (IEA). (2022). A vision for clean cooking access for all: Executive summary. https://www.iea.org/reports/a-vision-for-clean-cooking-access-for-all/executive-summary | I31: Share of population gaining access by technology in the Access for All scenario, 2022-2030 | J31: https://www.iea.org/reports/a-vision-for-clean-cooking-access-for-all/executive-summary | M31: Ready | N31: Chart to recreate | O31: Pie Chart | P31: Yes | Q31: https://echarts.apache.org/examples/en/editor.html?c=pie-rich-text | R31: Yes
A32: 2 | B32: 63 | C32: =_xlfn.CONCAT("M",$B$1,"_C",ChartsM2[[#This Row],[Chapter]],"_",ChartsM2[[#This Row],['#]],"_1") -> M2_C2_63_1 | D32: Anual investment required in the Access for All scenario 2022-2030 | E32: #VALUE! | G32: Divya | H32: International Energy Agency (IEA). (2022). Annual investments required in the Access for All scenario by region, 2030. Retrieved from https://www.iea.org/data-and-statistics/charts/annual-investments-required-in-the-access-for-all-scenario-by-region-2030 | J32: https://www.iea.org/data-and-statistics/charts/annual-investments-required-in-the-access-for-all-scenario-by-region-2030 | M32: Ready | N32: Chart to recreate | O32: Bar Chart Stacked Vertical | P32: Yes | Q32: https://echarts.apache.org/examples/en/editor.html?c=pie-simple https://echarts.apache.org/examples/en/editor.html?c=line-simple | R32: Yes
A33: 2 | B33: 63 | C33: =_xlfn.CONCAT("M",$B$1,"_C",ChartsM2[[#This Row],[Chapter]],"_",ChartsM2[[#This Row],['#]],"_2") -> M2_C2_63_2 | D33: Anual investment required in the Access for All scenario 2022-2030 | E33: #VALUE! | G33: Divya | H33: International Energy Agency (IEA). (2022). Annual investments required in the Access for All scenario by region, 2030. Retrieved from https://www.iea.org/data-and-statistics/charts/annual-investments-required-in-the-access-for-all-scenario-by-region-2030 | J33: https://www.iea.org/data-and-statistics/charts/annual-investments-required-in-the-access-for-all-scenario-by-region-2030 | M33: Ready | N33: Chart to recreate | O33: Pie Chart | P33: Yes | Q33: https://echarts.apache.org/examples/en/editor.html?c=pie-simple https://echarts.apache.org/examples/en/editor.html?c=line-simple | R33: Yes
A34: 3 | B34: 40 | C34: =_xlfn.CONCAT("M",$B$1,"_C",ChartsM2[[#This Row],[Chapter]],"_",ChartsM2[[#This Row],['#]]) -> M2_C3_40 | D34: Africa Minigrids Program Participating Countries | E34: #VALUE! | G34: Gabriela | H34: Africa Minigrids Program. (2025). AMP Participating Countries. | I34: Note: The following countries are currently participating in the Africa Minigrids Program | J34: https://africaminigrids.org/countries-projects/ | K34: Module 2 - Datasets for Charts.xlsx | L34: Pending | M34: Review pending | N34: Chart to recreate | O34: Animating Contour on Globe | P34: Yes | Q34: https://echarts.apache.org/examples/en/editor.html?c=animating-contour-on-globe&gl=1 | R34: No | S34: May you can higlight in the like in the example chart, but with different color each round
A35: 3 | B35: 46 | C35: =_xlfn.CONCAT("M",$B$1,"_C",ChartsM2[[#This Row],[Chapter]],"_",ChartsM2[[#This Row],['#]]) -> M2_C3_46 | D35: National and rural electrification rates in SIDS, 2020/2021 | E35: #VALUE! | G35: Gabriela | H35: IRENA. (2024). Small Island States at a Crossroads: Towards equitable energy access in least-electrified countries. International Renewable Energy Agency, Abu Dhabi. | I35: Sources: All from (UN, 2021), except (*), which denotes national and rural electrification rates (%) from (Energy, 2020), and (**), which denotes rural electrification rates (%) from (Energy, 2020) or (World Bank, 2021). Country classifications based on (World Bank, 2024). Note: AIS stands for Atlantic, Indian Ocean and South China Sea. | J35: https://www.irena.org/-/media/Files/IRENA/Agency/Publication/2024/Mar/IRENA_SIDS_crossroads_energy_access_2024.pdf | K35: Module 2 - Datasets for Charts.xlsx | L35: Pending | M35: Ready | N35: Chart to recreate | O35: Bar Chart Categories Vertical | P35: Yes | Q35: https://echarts.apache.org/examples/en/editor.html?c=dataset-simple1 | R35: Yes | S35: You can combine with bar race
A36: 3 | B36: 11 | C36: =_xlfn.CONCAT("M",$B$1,"_C",ChartsM2[[#This Row],[Chapter]],"_",ChartsM2[[#This Row],['#]]) -> M2_C3_11 | D36: Energy Access Explorer (EAE) | E36: #VALUE! | J36: https://www.wri.org/initiatives/energy-access-explorer
A37: 3 | B37: 12 | C37: =_xlfn.CONCAT("M",$B$1,"_C",ChartsM2[[#This Row],[Chapter]],"_",ChartsM2[[#This Row],['#]]) -> M2_C3_12 | D37: EAE analysis showing the locations that satisfy the set example criteria | E37: #VALUE!

Sheet Module3
A1: Module | B1: 3
A2: Chapter | B2: # | C2: Figure ID | D2: Title | E2: Screenshot | F2: New Screenshot | G2: Lead | H2: Source (APA) | I2: Footnote | J2: Source Link | K2: Dataset Link | L2: Chart Status | M2: Dataset Status | N2: Category | O2: Chart Type | P2: Apache Possible | Q2: Apache Link | R2: Automation Possible | S2: Notes
A3: 2 | B3: 5 | C3: =_xlfn.CONCAT("M",$B$1,"_C",ChartsM3[[#This Row],[Chapter]],"_",ChartsM3[[#This Row],['#]]) -> M3_C2_5 | D3: Documented human rights and energy conflicts around the globe | E3: #VALUE! | L3: In process | N3: Chart for Direct Use | S3: Enable zooming into each region to improve readability on large world maps. | Include a trivia element beside or within the charts to engage users with content-based questions. This is meant for curiosity and reflection—not as a test or evaluation
A4: 2 | B4: 7 | C4: =_xlfn.CONCAT("M",$B$1,"_C",ChartsM3[[#This Row],[Chapter]],"_",ChartsM3[[#This Row],['#]]) -> M3_C2_7 | D4: Employment difference by sector between the baseline and 1.5°C Scenario, thousand jobs | E4: #VALUE! | G4: Gabriela | H4: UNDP. (2021) . What are the socio-economic impacts of an energy transition? | I4: *World employment, thousand persons | J4: https://www.undp.org/eurasia/blog/what-are-socio-economic-impacts-energy-transition | K4: Module 3 - Dasasets for Charts.xlsx | L4: In process | M4: Ready | N4: Chart to recreate | O4: Bar Chart Categories Horizontal | P4: Yes | Q4: https://echarts.apache.org/examples/en/editor.html?c=bar-negative | R4: Yes | S4: You can combine with the animation of bar race. | User can interact with the chart at real time by clicking to reveal, zoom or highlight values | Include a trivia element beside or within the charts to engage users with content-based questions. This is meant for curiosity and reflection—not as a test or evaluation
A5: 3 | B5: 11 | C5: =_xlfn.CONCAT("M",$B$1,"_C",ChartsM3[[#This Row],[Chapter]],"_",ChartsM3[[#This Row],['#]],"_1") -> M3_C3_11_1 | D5: Critical minerals used in selected clean energy technologies | E5: #VALUE! | G5: Gabriela | H5: UN DESA. (2025).Policy Brief No. 171: Leveraging Critical Energy Transition Minerals: policy pathways for sustainable development. | I5: *Data based on data from IEA. | J5: https://desapublications.un.org/policy-briefs/un-desa-policy-brief-no-171-leveraging-critical-energy-transition-minerals-policy | K5: Module 3 - Dasasets for Charts.xlsx | L5: In process | M5: Ready | N5: Chart to recreate | O5: Bar Chart Stacked Horizontal | P5: Yes | Q5: https://echarts.apache.org/examples/en/editor.html?c=bar-polar-stack | R5: Yes | S5: User can interact with the chart at real time by clicking to reveal, zoom or highlight values | Include a trivia element beside or within the charts to engage users with content-based questions. This is meant for curiosity and reflection—not as a test or evaluation
A6: 3 | B6: 11 | C6: =_xlfn.CONCAT("M",$B$1,"_C",ChartsM3[[#This Row],[Chapter]],"_",ChartsM3[[#This Row],['#]],"_2") -> M3_C3_11_2 | D6: Critical minerals used in selected clean energy technologies | E6: #VALUE! | G6: Gabriela | H6: UN DESA. (2025).Policy Brief No. 171: Leveraging Critical Energy Transition Minerals: policy pathways for sustainable development. | I6: *Data based on data from IEA. | J6: https://desapublications.un.org/policy-briefs/un-desa-policy-brief-no-171-leveraging-critical-energy-transition-minerals-policy | K6: Module 3 - Dasasets for Charts.xlsx | L6: In process | M6: Ready | N6: Chart to recreate | O6: Bar Chart Stacked Horizontal | P6: Yes | Q6: https://echarts.apache.org/examples/en/editor.html?c=bar-polar-stack | R6: Yes | S6: User can interact with the chart at real time by clicking to reveal, zoom or highlight values | Include a trivia element beside or within the charts to engage users with content-based questions. This is meant for curiosity and reflection—not as a test or evaluation
A7: 3 | B7: 12 | C7: =_xlfn.CONCAT("M",$B$1,"_C",ChartsM3[[#This Row],[Chapter]],"_",ChartsM3[[#This Row],['#]],"_1") -> M3_C3_12_1 | D7: Global critical minerals demand in the STEPS, 2024-2040 - Copper | E7: #VALUE! | G7: Danae | H7: IEA, 2025 | J7: https://iea.blob.core.windows.net/assets/a33abe2e-f799-4787-b09b-2484a6f5a8e4/GlobalCriticalMineralsOutlook2025.pdf | K7: Module 3 - Dasasets for Charts.xlsx | L7: In process | M7: Ready | N7: Chart to recreate | O7: Bar Chart Categories Vertical | P7: Yes | Q7: https://echarts.apache.org/examples/en/editor.html?c=bar-polar-stack-radial | R7: Yes | S7: 4 different stacked bar chat on polar in just one dashboard. | User can interact with the chart at real time by clicking to reveal, zoom or highlight values | Include a trivia element beside or within the charts to engage users with content-based questions. This is meant for curiosity and reflection—not as a test or evaluation
A8: 3 | B8: 12 | C8: =_xlfn.CONCAT("M",$B$1,"_C",ChartsM3[[#This Row],[Chapter]],"_",ChartsM3[[#This Row],['#]],"_2") -> M3_C3_12_2 | D8: Global critical minerals demand in the STEPS, 2024-2040 - Lithium | E8: #VALUE! | G8: Danae | H8: IEA, 2025 | J8: https://iea.blob.core.windows.net/assets/a33abe2e-f799-4787-b09b-2484a6f5a8e4/GlobalCriticalMineralsOutlook2025.pdf | K8: Module 3 - Dasasets for Charts.xlsx | L8: In process | M8: Ready | N8: Chart to recreate | O8: Bar Chart Categories Vertical | P8: Yes | Q8: https://echarts.apache.org/examples/en/editor.html?c=bar-polar-stack-radial | R8: Yes | S8: 4 different stacked bar chat on polar in just one dashboard. | User can interact with the chart at real time by clicking to reveal, zoom or highlight values | Include a trivia element beside or within the charts to engage users with content-based questions. This is meant for curiosity and reflection—not as a test or evaluation
A9: 3 | B9: 12 | C9: =_xlfn.CONCAT("M",$B$1,"_C",ChartsM3[[#This Row],[Chapter]],"_",ChartsM3[[#This Row],['#]],"_3") -> M3_C3_12_3 | D9: Global critical minerals demand in the STEPS, 2024-2040 - Nickel | E9: #VALUE! | G9: Danae | H9: IEA, 2025 | J9: https://iea.blob.core.windows.net/assets/a33abe2e-f799-4787-b09b-2484a6f5a8e4/GlobalCriticalMineralsOutlook2025.pdf | K9: Module 3 - Dasasets for Charts.xlsx | L9: In process | M9: Ready | N9: Chart to recreate | O9: Bar Chart Categories Vertical | P9: Yes | Q9: https://echarts.apache.org/examples/en/editor.html?c=bar-polar-stack-radial | R9: Yes | S9: 4 different stacked bar chat on polar in just one dashboard. | User can interact with the chart at real time by clicking to reveal, zoom or highlight values | Include a trivia element beside or within the charts to engage users with content-based questions. This is meant for curiosity and reflection—not as a test or evaluation
A10: 3 | B10: 12 | C10: =_xlfn.CONCAT("M",$B$1,"_C",ChartsM3[[#This Row],[Chapter]],"_",ChartsM3[[#This Row],['#]],"_4") -> M3_C3_12_4 | D10: Global critical minerals demand in the STEPS, 2024-2040 - Cobalt | E10: #VALUE! | G10: Danae | H10: IEA, 2025 | J10: https://iea.blob.core.windows.net/assets/a33abe2e-f799-4787-b09b-2484a6f5a8e4/GlobalCriticalMineralsOutlook2025.pdf | K10: Module 3 - Dasasets for Charts.xlsx | L10: In process | M10: Ready | N10: Chart to recreate | O10: Bar Chart Categories Vertical | P10: Yes | Q10: https://echarts.apache.org/examples/en/editor.html?c=bar-polar-stack-radial | R10: Yes | S10: 4 different stacked bar chat on polar in just one dashboard. | User can interact with the chart at real time by clicking to reveal, zoom or highlight values | Include a trivia element beside or within the charts to engage users with content-based questions. This is meant for curiosity and reflection—not as a test or evaluation
A11: 3 | B11: 12 | C11: =_xlfn.CONCAT("M",$B$1,"_C",ChartsM3[[#This Row],[Chapter]],"_",ChartsM3[[#This Row],['#]],"_5") -> M3_C3_12_5 | D11: Global critical minerals demand in the STEPS, 2024-2040 - Graphite | E11: #VALUE! | G11: Danae | H11: IEA, 2025 | J11: https://iea.blob.core.windows.net/assets/a33abe2e-f799-4787-b09b-2484a6f5a8e4/GlobalCriticalMineralsOutlook2025.pdf | K11: Module 3 - Dasasets for Charts.xlsx | L11: In process | M11: Ready | N11: Chart to recreate | O11: Bar Chart Categories Vertical | P11: Yes | R11: Yes
A12: 3 | B12: 12 | C12: =_xlfn.CONCAT("M",$B$1,"_C",ChartsM3[[#This Row],[Chapter]],"_",ChartsM3[[#This Row],['#]],"_6") -> M3_C3_12_6 | D12: Global critical minerals demand in the STEPS, 2024-2040 - Rare Earths | E12: #VALUE! | G12: Danae | H12: IEA, 2025 | J12: https://iea.blob.core.windows.net/assets/a33abe2e-f799-4787-b09b-2484a6f5a8e4/GlobalCriticalMineralsOutlook2025.pdf | K12: Module 3 - Dasasets for Charts.xlsx | L12: In process | M12: Ready | N12: Chart to recreate | O12: Bar Chart Categories Vertical | P12: Yes | R12: Yes
A13: 3 | B13: 13 | C13: =_xlfn.CONCAT("M",$B$1,"_C",ChartsM3[[#This Row],[Chapter]],"_",ChartsM3[[#This Row],['#]]) -> M3_C3_13 | D13: Global distribution of mining and refining supply for selected critical materials | E13: #VALUE! | H13: IRENA (2023) | J13: https://www.irena.org/Publications/2023/Jul/Geopolitics-of-the-Energy-Transition-Critical-Materials?trk=public_post_comment-text | N13: Chart for Direct Use | S13: Consider using an icon for each mineral and showing its name as a label when the user clicks on it | Include a trivia element beside or within the charts to engage users with content-based questions. This is meant for curiosity and reflection—not as a test or evaluation
A14: 3 | B14: 15 | C14: =_xlfn.CONCAT("M",$B$1,"_C",ChartsM3[[#This Row],[Chapter]],"_",ChartsM3[[#This Row],['#]]) -> M3_C3_15 | D14: Lifecycle greenhouse gas emission ranges for different technologies | E14: #VALUE! | G14: Gabriela | H14: UNECE (2022). Carbon Neutrality in the UNECE Region: Integrated Life-cycle Assessment of Electricity Sources. United Nations Publications, New York. | J14: https://unece.org/sites/default/files/2022-04/LCA_3_FINAL%20March%202022.pdf | K14: Module 3 - Dasasets for Charts.xlsx | L14: In process | M14: Ready | N14: Chart to recreate | O14: OHLC Chart | P14: Yes | Q14: https://echarts.apache.org/examples/en/editor.html?c=custom-ohlc | R14: No | S14: User can interact with the chart at real time by clicking to reveal, zoom or highlight values | Add abbreviation meanings to improve clarity and help users better understand the content | Include a trivia element beside or within the charts to engage users with content-based questions. This is meant for curiosity and reflection—not as a test or evaluation

Sheet Module4
A1: Module | B1: 4
A2: Chapter | B2: # | C2: Figure ID | D2: Title | E2: Screenshot | F2: New Screenshot | G2: Lead | H2: Source (APA) | I2: Footnote | J2: Source Link | K2: Dataset Link | L2: Chart Status | M2: Dataset Status | N2: Category | O2: Chart Type | P2: Apache Possible | Q2: Apache Link | R2: Automation Possible | S2: Notes
A3: 1 | B3: 1 | C3: =_xlfn.CONCAT("M",$B$1,"_C",ChartsM4[[#This Row],[Chapter]],"_",ChartsM4[[#This Row],['#]]) -> M4_C1_1 | D3: Annual clean energy investment, 2015-2023 | E3: #VALUE! | F3: Picture | G3: Zhong | H3: International Energy Agency (2023, p.10) | I3: Notes: “Low-emission fuels” include modern liquid and gaseous bioenergy, low-emission hydrogen and hydrogen-based fuels that do not emit any CO2 from fossil fuels directly when used and emit very little when being produced; “Other end use” refers to renewables for end use and electrification in the buildings, transport and industrial sectors. 2023e = estimated values for 2023; CCUS = carbon capture, utilisation and storage; EV = electric vehicle. | J3: https://iea.blob.core.windows.net/assets/8834d3af-af60-4df0-9643-72e2684f7221/WorldEnergyInvestment2023.pdf | K3: M4_C1_1 | L3: In process | M3: Ready | N3: Chart to recreate | O3: Bar Chart Stacked Vertical | P3: Yes | Q3: https://echarts.apache.org/examples/en/editor.html?c=bar-stack | R3: Yes | S3: Zhong: Apache Example: https://echarts.apache.org/examples/en/editor.html?c=bar-stack Zhong: The original screenshot of the chart titled "Annual global investment in renewable energy, energy efficiency, and other transition-related technologies, 2015-2022" only shows data from 2015 to 2022 (see page 10 from https://www.irena.org/-/media/Files/IRENA/Agency/Publication/2023/Feb/IRENA_CPI_Global_RE_finance_2023.pdf). The old chart also did not show the exact breakdown headcount of different energies. However, the new dataset contains 2023 data and shows breakdowns. Additonal link to the new data: https://www.iea.org/data-and-statistics/charts/annual-clean-energy-investment-2015-2023 Zhong: need to add data labels for small data points.
A4: 1 | B4: 3 | C4: =_xlfn.CONCAT("M",$B$1,"_C",ChartsM4[[#This Row],[Chapter]],"_",ChartsM4[[#This Row],['#]]) -> M4_C1_3 | D4: Investment in renewable energy by region of destination, 2013-2022 | E4: #VALUE! | F4: #VALUE! | G4: Zhong | H4: IRENA (2023, p.54) | I4: Note: “North America (excluding Mexico)” includes Bermuda, Canada and the United States. “Others” include the Middle East and North Africa, Other Oceania, Transregional, Other Asia and Unknown. For more details on the geographic classification used in the analysis, please see methodology document (Appendix). Source: CPI (2022a). Investments for 2021 and 2022 represent preliminary estimates based on data from BNEF (2023b) | J4: https://www.irena.org/-/media/Files/IRENA/Agency/Publication/2023/Feb/IRENA_CPI_Global_RE_finance_2023.pdf | K4: M4_C1_3 | L4: In process | M4: Ready | N4: Chart to recreate | O4: Bar Chart Stacked Normalized Vertical | P4: Yes | Q4: https://echarts.apache.org/examples/en/editor.html?c=bar-stack-normalization | R4: Yes | S4: Zhong: Apache Example: https://echarts.apache.org/examples/en/editor.html?c=bar-stack-normalization Zhong: The source does not privide exact breakdowns for small data points (they are extracted by ChatGPT). Zhong: need to explain the denifition of different regions (e.g., Eurasia, Sub-Saharan Africa); need to add data labels for small data points.
A5: 1 | B5: 4 | C5: =_xlfn.CONCAT("M",$B$1,"_C",ChartsM4[[#This Row],[Chapter]],"_",ChartsM4[[#This Row],['#]]) -> M4_C1_4 | D5: Annual investment in clean energy by selected country and region, 2019 and 2024 | E5: #VALUE! | F5: #VALUE! | G5: Zhong | H5: International Energy Agency (2024, p.5) | I5: Note: 2024e = estimated values for 2024. US = United States. EU = European Union. | J5: https://iea.blob.core.windows.net/assets/60fcd1dd-d112-469b-87de-20d39227df3d/WorldEnergyInvestment2024.pdf | K5: M4_C1_4 | L5: In process | M5: Ready | N5: Chart to recreate | O5: Bar Chart Stacked Vertical | P5: Yes | Q5: https://echarts.apache.org/examples/en/editor.html?c=bar-stack | R5: Yes | S5: Zhong: need to add data labels for small data points. Zhong: Apache Example: https://echarts.apache.org/examples/en/editor.html?c=bar-stack Zhong: Exact data points can be downloaded from https://www.iea.org/data-and-statistics/charts/annual-investment-in-clean-energy-by-selected-country-and-region-2019-and-2024
A6: 1 | B6: 8 | C6: =_xlfn.CONCAT("M",$B$1,"_C",ChartsM4[[#This Row],[Chapter]],"_",ChartsM4[[#This Row],['#]]) -> M4_C1_8 | D6: Global primary energy consumption by source. | E6: #VALUE! | F6: #VALUE! | G6: Zhong | H6: Our World in Data (2024) via Energy Institute - Statistical Review of World Energy (2024), Smil (2017) | I6: Note: In the absence of more recent data, traditional biomass is assumed constant since 2015. | J6: https://ourworldindata.org/grapher/global-energy-consumption-source | K6: M4_C1_8 | L6: In process | M6: Ready | N6: Chart to recreate | O6: Line Chart Stacked | P6: Yes | Q6: https://echarts.apache.org/examples/en/editor.html?c=line-stack | R6: Yes | S6: Zhong: Apache Example: https://echarts.apache.org/examples/en/editor.html?c=line-stack Notes not from Zhong: The graph here sends the opposite message we are trying to send in this section. While RE investments have increased over time and are now exceeding fossil fuel investments, RE-share in global primary energy consumption remains marginal showing the long way we still have ahead of us to decarbonize energy systems. To send a more optimistic message we may want to focus on electricity sector figure where the share of renewable is steadily inceasing and projected to go beyond 30% before 2030 Zhong: The trend is unclear from 1800 to 1900.
A7: 1 | B7: 9 | C7: =_xlfn.CONCAT("M",$B$1,"_C",ChartsM4[[#This Row],[Chapter]],"_",ChartsM4[[#This Row],['#]]) -> M4_C1_9 | D7: Increasing Mineral Demand in Transport | E7: #VALUE! | F7: #VALUE! | G7: Zhong | H7: Mckinsey Company (2022) via International Energy Agency (2022, p. 6) | I7: Notes: kg = kilogramme; MW = megawatt. Steel and aluminium not included. See Chapter 1 and Annex for details on the assumptions and methodologies. | J7: https://www.mckinsey.com/industries/electric-power-and-natural-gas/our-insights/the-trading-opportunity-that-could-create-resilience-in-materials | K7: M4_C1_9 | L7: In process | M7: Ready | N7: Chart to recreate | O7: Bar Chart Stacked Horizontal | P7: Yes | Q7: https://echarts.apache.org/examples/en/editor.html?c=bar-y-category-stack | R7: Yes | S7: Zhong: Apache Example: https://echarts.apache.org/examples/en/editor.html?c=bar-y-category-stack Zhong: The original data points can be extracted from https://www.iea.org/data-and-statistics/charts/minerals-used-in-electric-cars-compared-to-conventional-cars ; The original data source is International Energy Agency (2022, p. 6), https://iea.blob.core.windows.net/assets/ffd2a83b-8c30-4e9d-980a-52b6d9a86fdc/TheRoleofCriticalMineralsinCleanEnergyTransitions.pdf CHART ALREADY EXISTS FROM DIFFERENT SOURCE IN MODULE3
A8: 2 | B8: 13 | C8: =_xlfn.CONCAT("M",$B$1,"_C",ChartsM4[[#This Row],[Chapter]],"_",ChartsM4[[#This Row],['#]]) -> M4_C2_13 | D8: Annual fossil fuel subsidies by region, 2013-2023 | E8: #VALUE! | G8: Zhong | H8: Fossil Fuels Subsidy Tracker (2023) | I8: Sources: OECD, IEA, IMF Disclaimer: Any data and any map included herein, are without prejudice to the status of or sovereignty over any territory, to the delimitation of international frontiers and boundaries and to the name of any territory, city or area. The dataset for 2023 is available for 83 economies, including: Angola, United Arab Emirates, Argentina, Armenia, Australia, Austria, Azerbaijan, Belgium, Bangladesh, Bahrain, Belarus, Bolivia, Brazil, Brunei Darussalam, Canada, Switzerland, Chile, People's Republic of China, Colombia, Costa Rica, Czech Republic, Germany, Denmark, Algeria, Ecuador, Egypt, Spain, Estonia, Finland, France, Gabon, United Kingdom, Georgia, Ghana, Greece, Croatia, Hungary, Indonesia, India, Ireland, Islamic Republic of Iran, Iraq, Iceland, Israel, Italy, Japan, Kazakhstan, Korea, Kuwait, Libya, Sri Lanka, Lithuania, Luxembourg, Latvia, Moldova, Mexico, Malaysia, Nigeria, Netherlands, Norway, New Zealand, Oman, Pakistan, Poland, Portugal, Qatar, Russian Federation, Saudi Arabia, El Salvador, Slovak Republic, Slovenia, Sweden, Thailand, Turkmenistan, Trinidad and Tobago, Turkey, Chinese Taipei, Ukraine, United States, Uzbekistan, Venezuela, Viet Nam, South Africa | J8: https://fossilfuelsubsidytracker.org/country/ | L8: Pending | M8: Pending | N8: Chart to recreate | O8: Bar Chart Categories Vertical | P8: Yes | Q8: https://echarts.apache.org/examples/en/editor.html?c=dataset-simple0 | R8: Yes | S8: Zhong: Apache Example: https://echarts.apache.org/examples/en/editor.html?c=dataset-simple0 Zhong: The country level data can be downloaded from https://fossilfuelsubsidytracker.org/country/ ; After that, combining countries into different regions (e.g., Eurasia). Need to decide what defenitions of world regions (e.g., World Bank, UN) to adopt - so far we do not have this definition. Zhong: needs to explain the denifition of different regions (e.g., Eurasia, Sub-Saharan Africa). too many columns may make it diffucult to read or visualize using inclusive color palettes.
A9: 2 | B9: 16 | C9: =_xlfn.CONCAT("M",$B$1,"_C",ChartsM4[[#This Row],[Chapter]],"_",ChartsM4[[#This Row],['#]]) -> M4_C2_16 | D9: Fossil fuel consumption subsidies by fuel, 2010-2022 | E9: #VALUE! | F9: #VALUE! | G9: Divya | H9: IEA (2022) | J9: https://www.iea.org/reports/fossil-fuels-consumption-subsidies-2022 | K9: https://www.iea.org/data-and-statistics/data-product/fossil-fuel-subsidies-database | L9: In process | M9: Ready | N9: Chart to recreate | O9: Bar Chart Stacked Vertical | P9: Yes | Q9: https://echarts.apache.org/examples/en/editor.html?c=bar-stack | R9: Yes | S9: Zhong: need to add data lables, especially for Coal as the small amount is unreadable.
A10: 2 | B10: 34 | C10: =_xlfn.CONCAT("M",$B$1,"_C",ChartsM4[[#This Row],[Chapter]],"_",ChartsM4[[#This Row],['#]]) -> M4_C2_34 | D10: Value of fossil-fuel subsidies by fuel in the top 25 countries, 2022 | E10: #VALUE! | L10: Pending | M10: Pending | N10: Chart to recreate
A11: 3 | B11: 37 | C11: =_xlfn.CONCAT("M",$B$1,"_C",ChartsM4[[#This Row],[Chapter]],"_",ChartsM4[[#This Row],['#]],"_1") -> M4_C3_37_1 | D11: Global investment in electricity networks in the NZE | E11: #VALUE! | G11: Divya | H11: IEA (2021, p.118) | J11: https://iea.blob.core.windows.net/assets/deebef5d-0c34-4539-9d0c-10b13d840027/NetZeroby2050-ARoadmapfortheGlobalEnergySector_CORR.pdf | K11: https://www.iea.org/product/download/008551-000293-008291 | L11: In process | M11: Ready | N11: Chart to recreate | O11: Bar Chart Vertical | P11: Yes | Q11: https://echarts.apache.org/examples/en/editor.html?c=bar-simple https://echarts.apache.org/examples/en/editor.html?c=bar-stack-normalization | R11: Yes | S11: Left Chart
A12: 3 | B12: 37 | C12: =_xlfn.CONCAT("M",$B$1,"_C",ChartsM4[[#This Row],[Chapter]],"_",ChartsM4[[#This Row],['#]],"_2") -> M4_C3_37_2 | D12: Global investment in electricity networks in the NZE | E12: #VALUE! | G12: Divya | H12: IEA (2021, p.118) | J12: https://iea.blob.core.windows.net/assets/deebef5d-0c34-4539-9d0c-10b13d840027/NetZeroby2050-ARoadmapfortheGlobalEnergySector_CORR.pdf | K12: https://www.iea.org/product/download/008551-000293-008291 | L12: In process | M12: Ready | N12: Chart to recreate | O12: Bar Chart Stacked Vertical | P12: Yes | Q12: https://echarts.apache.org/examples/en/editor.html?c=bar-simple https://echarts.apache.org/examples/en/editor.html?c=bar-stack-normalization | R12: Yes | S12: Right Chart
A13: 3 | B13: 21 | C13: =_xlfn.CONCAT("M",$B$1,"_C",ChartsM4[[#This Row],[Chapter]],"_",ChartsM4[[#This Row],['#]]) -> M4_C3_21 | D13: Countries where the DREI has being implemented. | E13: #VALUE! | L13: In process | N13: Chart for Direct Use | S13: Zhong: the map does not provide substantial information (maybe adding the year of implementation?); the original chart/data source is unknown.
A14: 4 | B14: 30 | C14: =_xlfn.CONCAT("M",$B$1,"_C",ChartsM4[[#This Row],[Chapter]],"_",ChartsM4[[#This Row],['#]]) -> M4_C4_30 | D14: Average carbon prices in selected countries in 2021 (EUR per tonne of CO2) | E14: #VALUE! | G14: Divya | H14: OECD (2021) | J14: https://www.statista.com/chart/17095/highest-carbon-taxes-in-the-world/ | K14: https://data-explorer.oecd.org/share/?token=eyJ0eXAiOiJKV1QiLCJhbGciOiJIUzI1NiJ9.eyJzdWIiOiJmNmI4MzFlMS0wNDJlLTQ5YzgtYWU5Yy01Njc0YWQxMDBmZmQiLCJlbWFpbCI6ImRpdnlhc2FuZ2FyYWp1QGxpdmUuY29tIiwianRpIjoiYjQ5NzVmMmYtZGUxYS00ZTA1LWFkNmItNmI3NzhkMWYzNWMyIiwiaWF0IjoxNzQ0NzI4MTIxLCJleHAiOjE3NDQ3NDI1MjF9.2ITfhYlnPoxtGfaKJH0QYjLZMF7MAolekhbpg5Acwb8&email=divyasangaraju@live.com&id=f6b831e1-042e-49c8-ae9c-5674ad100ffd | L14: In process | M14: Pending | N14: Chart to recreate | O14: Bar Chart Horizontal | P14: Yes | Q14: https://echarts.apache.org/examples/en/editor.html?c=bar-y-category The graph presents outdated data and mix or add several carbon pricing mechanisms that could exist. Carbon taxes may be implemented only partially, covering for instance one economic sector and not another. This could be result in misuderstanding. A more interesting approach could be to focus on carbon price in geographies with an ETS market to show differences in pricing. | R14: Yes | S14: Zhong: consider using the most recent data (2024)
A15: 4 | B15: 32 | C15: =_xlfn.CONCAT("M",$B$1,"_C",ChartsM4[[#This Row],[Chapter]],"_",ChartsM4[[#This Row],['#]]) -> M4_C4_32 | D15: Mitigation costs in the electricity sector by policy instrument. | E15: #VALUE! | G15: Divya | L15: In process | M15: Review pending | N15: Chart to recreate | O15: Basic Bar Horizontal and Basic Scatter Chart | P15: Yes | Q15: https://echarts.apache.org/examples/en/editor.html?c=bar-simple https://echarts.apache.org/examples/en/editor.html?c=scatter-simple Used Automeris as I couldn't find the data | R15: No | S15: Zhong: the original chart/data source is unknown.
A16: 4 | B16: 33 | C16: =_xlfn.CONCAT("M",$B$1,"_C",ChartsM4[[#This Row],[Chapter]],"_",ChartsM4[[#This Row],['#]]) -> M4_C4_33 | D16: Overview of national emissions pricing (in 2019) and | E16: #VALUE! | F16: #VALUE! | G16: Divya | H16: “World Bank Group. 2019. State and Trends of Carbon Pricing 2019. © World Bank. http://hdl.handle.net/10986/31755 License: CC BY 3.0 IGO.” | J16: https://openknowledge.worldbank.org/bitstreams/11cf8aed-1492-5c12-b2e9-27a12c8c9473/download | L16: In process | M16: In process | N16: Chart to recreate | O16: Geomap | P16: Yes | Q16: https://echarts.apache.org/examples/en/editor.html?c=map-HK | R16: No | S16: Zhong: consider using a dashboard to visualize with the most recent data (2024): https://carbonpricingdashboard.worldbank.org/compliance/instrument-detail

Sheet Module5
A1: Module | B1: 5
A2: Chapter | B2: # | C2: Figure ID | D2: Title | E2: Screenshot | F2: New Screenshot | G2: Lead | H2: Source (APA) | I2: Footnote | J2: Source Link | K2: Dataset Link | L2: Chart Status | M2: Dataset Status | N2: Category | O2: Chart Type | P2: Apache Possible | Q2: Apache Link | R2: Automation Possible | S2: Notes
A3: 1 | B3: 10 | C3: =_xlfn.CONCAT("M",$B$1,"_C",ChartsM5[[#This Row],[Chapter]],"_",ChartsM5[[#This Row],['#]]) -> M5_C1_10 | D3: Annual revenue and New debt issuance for 2014-22 | E3: #VALUE! | G3: Ahmad | H3: SAMA and Saudi Debt Management Office | K3: https://www.sama.gov.sa/en-US/EconomicReports/Pages/report.aspx | L3: Pending | M3: Pending | N3: Chart to recreate | O3: Bar Chart Stacked Vertical | P3: Yes | Q3: https://echarts.apache.org/examples/en/editor.html?c=bar-stack-normalization-and-variation | R3: Yes
A4: 2 | B4: 13 | C4: =_xlfn.CONCAT("M",$B$1,"_C",ChartsM5[[#This Row],[Chapter]],"_",ChartsM5[[#This Row],['#]]) -> M5_C2_13 | D4: Historical and forecasted annual percentage variation of Grenada electricity demand for different years and scenarios | E4: #VALUE! | G4: Ahmad | J4: https://aiguasol.coop/project/grenadas-power-system-integrated-assessment-with-united-nations-project-development-undp/ | K4: Used Automeris | L4: Pending | M4: Pending | N4: Chart to recreate | O4: Bar Chart Categories Vertical | P4: Yes | Q4: https://echarts.apache.org/examples/en/editor.html?c=bar-tick-align | R4: Yes | S4: A line graph might be better for this than a bar group. If we can have it animaed it might be helpful
A5: 2 | B5: 15 | C5: =_xlfn.CONCAT("M",$B$1,"_C",ChartsM5[[#This Row],[Chapter]],"_",ChartsM5[[#This Row],['#]]) -> M5_C2_15 | D5: Global annual and cumulative investment by technological avenue under 1.5°C, 2024-2030 | E5: #VALUE! | G5: Ahmad | J5: https://www.irena.org/-/media/Files/IRENA/Agency/Publication/2024/Nov/IRENA_World_energy_transitions_outlook_2024.pdf | L5: Pending | M5: Pending | N5: Chart to recreate | O5: Bar Chart Stacked Vertical | P5: Yes | Q5: https://echarts.apache.org/examples/en/editor.html?c=bar-stack-normalization-and-variation | R5: Yes | S5: Data is behind a paywall
A6: 3 | B6: 20 | C6: =_xlfn.CONCAT("M",$B$1,"_C",ChartsM5[[#This Row],[Chapter]],"_",ChartsM5[[#This Row],['#]]) -> M5_C3_20 | D6: UNDP helped 126 countries to enhance transparency, between 2015 and 2022 | E6: #VALUE! | G6: Divya | K6: Used AI tools to extract the country names highlighted | L6: Ready | M6: Ready | N6: Chart to recreate | O6: Map - Choropleth map | P6: Yes | Q6: https://echarts.apache.org/examples/en/editor.html?c=map-usa-projection | R6: No | S6: Not sure how useful this visualisation is. Could potentially be just a statistic. consider doing a time trend for this

Sheet Module6
A1: Module | B1: 6
A2: Chapter | B2: # | C2: Figure ID | D2: Title | E2: Screenshot | F2: New Screenshot | G2: Lead | H2: Source (APA) | I2: Footnote | J2: Source Link | K2: Dataset Link | L2: Chart Status | M2: Dataset Status | N2: Category | O2: Chart Type | P2: Apache Possible | Q2: Apache Link | R2: Automation Possible | S2: Notes
A3: 1 | B3: 1 | C3: =_xlfn.CONCAT("M",$B$1,"_C",ChartsM6[[#This Row],[Chapter]],"_",ChartsM6[[#This Row],['#]]) -> M6_C1_1 | D3: Global greenhouse gas emissions by sector and end use, 2021 | E3: #VALUE! | F3: #VALUE! | G3: Gabriela | H3: World resource institute. (2024). Global greenhouse gas emissions by sector, 2021. | I3: Source: Climate watch | J3: https://www.wri.org/data/world-greenhouse-gas-emissions-sector-2021-sunburst-chart | K3: Module 6 - Datasets for Charts.xlsx | L3: In process | M3: Ready | N3: Chart to recreate | O3: Pie Chart | P3: Yes | Q3: https://echarts.apache.org/examples/en/editor.html?c=gauge-ring | R3: Yes
A4: 1 | B4: 2 | C4: =_xlfn.CONCAT("M",$B$1,"_C",ChartsM6[[#This Row],[Chapter]],"_",ChartsM6[[#This Row],['#]]) -> M6_C1_2 | D4: Trends in sectoral emissions (Energy Subsector), 1990-2022 | E4: #VALUE! | G4: Gabriela | H4: World Resources Institute. (2024). Industry Is the Fastest Growing Source of Greenhouse Gas Emissions | I4: Source: Climate watch | J4: https://www.wri.org/insights/4-charts-explain-greenhouse-gas-emissions-countries-and-sectors | K4: Module 6 - Datasets for Charts.xlsx | L4: In process | M4: Ready | N4: Chart to recreate | O4: Line Chart Multi | P4: Yes | Q4: https://echarts.apache.org/examples/en/editor.html?c=line-race | R4: Yes | S4: Dataset updated through 2022
A5: 1 | B5: 26 | C5: =_xlfn.CONCAT("M",$B$1,"_C",ChartsM6[[#This Row],[Chapter]],"_",ChartsM6[[#This Row],['#]]) -> M6_C1_26 | D5: Global greenhouse gas emissions by sector and end use, 2021 | E5: #VALUE! | G5: Gabriela | H5: Climate Watch | I5: Source: Climate watch, 2021 | J5: https://www.wri.org/insights/4-charts-explain-greenhouse-gas-emissions-countries-and-sectors | K5: Module 6 - Datasets for Charts.xlsx | L5: Pending | M5: Pending | N5: Chart to recreate | O5: Sunburst with Rounded Corner | P5: Yes | Q5: https://echarts.apache.org/examples/en/editor.html?c=sunburst-borderRadius | R5: No | S5: When the chart appears you could increase the size of each part and when the user select each portion the value appears
A6: 1 | B6: 4 | C6: =_xlfn.CONCAT("M",$B$1,"_C",ChartsM6[[#This Row],[Chapter]],"_",ChartsM6[[#This Row],['#]]) -> M6_C1_4 | D6: Global energy-related greenhouse gas emissions, 2000-2022 | E6: #VALUE! | F6: #VALUE! | G6: Gabriela | H6: IEA. (2023). Global energy-related greenhouse gas emissions, 2000-2022 | I6: Source: Flaring emissions are from IEA analysis based on the World Bank Global Gas Flaring Reduction Programme. | J6: https://www.iea.org/data-and-statistics/charts/global-energy-related-greenhouse-gas-emissions-2000-2022 | K6: Module 6 - Datasets for Charts.xlsx | L6: In process | M6: Ready | N6: Chart to recreate | O6: Line Chart Stacked | P6: Yes | Q6: https://echarts.apache.org/examples/en/editor.html?c=area-stack | R6: Yes | S6: Like line race, but with area
A7: 1 | B7: 5 | C7: =_xlfn.CONCAT("M",$B$1,"_C",ChartsM6[[#This Row],[Chapter]],"_",ChartsM6[[#This Row],['#]]) -> M6_C1_5 | D7: Land use of different energy generation methods per unit of electricity | E7: #VALUE! | G7: Gabriela | H7: Our World in Data. (2022). How does the land use of different electricity sources compare? | I7: Source: Our World in Data, 2022 | J7: https://ourworldindata.org/land-use-per-energy-source#article-licence | K7: Module 6 - Datasets for Charts.xlsx | L7: Not supported by pipeline | M7: Ready | N7: Chart to recreate | P7: Yes | Q7: https://echarts.apache.org/examples/en/editor.html?c=data-transform-aggregate | R7: No | S7: When the chart appears you could increase the size of each part
A8: 2 | B8: 7 | C8: =_xlfn.CONCAT("M",$B$1,"_C",ChartsM6[[#This Row],[Chapter]],"_",ChartsM6[[#This Row],['#]]) -> M6_C2_7 | D8: Estimates of greenhouse gas emissions from different renewable and non-renewable energy technologies in electricity production | E8: #VALUE! | G8: Gabriela | H8: IPCC. (2011). Summary for Policymakers. In: IPCC Special Report on Renewable Energy Sources and Climate Change Mitigation [O. Edenhofer, R. Pichs-Madruga, Y. Sokona, K. Seyboth, P. Matschoss, S. Kadner, T. Zwickel, P. Eickemeier, G. Hansen, S. Schlömer, C. von Stechow (eds)], Cambridge University Press, Cambridge, United Kingdom and New York, NY, USA. | I8: Solar thermal and geothermal combined due to very small levels of activity. | J8: https://www.ipcc.ch/site/assets/uploads/2018/03/SRREN_Full_Report-1.pdf | K8: Module 6 - Datasets for Charts.xlsx | L8: Not supported by pipeline | M8: Ready | N8: Chart to recreate | O8: Boxplot Light Velocity | P8: Yes | Q8: https://echarts.apache.org/examples/en/editor.html?c=boxplot-light-velocity | R8: No | S8: Skip the table above if it is not relevant. | When the chart appears you could increase the size of each part
A9: 2 | B9: 8 | C9: =_xlfn.CONCAT("M",$B$1,"_C",ChartsM6[[#This Row],[Chapter]],"_",ChartsM6[[#This Row],['#]]) -> M6_C2_8 | D9: Potential air quality impacts in 2050 under two energy transition scenarios | E9: #VALUE! | G9: Gabriela | H9: ERM Sustainability Institute. (2024). RENEWABLES CONUNDRUMS Building Benefit: Four steps to mitigate renewable energy’s environmental downsides. | I9: Source: Building a Nature-Positive Energy Transformation (WWF), 2023 | J9: https://www.sustainability.com/globalassets/sustainability.com/reports/tl_renewables-conundrums-report-part-iii_0924_v4.pdf | K9: Module 6 - Datasets for Charts.xlsx | L9: In process | M9: Ready | N9: Chart to recreate | O9: Bar Chart Horizontal | P9: Yes | Q9: https://echarts.apache.org/examples/en/editor.html?c=bar-rich-text | R9: No | S9: You could combine with bar race
A10: 2 | B10: 9 | C10: =_xlfn.CONCAT("M",$B$1,"_C",ChartsM6[[#This Row],[Chapter]],"_",ChartsM6[[#This Row],['#]]) -> M6_C2_9 | D10: Disability-adjusted life years (DALY) from air pollution | E10: #VALUE! | G10: Gabriela | H10: ERM Sustainability Institute. (2024). RENEWABLES CONUNDRUMS Building Benefit: Four steps to mitigate renewable energy’s environmental downsides. | I10: https://www.worldwildlife.org/publications/building-a-nature-positive-energy-transformation--2 | J10: https://www.sustainability.com/globalassets/sustainability.com/reports/tl_renewables-conundrums-report-part-iii_0924_v4.pdf | K10: Module 6 - Datasets for Charts.xlsx | L10: In process | M10: Ready | N10: Chart to recreate | O10: Bar Chart Horizontal | P10: Yes | Q10: https://echarts.apache.org/examples/en/editor.html?c=bar-y-category | R10: No | S10: You could combine with bar race
A11: 2 | B11: 10 | C11: =_xlfn.CONCAT("M",$B$1,"_C",ChartsM6[[#This Row],[Chapter]],"_",ChartsM6[[#This Row],['#]]) -> M6_C2_10 | D11: Global energy sector water withdrawal by fuel and power generation method | E11: #VALUE! | G11: Gabriela | H11: ERM Sustainability Institute. (2024). RENEWABLES CONUNDRUMS Building Benefit: Four steps to mitigate renewable energy’s environmental downsides. | I11: Source: Clean energy can help to ease the water crisis (IEA), 2023 | J11: https://www.sustainability.com/globalassets/sustainability.com/reports/tl_renewables-conundrums-report-part-iii_0924_v4.pdf | K11: Module 6 - Datasets for Charts.xlsx | L11: In process | M11: Ready | N11: Chart to recreate | O11: Bar Chart Stacked Vertical | P11: Yes | Q11: https://echarts.apache.org/examples/en/editor.html?c=bar-stack | R11: Yes | S11: You could combine with bar race, may not possible in stacked chart
A12: 2 | B12: 23 | C12: =_xlfn.CONCAT("M",$B$1,"_C",ChartsM6[[#This Row],[Chapter]],"_",ChartsM6[[#This Row],['#]]) -> M6_C2_23 | D12: Global Renewable Capacity | E12: #VALUE! | H12: IRENA | L12: Pending | M12: Pending | N12: Chart to recreate | O12: Pie Chart
A13: 2 | B13: 11 | C13: =_xlfn.CONCAT("M",$B$1,"_C",ChartsM6[[#This Row],[Chapter]],"_",ChartsM6[[#This Row],['#]]) -> M6_C2_11 | D13: Weighted Average Cost of Capital for Onshore Wind Power and Solar PV, by Country Income Level, 2022 | E13: #VALUE! | G13: Divya | H13: Renewables 2024 Global Status Report Collection, Global Overview (REN21, 2024) | J13: https://www.ren21.net/wp-content/uploads/2019/05/240404_GSR2024_GO.pdf | K13: https://www.irena.org/Data/View-data-by-topic/Costs/Wind-Costs https://www.irena.org/Data/View-data-by-topic/Costs/Solar-costs | L13: Ready | M13: Ready | N13: Chart to recreate | O13: Bar Chart Categories Vertical | P13: Yes | Q13: https://echarts.apache.org/examples/en/editor.html?c=dataset-simple0 | R13: Yes
A14: 2 | B14: 27 | C14: =_xlfn.CONCAT("M",$B$1,"_C",ChartsM6[[#This Row],[Chapter]],"_",ChartsM6[[#This Row],['#]]) -> M6_C2_27 | D14: World Hydropower Technical Potential | E14: #VALUE! | F14: #VALUE! | G14: Divya | H14: IJHD (2010) | J14: https://www.researchgate.net/figure/Regional-hydropower-technical-potential-in-terms-of-annual-generation-and-installed_fig2_267639314 | K14: https://www.shutterstock.com/image-illustration/world-hydropower-statistics-2018-status-report-1199510938 | L14: Ready | M14: Ready | N14: Chart to recreate | R14: No | S14: Updated version in 2018 available
A15: 4 | B15: 28 | C15: =_xlfn.CONCAT("M",$B$1,"_C",ChartsM6[[#This Row],[Chapter]],"_",ChartsM6[[#This Row],['#]]) -> M6_C4_28 | D15: Net annual CO₂ emissions (GtCO₂/yr) | E15: #VALUE! | H15: IRENA | J15: https://www.irena.org/-/media/Files/IRENA/Agency/Publication/2021/Aug/IRENA_Bracing_for_climate_impact_2021.pdf | L15: Pending | M15: Pending | N15: Chart to recreate
A16: 4 | B16: 18 | C16: =_xlfn.CONCAT("M",$B$1,"_C",ChartsM6[[#This Row],[Chapter]],"_",ChartsM6[[#This Row],['#]]) -> M6_C4_18 | D16: Industrial Energy Consumption By Fuel, in the Net Zero Scenario, 2000- 2030 | E16: #VALUE! | G16: Divya | H16: Agency, Abu Dhabi. | J16: https://www.iea.org/data-and-statistics/charts/industrial-energy-consumption-by-fuel-in-the-net-zero-scenario-2000-2030 | L16: Ready | M16: In process | N16: Chart to recreate | O16: Bar Chart Stacked Vertical | P16: Yes | Q16: https://echarts.apache.org/examples/en/editor.html?c=bar-stack-normalization-and-variation | R16: Yes | S16: The remains could nt be found
A17: 4 | B17: 19 | C17: =_xlfn.CONCAT("M",$B$1,"_C",ChartsM6[[#This Row],[Chapter]],"_",ChartsM6[[#This Row],['#]]) -> M6_C4_19 | D17: Final energy consumption of buildings relative to other sectors, 2022 | E17: #VALUE! | G17: Divya | H17: IEA | J17: https://www.iea.org/data-and-statistics/charts/industrial-energy-consumption-by-fuel-in-the-net-zero-scenario-2000-2030 | L17: Ready | M17: Ready | N17: Chart to recreate | O17: Bar Chart Stacked Horizontal | P17: Yes | Q17: https://echarts.apache.org/examples/en/editor.html?c=bar-stack-normalization-and-variation | R17: Yes
A18: 4 | B18: 20 | C18: =_xlfn.CONCAT("M",$B$1,"_C",ChartsM6[[#This Row],[Chapter]],"_",ChartsM6[[#This Row],['#]]) -> M6_C4_20 | D18: Growth in Transport GHG Emissions, 2000-2018 | E18: #VALUE! | G18: Divya | H18: World Bank | J18: https://www.worldbank.org/en/programs/global-facility-to-decarbonize-transport | L18: Ready | M18: Pending | N18: Chart to recreate | O18: Line Chart Multi | P18: Yes | Q18: https://echarts.apache.org/examples/en/editor.html?c=line-race | R18: Yes
A19: 4 | B19: 21 | C19: =_xlfn.CONCAT("M",$B$1,"_C",ChartsM6[[#This Row],[Chapter]],"_",ChartsM6[[#This Row],['#]]) -> M6_C4_21 | D19: Prevalence of vehicle types | E19: #VALUE! | G19: Divya | H19: World Bank | I19: Note: 2W = Two-Wheeler, 3W = Three-Wheeler, 4W = Four-Wheeler; CO, = Carbon Dioxide. | J19: https://illuminem.com/illuminemvoices/electric-utopia-or-elite-privilege-rethinking-emobility-for-the-global-south | L19: Ready | M19: Ready | N19: Chart to recreate | O19: Bar Chart Stacked Normalized Vertical | P19: Yes | Q19: https://echarts.apache.org/examples/en/editor.html?c=bar-stack-normalization-and-variation | R19: Yes
A20: 4 | B20: 25 | C20: =_xlfn.CONCAT("M",$B$1,"_C",ChartsM6[[#This Row],[Chapter]],"_",ChartsM6[[#This Row],['#]]) -> M6_C4_25 | D20: Global employment in vehicle manufacturing, EV battery production | E20: #VALUE! | G20: Zhong | H20: IEA (2023, p.74) | J20: https://iea.blob.core.windows.net/assets/dfd9134f-12eb-4045-9789-9d6ab8d9fbf4/EnergyEfficiency2023.pdf | L20: Pending | M20: Pending | N20: Chart to recreate | O20: Bar Chart Stacked Vertical | P20: Yes | Q20: https://echarts.apache.org/examples/en/editor.html?c=bar-stack | R20: Yes | S20: Zhong: I cannot locate the exact data points to replicate the chart.
A21: 4 | B21: 22 | C21: =_xlfn.CONCAT("M",$B$1,"_C",ChartsM6[[#This Row],[Chapter]],"_",ChartsM6[[#This Row],['#]],"_1") -> M6_C4_22_1 | D21: Battery Demand By Mode and Region, 2016-2022 | E21: #VALUE! | F21: #VALUE! | G21: Zhong | H21: IEA (2023, p.56) | I21: Notes: LDVs = light-duty vehicles, including cars and vans; In the left chart, “Other” includes medium- and heavy-duty trucks and two/three-wheelers. Battery demand refers to automotive lithium-ion batteries. This analysis does not include conventional hybrid vehicles. Source: IEA analysis based on EV Volumes. | J21: https://iea.blob.core.windows.net/assets/dacf14d2-eabc-498a-8263-9f97fd5dc327/GEVO2023.pdf | K21: M6_C4_22 | L21: Ready | M21: Ready | N21: Chart to recreate | O21: Bar Chart Stacked Vertical | P21: Yes | Q21: https://echarts.apache.org/examples/en/editor.html?c=bar-stack | R21: Yes | S21: Zhong: Original data source: https://www.iea.org/data-and-statistics/charts/battery-demand-by-region-2016-2022 https://www.iea.org/data-and-statistics/charts/battery-demand-by-mode-2016-2022 Apache example: https://echarts.apache.org/examples/en/editor.html?c=bar-stack
A22: 4 | B22: 22 | C22: =_xlfn.CONCAT("M",$B$1,"_C",ChartsM6[[#This Row],[Chapter]],"_",ChartsM6[[#This Row],['#]],"_2") -> M6_C4_22_2 | D22: Battery Demand By Mode and Region, 2016-2022 | E22: #VALUE! | F22: #VALUE! | G22: Zhong | H22: IEA (2023, p.56) | I22: Notes: LDVs = light-duty vehicles, including cars and vans; In the left chart, “Other” includes medium- and heavy-duty trucks and two/three-wheelers. Battery demand refers to automotive lithium-ion batteries. This analysis does not include conventional hybrid vehicles. Source: IEA analysis based on EV Volumes. | J22: https://iea.blob.core.windows.net/assets/dacf14d2-eabc-498a-8263-9f97fd5dc327/GEVO2023.pdf | K22: M6_C4_22 | L22: Ready | M22: Ready | N22: Chart to recreate | O22: Bar Chart Stacked Vertical | P22: Yes | Q22: https://echarts.apache.org/examples/en/editor.html?c=bar-stack | R22: Yes | S22: Zhong: Original data source: https://www.iea.org/data-and-statistics/charts/battery-demand-by-region-2016-2022 https://www.iea.org/data-and-statistics/charts/battery-demand-by-mode-2016-2022 Apache example: https://echarts.apache.org/examples/en/editor.html?c=bar-stack

Sheet Module7
A1: Module | B1: 7
A2: Chapter | B2: # | C2: Figure ID | D2: Title | E2: Screenshot | F2: New Screenshot | G2: Lead | H2: Source (APA) | I2: Footnote | J2: Source Link | K2: Dataset Link | L2: Chart Status | M2: Dataset Status | N2: Category | O2: Chart Type | P2: Apache Possible | Q2: Apache Link | R2: Automation Possible | S2: Notes | T2: Column1
A3: 2 | B3: 1 | C3: =_xlfn.CONCAT("M",$B$1,"_C",ChartsM7[[#This Row],[Chapter]],"_",ChartsM7[[#This Row],['#]]) -> M7_C2_1 | D3: Female representation in senior management in different sectors and industries, 2019 | E3: #VALUE! | G3: Zhong | H3: IEA (2021) | I3: Based on data from almost 2 500 firms and over 38 000 employees, women make up only 13.9% of senior management within the energy and energy utilities composite, which is marginally lower than in the over 30 000 firms in the sample from non-energy industries at 15.5%. | J3: https://www.iea.org/commentaries/women-in-senior-management-roles-at-energy-firms-remains-stubbornly-low-but-efforts-to-improve-gender-diversity-are-moving-apace | K3: Module 7 - Datasets for Charts.xlsx | L3: In process | M3: Ready | N3: Chart to recreate | O3: Bar chart | P3: Yes | Q3: https://echarts.apache.org/examples/en/editor.html?c=bar-y-category | R3: No | S3: Zhong: It seems Apache does not have a matching chart type. Consider converting it into a bar chart: https://echarts.apache.org/examples/en/editor.html?c=bar-y-category The original data can be accessed via https://www.iea.org/data-and-statistics/charts/female-representation-in-senior-management-in-different-sectors-and-industries-2019 | T3: This can be used. in chapter 2, lession2, towards the end of part 2
A4: 2 | B4: 5 | C4: =_xlfn.CONCAT("M",$B$1,"_C",ChartsM7[[#This Row],[Chapter]],"_",ChartsM7[[#This Row],['#]]) -> M7_C2_5 | D4: Share of women in selected energy-related occupations, 2023 | E4: #VALUE! | G4: Divya | H4: UN Women (2023) | J4: https://www.iea.org/data-and-statistics/charts/share-of-women-in-selected-energy-related-occupations-2023 | K4: Module 7 - Datasets for Charts.xlsx | L4: In process | M4: Ready | N4: Chart to recreate | O4: Bar Chart Horizontal | P4: Yes | Q4: https://echarts.apache.org/examples/en/editor.html?c=bar-stack-normalization-and-variation | R4: Yes | T4: chapter 2.3.1 sex disaggregated data in energy
A5: 2 | B5: 8 | C5: =_xlfn.CONCAT("M",$B$1,"_C",ChartsM7[[#This Row],[Chapter]],"_",ChartsM7[[#This Row],['#]]) -> M7_C2_8 | D5: Gender data availability for SDG monitoring by region, 2022 | E5: #VALUE! | G5: Gabriela | H5: Sustainable Energy for All. (2024) | J5: report-g&y-genderdatastudy-002_compressed.pdf | K5: Module 7 - Datasets for Charts.xlsx | L5: In process | M5: Review pending | N5: Chart to recreate | O5: Bar Chart Stacked Horizontal | P5: Yes | Q5: Examples - Apache ECharts | R5: Yes | S5: May you can create a world map and also add the bar chart | T5: chapter 2.3.1 gender statistics in energy
A6: 3 | B6: 4 | C6: =_xlfn.CONCAT("M",$B$1,"_C",ChartsM7[[#This Row],[Chapter]],"_",ChartsM7[[#This Row],['#]]) -> M7_C3_4 | D6: Global Greenhouse Gas Emissions Reduction Forecast | G6: Divya | J6: https://www.weforum.org/stories/2016/11/paris-climate-deal-could-still-fail/ | K6: Module 7 - Datasets for Charts.xlsx | L6: Not supported by pipeline | M6: Review pending | N6: Chart to recreate | O6: Line Chart Multi | P6: Yes | Q6: https://echarts.apache.org/examples/en/editor.html?c=line-race | R6: Yes | T6: for chapter 3.2.1 prescriptive modelling
A7: 4 | B7: 9 | C7: =_xlfn.CONCAT("M",$B$1,"_C",ChartsM7[[#This Row],[Chapter]],"_",ChartsM7[[#This Row],['#]]) -> M7_C4_9 | D7: The evolution of blockchain | G7: Gabriela | H7: Shamika, N. (2021). How blockchain can power sustainable development. | J7: How blockchain can power sustainable development | UN Trade and Development (UNCTAD) | L7: In process | N7: Infographic WITHOUT Data | P7: No | S7: There's no possible chart type in Apache examples, but it's just a timeline | T7: chapter 4.2.1 blockchain technologies in energy innovation
A8: 1 | B8: 6 | C8: =_xlfn.CONCAT("M",$B$1,"_C",ChartsM7[[#This Row],[Chapter]],"_",ChartsM7[[#This Row],['#]]) -> M7_C1_6 | D8: Percentage of energy transition minerals located in countries with high levels of corruption | E8: #VALUE! | G8: Divya | J8: https://transparency.org.au/corruption-minerals-energy-transition-risk/ | L8: Deleted | M8: Deleted | N8: Chart to recreate | O8: Donut chart | Q8: https://echarts.apache.org/examples/en/editor.html?c=dataset-default | R8: No | T8: chapter 1.1.3 data and it's beneficiaries in the energy sector. (to show benefits in globl energy strategy planning)
A9: 1 | B9: 7 | C9: =_xlfn.CONCAT("M",$B$1,"_C",ChartsM7[[#This Row],[Chapter]],"_",ChartsM7[[#This Row],['#]]) -> M7_C1_7 | D9: SOI Digital transformation Journey | E9: #VALUE! | G9: Gabriela | H9: Victorial, Z. (2024). A digital transformation journey driven by data since 2020 in Solomon Islands. | J9: A digital transformation journey driven by data since 2020 in Solomon Islands - UN Capital Development Fund (UNCDF) | L9: Deleted | M9: Deleted | N9: Infographic WITHOUT Data | P9: No | S9: For case of study: Solomon Islands | There's no possible chart type in Apache examples, but it's just a timeline | T9: chapter 1.1.2 case study: the policy cycle and data's role in decision making
B10: 2 | C10: =_xlfn.CONCAT("M",$B$1,"_C",ChartsM7[[#This Row],[Chapter]],"_",ChartsM7[[#This Row],['#]]) -> M7_C_2 | D10: Validating Energy Data with Different Sources to Spot Anomalies | E10: #VALUE! | G10: Zhong | H10: IEA (2014, p.159) | I10: This figure shows an example of problems detected while validating data of energy consumption for an industrial sub-sector against energy balances data for the same sub-sector. Notes: unless otherwise indicated, all tables and figures in this chapter derive from IEA data and analysis. Ktoe is kilotonnes of oil equivalent. | J10: https://iea.blob.core.windows.net/assets/6862080c-8614-494e-a8aa-52c3c0d4291b/IEA_EnergyEfficiencyIndicatorsFundamentalsonStatistics.pdf | L10: Deleted | O10: Line Chart Multi | P10: Yes | Q10: https://echarts.apache.org/examples/en/editor.html?c=line-stack | R10: Yes | S10: Zhong: Apache examplpe: Stacked Line Chart https://echarts.apache.org/examples/en/editor.html?c=line-stack | T10: No good matching with the content
B11: 3 | C11: =_xlfn.CONCAT("M",$B$1,"_C",ChartsM7[[#This Row],[Chapter]],"_",ChartsM7[[#This Row],['#]]) -> M7_C_3 | D11: Exploring the Ranges of Observed Energy Data to Sopt Outliers | E11: #VALUE! | G11: Zhong | H11: IEA (2014, p.162) | I11: This table presents observed values based on the IEA data collection from fourteen OECD countries. Unit energy consumption (UEC) of appliances, as well as average daily unit energy consumption, should be within reasonable ranges. | J11: https://iea.blob.core.windows.net/assets/6862080c-8614-494e-a8aa-52c3c0d4291b/IEA_EnergyEfficiencyIndicatorsFundamentalsonStatistics.pdf | L11: Deleted | P11: Yes | Q11: https://echarts.apache.org/examples/en/editor.html?c=data-transform-aggregate | R11: No | S11: Zhong: The table could be converted into a boxplot to show the min, max, and median. Apache boxplot example: https://echarts.apache.org/examples/en/editor.html?c=data-transform-aggregate | T11: Could have been useful in discussing data validation. but in the lesson it is talk about differently and this is not suiable. cf. chapter 3.1.clustering and anomali detection

Sheet Module8
A1: Module | B1: 8
A2: Chapter | B2: # | C2: Figure ID | D2: Title | E2: Screenshot | F2: New Screenshot | G2: Lead | H2: Source (APA) | I2: Footnote | J2: Source Link | K2: Dataset Link | L2: Chart Status | M2: Dataset Status | N2: Category | O2: Chart Type | P2: Apache Possible | Q2: Apache Link | R2: Automation Possible | S2: Notes
A3: 1 | B3: 1 | C3: =_xlfn.CONCAT("M",$B$1,"_C",ChartsM8[[#This Row],[Chapter]],"_",ChartsM8[[#This Row],['#]]) -> M8_C1_1 | D3: Global Energy Supply by Source in STEPS and APC, 2000-2050 | E3: #VALUE! | H3: IEA, 2023 | J3: https://iea.blob.core.windows.net/assets/140a0470-5b90-4922-a0e9-838b3ac6918c/WorldEnergyOutlook2024.pdf | L3: In process | M3: Ready | N3: Chart to recreate | O3: Bar Chart Stacked Vertical | P3: Yes | R3: Yes
A4: 1 | B4: 2 | C4: =_xlfn.CONCAT("M",$B$1,"_C",ChartsM8[[#This Row],[Chapter]],"_",ChartsM8[[#This Row],['#]]) -> M8_C1_2 | D4: Breakdown of total final energy consumption by energy carrier between 2022, 2030 and 2050 under the 1.5C Scenario | E4: #VALUE! | H4: IRENA, 2024 | J4: https://www.irena.org/-/media/Files/IRENA/Agency/Publication/2024/Nov/IRENA_World_energy_transitions_outlook_2024.pdf | L4: Not supported by pipeline | M4: Pending | N4: Infographic WITH Data
A5: 1 | B5: 3 | C5: =_xlfn.CONCAT("M",$B$1,"_C",ChartsM8[[#This Row],[Chapter]],"_",ChartsM8[[#This Row],['#]]) -> M8_C1_3 | D5: Global population Projections from 2013 and 2024 | E5: #VALUE! | H5: UNDESA, 2024 | J5: https://desapublications.un.org/publications/world-population-prospects-2024-summary-results | K5: Module 8 - Datasets for Charts.xlsx | L5: Not supported by pipeline | M5: Review pending | N5: Chart to recreate | O5: Line Chart Multi
A6: 1 | B6: 4 | C6: =_xlfn.CONCAT("M",$B$1,"_C",ChartsM8[[#This Row],[Chapter]],"_",ChartsM8[[#This Row],['#]]) -> M8_C1_4 | D6: Projected change of population in urban and rural areas by region, 2023 to 2050 | E6: #VALUE! | G6: Danae | H6: IEA, 2024 | J6: https://iea.blob.core.windows.net/assets/140a0470-5b90-4922-a0e9-838b3ac6918c/WorldEnergyOutlook2024.pdf | K6: Module 8 - Datasets for Charts.xlsx | L6: In process | M6: Review pending | N6: Chart to recreate | O6: Bar Chart Stacked Horizontal
A7: 1 | B7: 5 | C7: =_xlfn.CONCAT("M",$B$1,"_C",ChartsM8[[#This Row],[Chapter]],"_",ChartsM8[[#This Row],['#]]) -> M8_C1_5 | D7: Estimated data center electricity demand due to AI, 2020-2030 | E7: #VALUE! | H7: IEA, 2025 | J7: https://iea.blob.core.windows.net/assets/34eac603-ecf1-464f-b813-2ecceb8f81c2/EnergyandAI.pdf | K7: Module 8 - Datasets for Charts.xlsx | L7: In process | M7: Review pending | N7: Chart to recreate | O7: Line Chart Multi | S7: Shade: Would rather have a graph with only the global demand ( without the US) or with other developing countries.
A8: 1 | B8: 6 | C8: =_xlfn.CONCAT("M",$B$1,"_C",ChartsM8[[#This Row],[Chapter]],"_",ChartsM8[[#This Row],['#]]) -> M8_C1_6 | D8: Evolution of global Power Generation, 1995-2050 | E8: #VALUE! | H8: McKinsey, 2024 | J8: https://www.mckinsey.com/industries/energy-and-materials/our-insights/global-energy-perspective#/ | K8: Module 8 - Datasets for Charts.xlsx | L8: In process | M8: Ready | N8: Chart to recreate | O8: Bar Chart Stacked Vertical | P8: Yes | R8: Yes
A9: 1 | B9: 7 | C9: =_xlfn.CONCAT("M",$B$1,"_C",ChartsM8[[#This Row],[Chapter]],"_",ChartsM8[[#This Row],['#]],"_1") -> M8_C1_7_1 | D9: Projections for global coal, oil and gas production, 2020-2050 - Oil Production | E9: #VALUE! | H9: UNEP, 2023 | J9: https://productiongap.org/wp-content/uploads/2023/11/PGR2023_web_rev.pdf | K9: Module 8 - Datasets for Charts.xlsx | L9: In process | M9: Review pending | N9: Chart to recreate | O9: Line Chart Multi
A10: 1 | B10: 7 | C10: =_xlfn.CONCAT("M",$B$1,"_C",ChartsM8[[#This Row],[Chapter]],"_",ChartsM8[[#This Row],['#]],"_2") -> M8_C1_7_2 | D10: Projections for global coal, oil and gas production, 2020-2050 - Coal production | E10: #VALUE! | H10: UNEP, 2023 | J10: https://productiongap.org/wp-content/uploads/2023/11/PGR2023_web_rev.pdf | K10: Module 8 - Datasets for Charts.xlsx | L10: In process | M10: Review pending | N10: Chart to recreate
A11: 1 | B11: 7 | C11: =_xlfn.CONCAT("M",$B$1,"_C",ChartsM8[[#This Row],[Chapter]],"_",ChartsM8[[#This Row],['#]],"_3") -> M8_C1_7_3 | D11: Projections for global coal, oil and gas production, 2020-2050 - Gas production | E11: #VALUE! | H11: UNEP, 2023 | J11: https://productiongap.org/wp-content/uploads/2023/11/PGR2023_web_rev.pdf | K11: Module 8 - Datasets for Charts.xlsx | L11: In process | M11: Review pending | N11: Chart to recreate
A12: 1 | B12: 8 | C12: =_xlfn.CONCAT("M",$B$1,"_C",ChartsM8[[#This Row],[Chapter]],"_",ChartsM8[[#This Row],['#]],"_1") -> M8_C1_8_1 | D12: Global critical minerals demand in the STEPS, 2024-2040 - Copper | E12: #VALUE! | G12: Danae | H12: IEA, 2025 | J12: https://iea.blob.core.windows.net/assets/a33abe2e-f799-4787-b09b-2484a6f5a8e4/GlobalCriticalMineralsOutlook2025.pdf | K12: Module 8 - Datasets for Charts.xlsx | L12: In process | M12: Review pending | N12: Chart to recreate | O12: Bar Chart Stacked Vertical | P12: Yes | Q12: https://echarts.apache.org/examples/en/editor.html?c=bar-polar-stack-radial
A13: 1 | B13: 8 | C13: =_xlfn.CONCAT("M",$B$1,"_C",ChartsM8[[#This Row],[Chapter]],"_",ChartsM8[[#This Row],['#]],"_2") -> M8_C1_8_2 | D13: Global critical minerals demand in the STEPS, 2024-2040 - Lithium | E13: #VALUE! | G13: Danae | H13: IEA, 2025 | J13: https://iea.blob.core.windows.net/assets/a33abe2e-f799-4787-b09b-2484a6f5a8e4/GlobalCriticalMineralsOutlook2025.pdf | K13: Module 8 - Datasets for Charts.xlsx | L13: In process | M13: Review pending | N13: Chart to recreate | O13: Bar Chart Stacked Vertical | P13: Yes | Q13: https://echarts.apache.org/examples/en/editor.html?c=bar-polar-stack-radial
A14: 1 | B14: 8 | C14: =_xlfn.CONCAT("M",$B$1,"_C",ChartsM8[[#This Row],[Chapter]],"_",ChartsM8[[#This Row],['#]],"_3") -> M8_C1_8_3 | D14: Global critical minerals demand in the STEPS, 2024-2040 - Nickel | E14: #VALUE! | G14: Danae | H14: IEA, 2025 | J14: https://iea.blob.core.windows.net/assets/a33abe2e-f799-4787-b09b-2484a6f5a8e4/GlobalCriticalMineralsOutlook2025.pdf | K14: Module 8 - Datasets for Charts.xlsx | L14: In process | M14: Review pending | N14: Chart to recreate | O14: Bar Chart Stacked Vertical | P14: Yes | Q14: https://echarts.apache.org/examples/en/editor.html?c=bar-polar-stack-radial
A15: 1 | B15: 8 | C15: =_xlfn.CONCAT("M",$B$1,"_C",ChartsM8[[#This Row],[Chapter]],"_",ChartsM8[[#This Row],['#]],"_4") -> M8_C1_8_4 | D15: Global critical minerals demand in the STEPS, 2024-2040 - Cobalt | E15: #VALUE! | G15: Danae | H15: IEA, 2025 | J15: https://iea.blob.core.windows.net/assets/a33abe2e-f799-4787-b09b-2484a6f5a8e4/GlobalCriticalMineralsOutlook2025.pdf | K15: Module 8 - Datasets for Charts.xlsx | L15: In process | M15: Review pending | N15: Chart to recreate | O15: Bar Chart Stacked Vertical | P15: Yes | Q15: https://echarts.apache.org/examples/en/editor.html?c=bar-polar-stack-radial
A16: 1 | B16: 8 | C16: =_xlfn.CONCAT("M",$B$1,"_C",ChartsM8[[#This Row],[Chapter]],"_",ChartsM8[[#This Row],['#]],"_5") -> M8_C1_8_5 | D16: Global critical minerals demand in the STEPS, 2024-2040 - Graphite | E16: #VALUE! | G16: Danae | H16: IEA, 2025 | J16: https://iea.blob.core.windows.net/assets/a33abe2e-f799-4787-b09b-2484a6f5a8e4/GlobalCriticalMineralsOutlook2025.pdf | K16: Module 8 - Datasets for Charts.xlsx | L16: In process | M16: Review pending | N16: Chart to recreate | O16: Bar Chart Stacked Vertical | P16: Yes | Q16: https://echarts.apache.org/examples/en/editor.html?c=bar-polar-stack-radial
A17: 1 | B17: 8 | C17: =_xlfn.CONCAT("M",$B$1,"_C",ChartsM8[[#This Row],[Chapter]],"_",ChartsM8[[#This Row],['#]],"_6") -> M8_C1_8_6 | D17: Global critical minerals demand in the STEPS, 2024-2040 - Rare Earths | E17: #VALUE! | G17: Danae | H17: IEA, 2025 | J17: https://iea.blob.core.windows.net/assets/a33abe2e-f799-4787-b09b-2484a6f5a8e4/GlobalCriticalMineralsOutlook2025.pdf | K17: Module 8 - Datasets for Charts.xlsx | L17: In process | M17: Review pending | N17: Chart to recreate | O17: Bar Chart Stacked Vertical | P17: Yes | Q17: https://echarts.apache.org/examples/en/editor.html?c=bar-polar-stack-radial
A18: 1 | B18: 9 | C18: =_xlfn.CONCAT("M",$B$1,"_C",ChartsM8[[#This Row],[Chapter]],"_",ChartsM8[[#This Row],['#]],"_1") -> M8_C1_9_1 | D18: Reduction in primary supply requirements from recycling in the APS, 2020-2050 - Copper | E18: #VALUE! | G18: Danae | H18: IEA, 2024 | J18: https://iea.blob.core.windows.net/assets/3af7fda6-8fd9-46b7-bede-395f7f8f9943/RecyclingofCriticalMinerals.pdf | K18: Module 8 - Datasets for Charts.xlsx | L18: In process | M18: Review pending | N18: Chart to recreate | O18: Line Chart Multi
A19: 1 | B19: 9 | C19: =_xlfn.CONCAT("M",$B$1,"_C",ChartsM8[[#This Row],[Chapter]],"_",ChartsM8[[#This Row],['#]],"_2") -> M8_C1_9_2 | D19: Reduction in primary supply requirements from recycling in the APS, 2020-2050 - Lithium | E19: #VALUE! | G19: Danae | H19: IEA, 2024 | J19: https://iea.blob.core.windows.net/assets/3af7fda6-8fd9-46b7-bede-395f7f8f9943/RecyclingofCriticalMinerals.pdf | K19: Module 8 - Datasets for Charts.xlsx | L19: In process | M19: Review pending | N19: Chart to recreate | O19: Line Chart Multi
A20: 1 | B20: 9 | C20: =_xlfn.CONCAT("M",$B$1,"_C",ChartsM8[[#This Row],[Chapter]],"_",ChartsM8[[#This Row],['#]],"_3") -> M8_C1_9_3 | D20: Reduction in primary supply requirements from recycling in the APS, 2020-2050 - Nickel | E20: #VALUE! | G20: Danae | H20: IEA, 2024 | J20: https://iea.blob.core.windows.net/assets/3af7fda6-8fd9-46b7-bede-395f7f8f9943/RecyclingofCriticalMinerals.pdf | K20: Module 8 - Datasets for Charts.xlsx | L20: In process | M20: Review pending | N20: Chart to recreate | O20: Line Chart Multi
A21: 1 | B21: 9 | C21: =_xlfn.CONCAT("M",$B$1,"_C",ChartsM8[[#This Row],[Chapter]],"_",ChartsM8[[#This Row],['#]],"_4") -> M8_C1_9_4 | D21: Reduction in primary supply requirements from recycling in the APS, 2020-2050 - Cobalt | E21: #VALUE! | G21: Danae | H21: IEA, 2024 | J21: https://iea.blob.core.windows.net/assets/3af7fda6-8fd9-46b7-bede-395f7f8f9943/RecyclingofCriticalMinerals.pdf | K21: Module 8 - Datasets for Charts.xlsx | L21: In process | M21: Review pending | N21: Chart to recreate | O21: Line Chart Multi
A22: 1 | B22: 10 | C22: =_xlfn.CONCAT("M",$B$1,"_C",ChartsM8[[#This Row],[Chapter]],"_",ChartsM8[[#This Row],['#]]) -> M8_C1_10 | D22: Average number of weekly cyberattacks per organization in selected industries, 2020-2022 | E22: #VALUE! | G22: Danae | H22: IEA, 2023 | J22: https://www.iea.org/commentaries/cybersecurity-is-the-power-system-lagging-behind | K22: Module 8 - Datasets for Charts.xlsx | L22: In process | M22: Ready | N22: Chart to recreate | O22: Bar Chart Categories Vertical | P22: Yes | R22: Yes
A23: 1 | B23: 11 | C23: =_xlfn.CONCAT("M",$B$1,"_C",ChartsM8[[#This Row],[Chapter]],"_",ChartsM8[[#This Row],['#]]) -> M8_C1_11 | D23: Land use of energy sources per unit of electricity | E23: #VALUE! | H23: UNECE, 2021 | J23: https://ourworldindata.org/land-use-per-energy-source?itid=lk_inline_enhanced-template | L23: In process | N23: Chart for Direct Use
A24: 2 | B24: 12 | C24: =_xlfn.CONCAT("M",$B$1,"_C",ChartsM8[[#This Row],[Chapter]],"_",ChartsM8[[#This Row],['#]],"_1") -> M8_C2_12_1 | D24: Historical and projected global wind installation, 2021-2030 | E24: #VALUE! | G24: Danae | H24: GWEC, 2025 | J24: https://26973329.fs1.hubspotusercontent-eu1.net/hubfs/26973329/2.%20Reports/Global%20Wind%20Report/GWEC%20Global%20Wind%20Report%202025.pdf | K24: Module 8 - Datasets for Charts.xlsx | L24: In process | M24: Ready | N24: Chart to recreate | O24: Bar Chart Stacked Vertical | P24: Yes | R24: Yes
A25: 2 | B25: 12 | C25: =_xlfn.CONCAT("M",$B$1,"_C",ChartsM8[[#This Row],[Chapter]],"_",ChartsM8[[#This Row],['#]],"_2") -> M8_C2_12_2 | D25: Historical and projected global wind installation, 2021-2030 | E25: #VALUE! | G25: Danae | H25: GWEC, 2025 | J25: https://26973329.fs1.hubspotusercontent-eu1.net/hubfs/26973329/2.%20Reports/Global%20Wind%20Report/GWEC%20Global%20Wind%20Report%202025.pdf | K25: Module 8 - Datasets for Charts.xlsx | L25: In process | M25: Ready | N25: Chart to recreate | O25: Line Chart | P25: Yes | R25: Yes
A26: 2 | B26: 13 | C26: =_xlfn.CONCAT("M",$B$1,"_C",ChartsM8[[#This Row],[Chapter]],"_",ChartsM8[[#This Row],['#]]) -> M8_C2_13 | D26: Global Ocean Energy Capacity Forecast, 2030 and 2050 | E26: #VALUE! | G26: Danae | H26: IRENA, 2020 | J26: https://www.oceanenergy-europe.eu/wp-content/uploads/2023/03/IRENA_OEE_Scaling_up_investment_ocean_energy_2023.pdf | K26: Module 8 - Datasets for Charts.xlsx | L26: In process | M26: Ready | N26: Chart to recreate | O26: Bar Chart Vertical | P26: Yes | R26: Yes
A27: 2 | B27: 14 | C27: =_xlfn.CONCAT("M",$B$1,"_C",ChartsM8[[#This Row],[Chapter]],"_",ChartsM8[[#This Row],['#]]) -> M8_C2_14 | D27: Global Ocean Energy Potential | E27: #VALUE! | G27: Danae | H27: IRENA, 2020 | J27: https://www.oceanenergy-europe.eu/wp-content/uploads/2023/03/IRENA_OEE_Scaling_up_investment_ocean_energy_2023.pdf | K27: Module 8 - Datasets for Charts.xlsx | L27: In process | M27: Ready | N27: Chart to recreate | O27: Doughnut Chart | P27: Yes | R27: Yes
A28: 3 | B28: 15 | C28: =_xlfn.CONCAT("M",$B$1,"_C",ChartsM8[[#This Row],[Chapter]],"_",ChartsM8[[#This Row],['#]]) -> M8_C3_15 | D28: Early and growth-stage equity investment in energy start-ups by region and technology area, 2020-2022 | E28: #VALUE! | G28: Danae | H28: IEA, 2023 | J28: https://www.iea.org/reports/world-energy-investment-2023 | K28: Module 8 - Datasets for Charts.xlsx | L28: In process | M28: Ready | N28: Chart to recreate | O28: Bar Chart Stacked Normalized Vertical | P28: Yes | R28: Yes

Sheet (Legacy) Module4 
A1: Module | B1: 4
A2: Chapter | B2: # | C2: Figure ID | D2: Title | E2: Subtitle | F2: Screenshot | G2: New Screenshot (if available) | H2: Category | I2: Status | J2: LEAD | K2: Source (APA) | L2: Source Link | M2: Footnote | N2: DataViz possible? | O2: Chart Type UNDP | P2: Apache possible | Q2: Chart Type | R2: Dataset Status | S2: Dataset Link | T2: Apache Link | U2: Notes
A3: 1 | B3: 1 | C3: =_xlfn.CONCAT("M",$B$1,"_C",ChartsM45[[#This Row],[Chapter]],"_",ChartsM45[[#This Row],['#]]) -> M4_C1_1 | D3: Annual clean energy investment, 2015-2023 | F3: #VALUE! | G3: #VALUE! | H3: Chart to recreate | I3: Ready | J3: Zhong | K3: International Energy Agency (2023, p.10) | L3: https://iea.blob.core.windows.net/assets/8834d3af-af60-4df0-9643-72e2684f7221/WorldEnergyInvestment2023.pdf | M3: Notes: “Low-emission fuels” include modern liquid and gaseous bioenergy, low-emission hydrogen and hydrogen-based fuels that do not emit any CO2 from fossil fuels directly when used and emit very little when being produced; “Other end use” refers to renewables for end use and electrification in the buildings, transport and industrial sectors. 2023e = estimated values for 2023; CCUS = carbon capture, utilisation and storage; EV = electric vehicle. | N3: Yes | O3: Bar chart - Vertical - Stacked | P3: Yes | Q3: Stacked Column Chart | R3: Ready | S3: M4_C1_1 | T3: https://echarts.apache.org/examples/en/editor.html?c=bar-stack | U3: Zhong: Apache Example: https://echarts.apache.org/examples/en/editor.html?c=bar-stack Zhong: The original screenshot of the chart titled "Annual global investment in renewable energy, energy efficiency, and other transition-related technologies, 2015-2022" only shows data from 2015 to 2022 (see page 10 from https://www.irena.org/-/media/Files/IRENA/Agency/Publication/2023/Feb/IRENA_CPI_Global_RE_finance_2023.pdf). The old chart also did not show the exact breakdown headcount of different energies. However, the new dataset contains 2023 data and shows breakdowns. Additonal link to the new data: https://www.iea.org/data-and-statistics/charts/annual-clean-energy-investment-2015-2023 Zhong: need to add data labels for small data points.
A4: 1 | B4: 3 | C4: =_xlfn.CONCAT("M",$B$1,"_C",ChartsM45[[#This Row],[Chapter]],"_",ChartsM45[[#This Row],['#]]) -> M4_C1_3 | D4: Investment in renewable energy by region of destination, 2013-2022 | F4: #VALUE! | H4: Chart to recreate | I4: Ready | J4: Zhong | K4: IRENA (2023, p.54) | L4: https://www.irena.org/-/media/Files/IRENA/Agency/Publication/2023/Feb/IRENA_CPI_Global_RE_finance_2023.pdf | M4: Note: “North America (excluding Mexico)” includes Bermuda, Canada and the United States. “Others” include the Middle East and North Africa, Other Oceania, Transregional, Other Asia and Unknown. For more details on the geographic classification used in the analysis, please see methodology document (Appendix). Source: CPI (2022a). Investments for 2021 and 2022 represent preliminary estimates based on data from BNEF (2023b) | N4: Yes | O4: Bar chart - Vertical - Stacked | P4: Yes | Q4: Stacked Bar Normalization | R4: Ready | S4: M4_C1_3 | T4: https://echarts.apache.org/examples/en/editor.html?c=bar-stack-normalization | U4: Zhong: Apache Example: https://echarts.apache.org/examples/en/editor.html?c=bar-stack-normalization Zhong: The source does not privide exact breakdowns for small data points (they are extracted by ChatGPT). Zhong: need to explain the denifition of different regions (e.g., Eurasia, Sub-Saharan Africa); need to add data labels for small data points.
A5: 1 | B5: 4 | C5: =_xlfn.CONCAT("M",$B$1,"_C",ChartsM45[[#This Row],[Chapter]],"_",ChartsM45[[#This Row],['#]]) -> M4_C1_4 | D5: Annual investment in clean energy by selected country and region, 2019 and 2024 | F5: #VALUE! | G5: #VALUE! | H5: Chart to recreate | I5: Ready | J5: Zhong | K5: International Energy Agency (2024, p.5) | L5: https://iea.blob.core.windows.net/assets/60fcd1dd-d112-469b-87de-20d39227df3d/WorldEnergyInvestment2024.pdf | M5: Note: 2024e = estimated values for 2024. US = United States. EU = European Union. | N5: Yes | O5: Bar chart - Vertical - Stacked | P5: Yes | Q5: Stacked Column Chart | R5: Ready | S5: M4_C1_4 | T5: https://echarts.apache.org/examples/en/editor.html?c=bar-stack | U5: Zhong: need to add data labels for small data points. Zhong: Apache Example: https://echarts.apache.org/examples/en/editor.html?c=bar-stack Zhong: Exact data points can be downloaded from https://www.iea.org/data-and-statistics/charts/annual-investment-in-clean-energy-by-selected-country-and-region-2019-and-2024
A6: 1 | B6: 8 | C6: =_xlfn.CONCAT("M",$B$1,"_C",ChartsM45[[#This Row],[Chapter]],"_",ChartsM45[[#This Row],['#]]) -> M4_C1_8 | D6: Global primary energy consumption by source. | F6: #VALUE! | G6: #VALUE! | H6: Chart to recreate | I6: Ready | J6: Zhong | K6: Our World in Data (2024) via Energy Institute - Statistical Review of World Energy (2024), Smil (2017) | L6: https://ourworldindata.org/grapher/global-energy-consumption-source | M6: Note: In the absence of more recent data, traditional biomass is assumed constant since 2015. | N6: Yes | O6: Line chart - Multi-line | P6: Yes | Q6: Stacked Line Chart | R6: Ready | S6: M4_C1_8 | T6: https://echarts.apache.org/examples/en/editor.html?c=line-stack | U6: Zhong: Apache Example: https://echarts.apache.org/examples/en/editor.html?c=line-stack Notes not from Zhong: The graph here sends the opposite message we are trying to send in this section. While RE investments have increased over time and are now exceeding fossil fuel investments, RE-share in global primary energy consumption remains marginal showing the long way we still have ahead of us to decarbonize energy systems. To send a more optimistic message we may want to focus on electricity sector figure where the share of renewable is steadily inceasing and projected to go beyond 30% before 2030 Zhong: The trend is unclear from 1800 to 1900.
A7: 1 | B7: 9 | C7: =_xlfn.CONCAT("M",$B$1,"_C",ChartsM45[[#This Row],[Chapter]],"_",ChartsM45[[#This Row],['#]]) -> M4_C1_9 | D7: Increasing Mineral Demand in Transport | F7: #VALUE! | G7: #VALUE! | H7: Chart to recreate | I7: Ready | J7: Zhong | K7: Mckinsey Company (2022) via International Energy Agency (2022, p. 6) | L7: https://www.mckinsey.com/industries/electric-power-and-natural-gas/our-insights/the-trading-opportunity-that-could-create-resilience-in-materials | M7: Notes: kg = kilogramme; MW = megawatt. Steel and aluminium not included. See Chapter 1 and Annex for details on the assumptions and methodologies. | N7: Yes | O7: Bar chart - Horizontal - Stacked | P7: Yes | Q7: Stacked Horizontal Bar | R7: Ready | S7: M4_C1_9 | T7: https://echarts.apache.org/examples/en/editor.html?c=bar-y-category-stack | U7: Zhong: Apache Example: https://echarts.apache.org/examples/en/editor.html?c=bar-y-category-stack Zhong: The original data points can be extracted from https://www.iea.org/data-and-statistics/charts/minerals-used-in-electric-cars-compared-to-conventional-cars ; The original data source is International Energy Agency (2022, p. 6), https://iea.blob.core.windows.net/assets/ffd2a83b-8c30-4e9d-980a-52b6d9a86fdc/TheRoleofCriticalMineralsinCleanEnergyTransitions.pdf
A8: 2 | B8: 13 | C8: =_xlfn.CONCAT("M",$B$1,"_C",ChartsM45[[#This Row],[Chapter]],"_",ChartsM45[[#This Row],['#]]) -> M4_C2_13 | D8: Annual fossil fuel subsidies by region, 2013-2023 | F8: #VALUE! | H8: Chart to recreate | I8: Pending | J8: Zhong | K8: Fossil Fuels Subsidy Tracker (2023) | L8: https://fossilfuelsubsidytracker.org/country/ | M8: Sources: OECD, IEA, IMF Disclaimer: Any data and any map included herein, are without prejudice to the status of or sovereignty over any territory, to the delimitation of international frontiers and boundaries and to the name of any territory, city or area. The dataset for 2023 is available for 83 economies, including: Angola, United Arab Emirates, Argentina, Armenia, Australia, Austria, Azerbaijan, Belgium, Bangladesh, Bahrain, Belarus, Bolivia, Brazil, Brunei Darussalam, Canada, Switzerland, Chile, People's Republic of China, Colombia, Costa Rica, Czech Republic, Germany, Denmark, Algeria, Ecuador, Egypt, Spain, Estonia, Finland, France, Gabon, United Kingdom, Georgia, Ghana, Greece, Croatia, Hungary, Indonesia, India, Ireland, Islamic Republic of Iran, Iraq, Iceland, Israel, Italy, Japan, Kazakhstan, Korea, Kuwait, Libya, Sri Lanka, Lithuania, Luxembourg, Latvia, Moldova, Mexico, Malaysia, Nigeria, Netherlands, Norway, New Zealand, Oman, Pakistan, Poland, Portugal, Qatar, Russian Federation, Saudi Arabia, El Salvador, Slovak Republic, Slovenia, Sweden, Thailand, Turkmenistan, Trinidad and Tobago, Turkey, Chinese Taipei, Ukraine, United States, Uzbekistan, Venezuela, Viet Nam, South Africa | N8: Yes | O8: Bar chart - Vertical - Grouped | P8: Yes | Q8: Simple Example of Dataset | R8: Pending | T8: https://echarts.apache.org/examples/en/editor.html?c=dataset-simple0 | U8: Zhong: Apache Example: https://echarts.apache.org/examples/en/editor.html?c=dataset-simple0 Zhong: The country level data can be downloaded from https://fossilfuelsubsidytracker.org/country/ ; After that, combining countries into different regions (e.g., Eurasia). Need to decide what defenitions of world regions (e.g., World Bank, UN) to adopt - so far we do not have this definition. Zhong: needs to explain the denifition of different regions (e.g., Eurasia, Sub-Saharan Africa). too many columns may make it diffucult to read or visualize using inclusive color palettes.
A9: 2 | B9: 16 | C9: =_xlfn.CONCAT("M",$B$1,"_C",ChartsM45[[#This Row],[Chapter]],"_",ChartsM45[[#This Row],['#]]) -> M4_C2_16 | D9: Fossil fuel consumption subsidies by fuel, 2010-2022 | F9: #VALUE! | H9: Chart to recreate | I9: Ready | J9: Divya | K9: IEA (2022) | L9: https://www.iea.org/reports/fossil-fuels-consumption-subsidies-2022 | N9: Yes | O9: Bar chart - Vertical - Simple | P9: Yes | Q9: Stacked Horizontal Bar | R9: Ready | S9: https://www.iea.org/data-and-statistics/data-product/fossil-fuel-subsidies-database | T9: https://echarts.apache.org/examples/en/editor.html?c=bar-stack | U9: Zhong: need to add data lables, especially for Coal as the small amount is unreadable.
A10: 3 | B10: 37 | C10: =_xlfn.CONCAT("M",$B$1,"_C",ChartsM45[[#This Row],[Chapter]],"_",ChartsM45[[#This Row],['#]]) -> M4_C3_37 | D10: Global investment in electricity networks in the NZE | F10: #VALUE! | H10: Chart to recreate | I10: Ready | J10: Divya | K10: IEA (2021, p.118) | L10: https://iea.blob.core.windows.net/assets/deebef5d-0c34-4539-9d0c-10b13d840027/NetZeroby2050-ARoadmapfortheGlobalEnergySector_CORR.pdf | N10: Yes | O10: Bar chart - Vertical - Stacked (animated) | P10: Yes | Q10: Basic Bar on the left and Stacked Horizontal Bar on the right | R10: Ready | S10: https://www.iea.org/product/download/008551-000293-008291 | T10: https://echarts.apache.org/examples/en/editor.html?c=bar-simple https://echarts.apache.org/examples/en/editor.html?c=bar-stack-normalization
A11: 3 | B11: 21 | C11: =_xlfn.CONCAT("M",$B$1,"_C",ChartsM45[[#This Row],[Chapter]],"_",ChartsM45[[#This Row],['#]]) -> M4_C3_21 | D11: Countries where the DREI has being implemented. | F11: #VALUE! | H11: Chart for Direct Use | U11: Zhong: the map does not provide substantial information (maybe adding the year of implementation?); the original chart/data source is unknown.
A12: 4 | B12: 30 | C12: =_xlfn.CONCAT("M",$B$1,"_C",ChartsM45[[#This Row],[Chapter]],"_",ChartsM45[[#This Row],['#]]) -> M4_C4_30 | D12: Average carbon prices in selected countries in 2021 (EUR per tonne of CO2) | F12: #VALUE! | H12: Chart to recreate | I12: Ready | J12: Divya | K12: OECD (2021) | L12: https://www.statista.com/chart/17095/highest-carbon-taxes-in-the-world/ | O12: Bar chart - Horizontal - Simple | P12: Yes | Q12: Basic Bar Vertical | R12: Ready | S12: https://data-explorer.oecd.org/share/?token=eyJ0eXAiOiJKV1QiLCJhbGciOiJIUzI1NiJ9.eyJzdWIiOiJmNmI4MzFlMS0wNDJlLTQ5YzgtYWU5Yy01Njc0YWQxMDBmZmQiLCJlbWFpbCI6ImRpdnlhc2FuZ2FyYWp1QGxpdmUuY29tIiwianRpIjoiYjQ5NzVmMmYtZGUxYS00ZTA1LWFkNmItNmI3NzhkMWYzNWMyIiwiaWF0IjoxNzQ0NzI4MTIxLCJleHAiOjE3NDQ3NDI1MjF9.2ITfhYlnPoxtGfaKJH0QYjLZMF7MAolekhbpg5Acwb8&email=divyasangaraju@live.com&id=f6b831e1-042e-49c8-ae9c-5674ad100ffd | T12: https://echarts.apache.org/examples/en/editor.html?c=bar-y-category The graph presents outdated data and mix or add several carbon pricing mechanisms that could exist. Carbon taxes may be implemented only partially, covering for instance one economic sector and not another. This could be result in misuderstanding. A more interesting approach could be to focus on carbon price in geographies with an ETS market to show differences in pricing. | U12: Zhong: consider using the most recent data (2024)
A13: 4 | B13: 32 | C13: =_xlfn.CONCAT("M",$B$1,"_C",ChartsM45[[#This Row],[Chapter]],"_",ChartsM45[[#This Row],['#]]) -> M4_C4_32 | D13: Mitigation costs in the electricity sector by policy instrument. | F13: #VALUE! | H13: Chart to recreate | I13: Ready | J13: Divya | N13: Yes | O13: Bar chart - Vertical - Simple | P13: Yes | Q13: Basic Bar Horizontal and Basic Scatter Chart | R13: Ready | T13: https://echarts.apache.org/examples/en/editor.html?c=bar-simple https://echarts.apache.org/examples/en/editor.html?c=scatter-simple Used Automeris as I couldn't find the data | U13: Zhong: the original chart/data source is unknown.
A14: 4 | B14: 33 | C14: =_xlfn.CONCAT("M",$B$1,"_C",ChartsM45[[#This Row],[Chapter]],"_",ChartsM45[[#This Row],['#]]) -> M4_C4_33 | D14: Overview of national emissions pricing (in 2019) and | F14: #VALUE! | G14: #VALUE! | H14: Chart to recreate | I14: In process | J14: Divya | K14: “World Bank Group. 2019. State and Trends of Carbon Pricing 2019. © World Bank. http://hdl.handle.net/10986/31755 License: CC BY 3.0 IGO.” | L14: https://openknowledge.worldbank.org/bitstreams/11cf8aed-1492-5c12-b2e9-27a12c8c9473/download | O14: Map - Choropleth map | P14: Yes | Q14: Geomap | R14: In process | T14: https://echarts.apache.org/examples/en/editor.html?c=map-HK | U14: Zhong: consider using a dashboard to visualize with the most recent data (2024): https://carbonpricingdashboard.worldbank.org/compliance/instrument-detail

Sheet Validation
A1: Category | C1: Charts Currently supported by the pipeline | D1: Apache Chart Types | E1: Chart type | F1: Check examples here | I1: Status Charts | J1: Status Datasets | K1: Data Viz possible
A2: Infographic WITHOUT Data | C2: Bar Chart Vertical | D2: Line | E2: Bar chart - Horizontal - Simple | I2: Pending | J2: Pending | K2: Yes
A3: Infographic WITH Data | C3: Bar Chart Horizontal | D3: Bar | E3: Bar chart - Horizontal - Simple (animated) | I3: In process | J3: In process | K3: No
A4: Chart to recreate | C4: Bar Chart Categories Horizontal | D4: Pie | E4: Bar chart - Horizontal - Grouped | I4: Not supported by pipeline | J4: Review pending | K4: Unsure
A5: Chart for Direct Use | C5: Bar Chart Categories Vertical | D5: Scatter | E5: Bar chart - Horizontal - Grouped (animated) | I5: Ready | J5: Needs fixing
A6: Maps to recreate | C6: Bar Chart Stacked Horizontal | D6: GEO/Map | E6: Bar chart - Horizontal - Stacked | I6: Deleted | J6: Ready
C7: Bar Chart Stacked Vertical | D7: Candlestick | E7: Bar chart - Horizontal - Stacked (animated) | J7: Deleted
C8: Pie Chart | D8: Radar | E8: Bar chart - Vertical - Simple
C9: Scatter Chart | D9: Boxplot | E9: Bar chart - Vertical - Simple (animated)
C10: Scatter Chart Categories | D10: Heatmap | E10: Bar chart - Vertical - Grouped
C11: Line Chart | D11: Graph | E11: Bar chart - Vertical - Grouped (animated)
C12: Line Chart Multi | D12: Line | E12: Bar chart - Vertical - Stacked
C13: Line Chart Stacked | D13: Tree | E13: Bar chart - Vertical - Stacked (animated)
D14: Treemap | E14: BeeSwarm Chart - Horizontal
D15: Sunburst | E15: BeeSwarm Chart - Vertical
D16: Parallel | E16: Butterfly chart - Static
D17: Sankey | E17: Butterfly chart - Animated
D18: Funnel | E18: Circle packing chart
D19: Gauge | E19: Data Cards
D20: PictorialBar | E20: Data table
D21: ThemeRiver | E21: Donut chart
D22: Calendar | E22: Dumbbell chart - Horizontal
D23: Custom | E23: Dumbbell chart - Horizontal (animated)
D24: Dataset | E24: Dumbbell chart - Vertical
D25: DataZoom | E25: Dumbbell chart - Vertical (animated)
... D37: Graph GL | E37: Map - Bivariate map (animated)
E38: Map - Dot density map
E39: Map - Dot density map (animated)
E40: Map - GeoHub map
E41: Map - GeoHub map with later selection
E42: Map - GeoHub compare map
E43: Pareto chart
E44: Sankey chart
E45: Scatter plot - Static
E46: Scatter plot - Animated
E47: Slope chart
E48: Stacked area chart
E49: Stat card - Simple
... E54: Unit chart
